Workbook

Sheet 使用说明
A1: 营业额自动导入 · 纯函数模板
A3: 使用方式
A5: 1. 在“营业额数据源”页，从第 4 行开始覆盖粘贴当月原稿数据；不要改动第 3 行表头。
A6: 2. 如有确认需保留的人工营业额，在“人工营业额覆盖”页维护五项键、营业额和原因。
A7: 3. 打开“各项指标明细（最终表）”：营业额列直接引用本文件数据源；新增窗口会自动追加在表格下方。
A8: 4. 打开“营业额导入核验”复核状态；点击“数据源行”可跳转到本文件内的源数据。
A9: 5. 核验通过后，使用“另存为”保存成当月目标文件。纯 Excel 函数无法自行另存为新文件。
A10: 6. 本模板不计算、不修改任何成本数据；仅管理营业额导入和核验。
A13: 环境要求：Microsoft 365 Excel（需支持 LET、XLOOKUP、FILTER、VSTACK、HSTACK、XMATCH）。

Sheet 各项指标明细（最终表）
A1: 2026年科桥餐饮公司各项指标明细
A2: 序号 | B2: 档口唯一标志 | C2: 分部名称 | D2: 项目代码 | E2: 项目名称 | F2: 项目类型 | G2: 核算会计 | H2: 分组作业名称 | I2: 分组作业窗口名称 | J2: 签订人 （会议纪要） | K2: 8月营业额 | L2: 目标值 | M2: 备注 | N2: 人员工资 | O2: 营业额指标 【部分金额折算成一年】 | P2: 服务费 | Q2: 服务费金额 | R2: 服务费项目填写当月实际金额 | S2: 服务费差异 | T2: 虫害消杀 | U2: 虫害消杀金额 | V2: 虫害消杀项目填写当月实际金额 | W2: 虫害消杀差异 | X2: 采购费 | Y2: 采购费金额 | Z2: 采购费项目填写当月实际金额 | AA2: 采购费差异 | AB2: 装修折旧 | AC2: 装修折旧金额 | AD2: 装修折旧项目填写当月实际金额 | AE2: 装修折旧差异 | AF2: 管理人员 | AG2: 管理人员金额 | AH2: 管理人员项目填写当月实际金额 | AI2: 管理人员差异 | AJ2: 共建活动 | AK2: 共建活动金额 | AL2: 共建活动项目填写当月实际金额 | AM2: 共建活动差异 | AN2: 资产 | AO2: 资产金额 | AP2: 资产项目填写当月实际金额 | AQ2: 资产差异 | AR2: 卫生费 | AS2: 卫生费金额 | AT2: 卫生费项目填写当月实际金额 | AU2: 卫生费差异 | AV2: 能源费 | AW2: 能源费金额 | AX2: 能源费项目填写当月实际金额 | AY2: 能源费差异 | AZ2: 其他 | BA2: 其他金额 | BB2: 其他项目填写当月实际金额米饭差价 | BC2: 其他差异 | BD2: 其他费用1 | BE2: 其他费用1金额 | BF2: 其他费用1项目填写当月实际金额 | BG2: 其他费用1差异 | BH2: 其他费用2 | BI2: 其他费用2金额 | BJ2: 其他费用2项目填写当月实际金额 | BK2: 其他费用2差异 | BL2: 原材料比例 | BM2: 原材料金额 | BN2: 原材料项目填写当月实际金额 | BO2: 原材料差异 | BP2: 成本费用合计金额 | BQ2: 项目填写成本费用合计 | BR2: 差异合计 | BS2: 分部管理费 （按实+固定值） | BT2: 业务费 | BU2: 备注1 | BV2: 备注2
A3: 4 | B3: KQCY0004 | C3: 餐饮一分部 | D3: CF751 | E3: 国防科大（长沙）食堂 | F3: 人员服务外包 | G3: 徐敏捷 | H3: / | I3: / | J3: / | K3: =LET(k,D3&"|"&E3&"|"&H3&"|"&I3&"|"&J3,sk,tblRevenueInput[项目代码]&"|"&tblRevenueInput[项目名称]&"|"&tblRevenueInput[分组作业名称]&"|"&tblRevenueInput[分组作业窗口名称]&"|"&tblRevenueInput[签订人],ok,tblRevenueOverride[项目代码]&"|"&tblRevenueOverride[项目名称]&"|"&tblRevenueOverride[分组作业名称]&"|"&tblRevenueOverride[分组作业窗口名称]&"|"&tblRevenueOverride[责任人],ov,IFERROR(XLOOKUP(k,ok,tblRevenueOverride[营业额覆盖],""),""),IF(ov<>"",ov,IFERROR(XLOOKUP(k,sk,tblRevenueInput[全额营业额合计],""),""))) | O3: 8931000 | P3: 0 | Q3: =K3*P3 | S3: =Q3-R3 | T3: 0 | U3: =K3*T3 | W3: =U3-V3 | X3: 0 | Y3: =K3*X3 | AA3: =Y3-Z3 | AB3: 0 | AC3: =K3*AB3 | AE3: =AC3-AD3 | AF3: 0 | AG3: =K3*AF3 | AI3: =AG3-AH3 | AJ3: 0 | AK3: =K3*AJ3 | AM3: =AK3-AL3 | AN3: 0 | AO3: =K3*AN3 | AQ3: =AO3-AP3 | AR3: 0 | AS3: =K3*AR3 | AU3: =AS3-AT3 | AV3: 0 | AW3: =K3*AV3 | AY3: =AW3-AX3 | AZ3: 0 | BA3: =K3*AZ3 | BC3: =BA3-BB3 | BE3: =K3*BD3 | BG3: =BE3-BF3 | BI3: =K3*BH3 | BK3: =BI3-BJ3 | BL3: 0 | BM3: =K3*BL3 | BO3: =BM3-BN3 | BP3: =N3+Q3+U3+Y3+AC3+AG3+AK3+AO3+AS3+AW3+BA3+BE3+BI3+BM3 | BQ3: =N3+R3+V3+Z3+AD3+AH3+AL3+AP3+AT3+AX3+BB3+BF3+BJ3+BN3 | BR3: =BP3-BQ3 | BS3: 0.045 | BT3: /
A4: 6 | B4: KQCY0006 | C4: 餐饮一分部 | D4: CF474 | E4: 安工大七食堂 | F4: 强责 | G4: 卫屹 | H4: 第一班组 | I4: 手工馄饨（大陷水饺、刀削面/汆肉米线） | J4: 潘海英 | K4: =LET(k,D4&"|"&E4&"|"&H4&"|"&I4&"|"&J4,sk,tblRevenueInput[项目代码]&"|"&tblRevenueInput[项目名称]&"|"&tblRevenueInput[分组作业名称]&"|"&tblRevenueInput[分组作业窗口名称]&"|"&tblRevenueInput[签订人],ok,tblRevenueOverride[项目代码]&"|"&tblRevenueOverride[项目名称]&"|"&tblRevenueOverride[分组作业名称]&"|"&tblRevenueOverride[分组作业窗口名称]&"|"&tblRevenueOverride[责任人],ov,IFERROR(XLOOKUP(k,ok,tblRevenueOverride[营业额覆盖],""),""),IF(ov<>"",ov,IFERROR(XLOOKUP(k,sk,tblRevenueInput[全额营业额合计],""),""))) | O4: 700000 | P4: 0.07 | Q4: =K4*P4 | S4: =Q4-R4 | T4: 0.01 | U4: =K4*T4 | W4: =U4-V4 | X4: 0 | Y4: =K4*X4 | AA4: =Y4-Z4 | AB4: 0.03 | AC4: =K4*AB4 | AE4: =AC4-AD4 | AF4: 0.03 | AG4: =K4*AF4 | AI4: =AG4-AH4 | AJ4: 0.01 | AK4: =K4*AJ4 | AM4: =AK4-AL4 | AN4: 0.02 | AO4: =K4*AN4 | AQ4: =AO4-AP4 | AR4: 0.04 | AS4: =K4*AR4 | AU4: =AS4-AT4 | AV4: 0.05 | AW4: =K4*AV4 | AY4: =AW4-AX4 | AZ4: 按实 | BA4: =BB4 | BC4: =BA4-BB4 | BD4: 0 | BE4: =K4*BD4 | BG4: =BE4-BF4 | BH4: 0 | BI4: =K4*BH4 | BK4: =BI4-BJ4 | BL4: 按实 | BM4: =BN4 | BO4: =BM4-BN4 | BP4: =N4+Q4+U4+Y4+AC4+AG4+AK4+AO4+AS4+AW4+BA4+BE4+BI4+BM4 | BQ4: =N4+R4+V4+Z4+AD4+AH4+AL4+AP4+AT4+AX4+BB4+BF4+BJ4+BN4 | BR4: =BP4-BQ4 | BS4: / | BT4: / | BU4: 1、甲方管理费：乙方自愿向甲方缴纳考核奖励资金，费用金额为29.5万元/年。一年按照10个月计算(2、8月份不计)，每月从餐厅营业款中扣除。服务费包含未拆分 2、甲方捐赠：助学基金5000元。服务费包含未拆分 3、原材料：安徽工业大学食堂食品原材料定点采购办法约定食品原材料≥55%营业额（不含一次性打包用品）
A5: 7 | B5: KQCY0007 | C5: 餐饮一分部 | D5: CF474 | E5: 安工大七食堂 | F5: 强责 | G5: 卫屹 | H5: 第二班组 | I5: 黄焖系列（酸菜肉煲系列、椒麻鸡系列、酸菜鱼系列） | J5: 胡科才 | K5: =LET(k,D5&"|"&E5&"|"&H5&"|"&I5&"|"&J5,sk,tblRevenueInput[项目代码]&"|"&tblRevenueInput[项目名称]&"|"&tblRevenueInput[分组作业名称]&"|"&tblRevenueInput[分组作业窗口名称]&"|"&tblRevenueInput[签订人],ok,tblRevenueOverride[项目代码]&"|"&tblRevenueOverride[项目名称]&"|"&tblRevenueOverride[分组作业名称]&"|"&tblRevenueOverride[分组作业窗口名称]&"|"&tblRevenueOverride[责任人],ov,IFERROR(XLOOKUP(k,ok,tblRevenueOverride[营业额覆盖],""),""),IF(ov<>"",ov,IFERROR(XLOOKUP(k,sk,tblRevenueInput[全额营业额合计],""),""))) | O5: 500000 | P5: 0.07 | Q5: =K5*P5 | S5: =Q5-R5 | T5: 0.01 | U5: =K5*T5 | W5: =U5-V5 | X5: 0 | Y5: =K5*X5 | AA5: =Y5-Z5 | AB5: 0.03 | AC5: =K5*AB5 | AE5: =AC5-AD5 | AF5: 0.03 | AG5: =K5*AF5 | AI5: =AG5-AH5 | AJ5: 0.01 | AK5: =K5*AJ5 | AM5: =AK5-AL5 | AN5: 0.02 | AO5: =K5*AN5 | AQ5: =AO5-AP5 | AR5: 0.04 | AS5: =K5*AR5 | AU5: =AS5-AT5 | AV5: 0.05 | AW5: =K5*AV5 | AY5: =AW5-AX5 | AZ5: 按实 | BA5: =BB5 | BC5: =BA5-BB5 | BD5: 0 | BE5: =K5*BD5 | BG5: =BE5-BF5 | BH5: 0 | BI5: =K5*BH5 | BK5: =BI5-BJ5 | BL5: 按实 | BM5: =BN5 | BO5: =BM5-BN5 | BP5: =N5+Q5+U5+Y5+AC5+AG5+AK5+AO5+AS5+AW5+BA5+BE5+BI5+BM5 | BQ5: =N5+R5+V5+Z5+AD5+AH5+AL5+AP5+AT5+AX5+BB5+BF5+BJ5+BN5 | BR5: =BP5-BQ5 | BS5: / | BT5: / | BU5: 1、甲方管理费：乙方自愿向甲方缴纳考核奖励资金，费用金额为29.5万元/年。一年按照10个月计算(2、8月份不计)，每月从餐厅营业款中扣除。服务费包含未拆分 2、甲方捐赠：助学基金5000元。服务费包含未拆分 3、原材料：安徽工业大学食堂食品原材料定点采购办法约定食品原材料≥55%营业额（不含一次性打包用品）
A6: 8 | B6: KQCY0008 | C6: 餐饮一分部 | D6: CF474 | E6: 安工大七食堂 | F6: 强责 | G6: 卫屹 | H6: 第三班组 | I6: 猪脚饭系列（套饭系列、菜饭骨头汤系列） | J6: 杨克顺 | K6: =LET(k,D6&"|"&E6&"|"&H6&"|"&I6&"|"&J6,sk,tblRevenueInput[项目代码]&"|"&tblRevenueInput[项目名称]&"|"&tblRevenueInput[分组作业名称]&"|"&tblRevenueInput[分组作业窗口名称]&"|"&tblRevenueInput[签订人],ok,tblRevenueOverride[项目代码]&"|"&tblRevenueOverride[项目名称]&"|"&tblRevenueOverride[分组作业名称]&"|"&tblRevenueOverride[分组作业窗口名称]&"|"&tblRevenueOverride[责任人],ov,IFERROR(XLOOKUP(k,ok,tblRevenueOverride[营业额覆盖],""),""),IF(ov<>"",ov,IFERROR(XLOOKUP(k,sk,tblRevenueInput[全额营业额合计],""),""))) | N6: 3866 | O6: 700000 | P6: 0.07 | Q6: =K6*P6 | S6: =Q6-R6 | T6: 0.01 | U6: =K6*T6 | W6: =U6-V6 | X6: 0 | Y6: =K6*X6 | AA6: =Y6-Z6 | AB6: 0.03 | AC6: =K6*AB6 | AE6: =AC6-AD6 | AF6: 0.03 | AG6: =K6*AF6 | AI6: =AG6-AH6 | AJ6: 0.01 | AK6: =K6*AJ6 | AM6: =AK6-AL6 | AN6: 0.02 | AO6: =K6*AN6 | AQ6: =AO6-AP6 | AR6: 0.04 | AS6: =K6*AR6 | AU6: =AS6-AT6 | AV6: 0.05 | AW6: =K6*AV6 | AY6: =AW6-AX6 | AZ6: 按实 | BA6: =BB6 | BC6: =BA6-BB6 | BD6: 0 | BE6: =K6*BD6 | BG6: =BE6-BF6 | BH6: 0 | BI6: =K6*BH6 | BK6: =BI6-BJ6 | BL6: 按实 | BM6: =BN6 | BO6: =BM6-BN6 | BP6: =N6+Q6+U6+Y6+AC6+AG6+AK6+AO6+AS6+AW6+BA6+BE6+BI6+BM6 | BQ6: =N6+R6+V6+Z6+AD6+AH6+AL6+AP6+AT6+AX6+BB6+BF6+BJ6+BN6 | BR6: =BP6-BQ6 | BS6: / | BT6: / | BU6: 1、甲方管理费：乙方自愿向甲方缴纳考核奖励资金，费用金额为29.5万元/年。一年按照10个月计算(2、8月份不计)，每月从餐厅营业款中扣除。服务费包含未拆分 2、甲方捐赠：助学基金5000元。服务费包含未拆分 3、原材料：安徽工业大学食堂食品原材料定点采购办法约定食品原材料≥55%营业额（不含一次性打包用品）
A7: 9 | B7: KQCY0009 | C7: 餐饮一分部 | D7: CF474 | E7: 安工大七食堂 | F7: 强责 | G7: 卫屹 | H7: 第四班组 | I7: 拌饭系列（肉夹馍、紫菜包饭） | J7: 魏祖华 | K7: =LET(k,D7&"|"&E7&"|"&H7&"|"&I7&"|"&J7,sk,tblRevenueInput[项目代码]&"|"&tblRevenueInput[项目名称]&"|"&tblRevenueInput[分组作业名称]&"|"&tblRevenueInput[分组作业窗口名称]&"|"&tblRevenueInput[签订人],ok,tblRevenueOverride[项目代码]&"|"&tblRevenueOverride[项目名称]&"|"&tblRevenueOverride[分组作业名称]&"|"&tblRevenueOverride[分组作业窗口名称]&"|"&tblRevenueOverride[责任人],ov,IFERROR(XLOOKUP(k,ok,tblRevenueOverride[营业额覆盖],""),""),IF(ov<>"",ov,IFERROR(XLOOKUP(k,sk,tblRevenueInput[全额营业额合计],""),""))) | O7: 700000 | P7: 0.07 | Q7: =K7*P7 | R7: 279.09 | S7: =Q7-R7 | T7: 0.01 | U7: =K7*T7 | V7: 39.87 | W7: =U7-V7 | X7: 0 | Y7: =K7*X7 | Z7: 0 | AA7: =Y7-Z7 | AB7: 0.03 | AC7: =K7*AB7 | AD7: 119.61 | AE7: =AC7-AD7 | AF7: 0.03 | AG7: =K7*AF7 | AH7: 119.61 | AI7: =AG7-AH7 | AJ7: 0.01 | AK7: =K7*AJ7 | AL7: 39.87 | AM7: =AK7-AL7 | AN7: 0.02 | AO7: =K7*AN7 | AP7: 79.74 | AQ7: =AO7-AP7 | AR7: 0.04 | AS7: =K7*AR7 | AT7: 159.48 | AU7: =AS7-AT7 | AV7: 0.05 | AW7: =K7*AV7 | AX7: 199.35 | AY7: =AW7-AX7 | AZ7: 按实 | BA7: =BB7 | BB7: 0 | BC7: =BA7-BB7 | BD7: 0 | BE7: =K7*BD7 | BF7: 0 | BG7: =BE7-BF7 | BH7: 0 | BI7: =K7*BH7 | BJ7: 0 | BK7: =BI7-BJ7 | BL7: 按实 | BM7: =BN7 | BN7: 0 | BO7: =BM7-BN7 | BP7: =N7+Q7+U7+Y7+AC7+AG7+AK7+AO7+AS7+AW7+BA7+BE7+BI7+BM7 | BQ7: =N7+R7+V7+Z7+AD7+AH7+AL7+AP7+AT7+AX7+BB7+BF7+BJ7+BN7 | BR7: =BP7-BQ7 | BS7: / | BT7: / | BU7: 1、甲方管理费：乙方自愿向甲方缴纳考核奖励资金，费用金额为29.5万元/年。一年按照10个月计算(2、8月份不计)，每月从餐厅营业款中扣除。服务费包含未拆分 2、甲方捐赠：助学基金5000元。服务费包含未拆分 3、原材料：安徽工业大学食堂食品原材料定点采购办法约定食品原材料≥55%营业额（不含一次性打包用品）
A8: 11 | B8: KQCY0011 | C8: 餐饮一分部 | D8: CF477 | E8: 上海民航第一食堂 | F8: 分组作业 | G8: 卫屹 | H8: 第二班组 | I8: 山东煎饼 | J8: 姚群 | K8: =LET(k,D8&"|"&E8&"|"&H8&"|"&I8&"|"&J8,sk,tblRevenueInput[项目代码]&"|"&tblRevenueInput[项目名称]&"|"&tblRevenueInput[分组作业名称]&"|"&tblRevenueInput[分组作业窗口名称]&"|"&tblRevenueInput[签订人],ok,tblRevenueOverride[项目代码]&"|"&tblRevenueOverride[项目名称]&"|"&tblRevenueOverride[分组作业名称]&"|"&tblRevenueOverride[分组作业窗口名称]&"|"&tblRevenueOverride[责任人],ov,IFERROR(XLOOKUP(k,ok,tblRevenueOverride[营业额覆盖],""),""),IF(ov<>"",ov,IFERROR(XLOOKUP(k,sk,tblRevenueInput[全额营业额合计],""),""))) | O8: 570000 | P8: 0.1 | Q8: =K8*P8 | S8: =Q8-R8 | T8: 0.03 | U8: =K8*T8 | W8: =U8-V8 | X8: 0 | Y8: =K8*X8 | AA8: =Y8-Z8 | AB8: 0.05 | AC8: =K8*AB8 | AE8: =AC8-AD8 | AF8: 0.02 | AG8: =K8*AF8 | AI8: =AG8-AH8 | AJ8: 0 | AK8: =K8*AJ8 | AM8: =AK8-AL8 | AN8: 0.03 | AO8: =K8*AN8 | AQ8: =AO8-AP8 | AR8: 0 | AS8: =K8*AR8 | AU8: =AS8-AT8 | AV8: 0.04 | AW8: =K8*AV8 | AY8: =AW8-AX8 | AZ8: 按实 | BA8: =BB8 | BC8: =BA8-BB8 | BD8: 0 | BE8: =K8*BD8 | BG8: =BE8-BF8 | BH8: 0 | BI8: =K8*BH8 | BK8: =BI8-BJ8 | BL8: 按实 | BM8: =BN8 | BO8: =BM8-BN8 | BP8: =N8+Q8+U8+Y8+AC8+AG8+AK8+AO8+AS8+AW8+BA8+BE8+BI8+BM8 | BQ8: =N8+R8+V8+Z8+AD8+AH8+AL8+AP8+AT8+AX8+BB8+BF8+BJ8+BN8 | BR8: =BP8-BQ8 | BS8: / | BT8: / | BU8: 1、服务费：包含卫生费，不单独分摊
A9: 12 | B9: KQCY0012 | C9: 餐饮一分部 | D9: CF477 | E9: 上海民航第一食堂 | F9: 分组作业 | G9: 卫屹 | H9: 第六班组 | I9: 蜜雪冰城 | J9: 任黎明 | K9: =LET(k,D9&"|"&E9&"|"&H9&"|"&I9&"|"&J9,sk,tblRevenueInput[项目代码]&"|"&tblRevenueInput[项目名称]&"|"&tblRevenueInput[分组作业名称]&"|"&tblRevenueInput[分组作业窗口名称]&"|"&tblRevenueInput[签订人],ok,tblRevenueOverride[项目代码]&"|"&tblRevenueOverride[项目名称]&"|"&tblRevenueOverride[分组作业名称]&"|"&tblRevenueOverride[分组作业窗口名称]&"|"&tblRevenueOverride[责任人],ov,IFERROR(XLOOKUP(k,ok,tblRevenueOverride[营业额覆盖],""),""),IF(ov<>"",ov,IFERROR(XLOOKUP(k,sk,tblRevenueInput[全额营业额合计],""),""))) | O9: 899800 | P9: 0 | Q9: =K9*P9 | S9: =Q9-R9 | T9: 0 | U9: =K9*T9 | W9: =U9-V9 | X9: 0 | Y9: =K9*X9 | AA9: =Y9-Z9 | AB9: 0 | AC9: =K9*AB9 | AE9: =AC9-AD9 | AF9: 0 | AG9: =K9*AF9 | AI9: =AG9-AH9 | AJ9: 0 | AK9: =K9*AJ9 | AM9: =AK9-AL9 | AN9: 0 | AO9: =K9*AN9 | AQ9: =AO9-AP9 | AR9: 0 | AS9: =K9*AR9 | AU9: =AS9-AT9 | AV9: 0 | AW9: =K9*AV9 | AY9: =AW9-AX9 | AZ9: 按实 | BA9: =BB9 | BC9: =BA9-BB9 | BD9: 16万元/年，3月-9月、9月-12月分8个月收取，每月收取20000元 | BE9: =BF9 | BF9: 0 | BG9: =BE9-BF9 | BH9: 0 | BI9: =K9*BH9 | BK9: =BI9-BJ9 | BL9: 按实 | BM9: =BN9 | BO9: =BM9-BN9 | BP9: =N9+Q9+U9+Y9+AC9+AG9+AK9+AO9+AS9+AW9+BA9+BE9+BI9+BM9 | BQ9: =N9+R9+V9+Z9+AD9+AH9+AL9+AP9+AT9+AX9+BB9+BF9+BJ9+BN9 | BR9: =BP9-BQ9 | BS9: / | BT9: / | BU9: 1、其他：固定资金16万元/年，3月-9月、9月-12月分8个月收取，每月收取20000元
A10: 13 | B10: KQCY0013 | C10: 餐饮一分部 | D10: CF477 | E10: 上海民航第一食堂 | F10: 分组作业 | G10: 卫屹 | H10: 第三班组 | I10: 糖水粥铺 | J10: 孙青青 | K10: =LET(k,D10&"|"&E10&"|"&H10&"|"&I10&"|"&J10,sk,tblRevenueInput[项目代码]&"|"&tblRevenueInput[项目名称]&"|"&tblRevenueInput[分组作业名称]&"|"&tblRevenueInput[分组作业窗口名称]&"|"&tblRevenueInput[签订人],ok,tblRevenueOverride[项目代码]&"|"&tblRevenueOverride[项目名称]&"|"&tblRevenueOverride[分组作业名称]&"|"&tblRevenueOverride[分组作业窗口名称]&"|"&tblRevenueOverride[责任人],ov,IFERROR(XLOOKUP(k,ok,tblRevenueOverride[营业额覆盖],""),""),IF(ov<>"",ov,IFERROR(XLOOKUP(k,sk,tblRevenueInput[全额营业额合计],""),""))) | O10: 449900 | P10: 0.1 | Q10: =K10*P10 | S10: =Q10-R10 | T10: 0.03 | U10: =K10*T10 | W10: =U10-V10 | X10: 0 | Y10: =K10*X10 | AA10: =Y10-Z10 | AB10: 0.05 | AC10: =K10*AB10 | AE10: =AC10-AD10 | AF10: 0.02 | AG10: =K10*AF10 | AI10: =AG10-AH10 | AJ10: 0 | AK10: =K10*AJ10 | AM10: =AK10-AL10 | AN10: 0.03 | AO10: =K10*AN10 | AQ10: =AO10-AP10 | AR10: 0 | AS10: =K10*AR10 | AU10: =AS10-AT10 | AV10: 0.04 | AW10: =K10*AV10 | AY10: =AW10-AX10 | AZ10: 按实 | BA10: =BB10 | BC10: =BA10-BB10 | BD10: 0 | BE10: =K10*BD10 | BG10: =BE10-BF10 | BH10: 0 | BI10: =K10*BH10 | BK10: =BI10-BJ10 | BL10: 按实 | BM10: =BN10 | BO10: =BM10-BN10 | BP10: =N10+Q10+U10+Y10+AC10+AG10+AK10+AO10+AS10+AW10+BA10+BE10+BI10+BM10 | BQ10: =N10+R10+V10+Z10+AD10+AH10+AL10+AP10+AT10+AX10+BB10+BF10+BJ10+BN10 | BR10: =BP10-BQ10 | BS10: / | BT10: / | BU10: 1、服务费：包含卫生费，不单独分摊
A11: 14 | B11: KQCY0014 | C11: 餐饮一分部 | D11: CF477 | E11: 上海民航第一食堂 | F11: 分组作业 | G11: 卫屹 | H11: 第四班组 | I11: 大碗面 | J11: 景帅帅 | K11: =LET(k,D11&"|"&E11&"|"&H11&"|"&I11&"|"&J11,sk,tblRevenueInput[项目代码]&"|"&tblRevenueInput[项目名称]&"|"&tblRevenueInput[分组作业名称]&"|"&tblRevenueInput[分组作业窗口名称]&"|"&tblRevenueInput[签订人],ok,tblRevenueOverride[项目代码]&"|"&tblRevenueOverride[项目名称]&"|"&tblRevenueOverride[分组作业名称]&"|"&tblRevenueOverride[分组作业窗口名称]&"|"&tblRevenueOverride[责任人],ov,IFERROR(XLOOKUP(k,ok,tblRevenueOverride[营业额覆盖],""),""),IF(ov<>"",ov,IFERROR(XLOOKUP(k,sk,tblRevenueInput[全额营业额合计],""),""))) | N11: 20030.94 | O11: 486500 | P11: 0.1 | Q11: =K11*P11 | S11: =Q11-R11 | T11: 0.03 | U11: =K11*T11 | V11: 0 | W11: =U11-V11 | X11: 0 | Y11: =K11*X11 | Z11: 0 | AA11: =Y11-Z11 | AB11: 0.05 | AC11: =K11*AB11 | AD11: 0 | AE11: =AC11-AD11 | AF11: 0.02 | AG11: =K11*AF11 | AH11: 0 | AI11: =AG11-AH11 | AJ11: 0 | AK11: =K11*AJ11 | AL11: 0 | AM11: =AK11-AL11 | AN11: 0.03 | AO11: =K11*AN11 | AP11: 0 | AQ11: =AO11-AP11 | AR11: 0 | AS11: =K11*AR11 | AT11: 0 | AU11: =AS11-AT11 | AV11: 0.04 | AW11: =K11*AV11 | AX11: 0 | AY11: =AW11-AX11 | AZ11: 按实 | BA11: =BB11 | BB11: 0 | BC11: =BA11-BB11 | BD11: 0 | BE11: =K11*BD11 | BF11: 0 | BG11: =BE11-BF11 | BH11: 0 | BI11: =K11*BH11 | BJ11: 0 | BK11: =BI11-BJ11 | BL11: 按实 | BM11: =BN11 | BN11: 0 | BO11: =BM11-BN11 | BP11: =N11+Q11+U11+Y11+AC11+AG11+AK11+AO11+AS11+AW11+BA11+BE11+BI11+BM11 | BQ11: =N11+R11+V11+Z11+AD11+AH11+AL11+AP11+AT11+AX11+BB11+BF11+BJ11+BN11 | BR11: =BP11-BQ11 | BS11: / | BT11: / | BU11: 1、服务费：包含卫生费，不单独分摊
A12: 15 | B12: KQCY0015 | C12: 餐饮一分部 | D12: CF477 | E12: 上海民航第一食堂 | F12: 分组作业 | G12: 卫屹 | H12: 第一班组 | I12: 早餐 | J12: 芦磊 | K12: =LET(k,D12&"|"&E12&"|"&H12&"|"&I12&"|"&J12,sk,tblRevenueInput[项目代码]&"|"&tblRevenueInput[项目名称]&"|"&tblRevenueInput[分组作业名称]&"|"&tblRevenueInput[分组作业窗口名称]&"|"&tblRevenueInput[签订人],ok,tblRevenueOverride[项目代码]&"|"&tblRevenueOverride[项目名称]&"|"&tblRevenueOverride[分组作业名称]&"|"&tblRevenueOverride[分组作业窗口名称]&"|"&tblRevenueOverride[责任人],ov,IFERROR(XLOOKUP(k,ok,tblRevenueOverride[营业额覆盖],""),""),IF(ov<>"",ov,IFERROR(XLOOKUP(k,sk,tblRevenueInput[全额营业额合计],""),""))) | O12: 628600 | P12: 0.1 | Q12: =K12*P12 | R12: 0 | S12: =Q12-R12 | T12: 0.03 | U12: =K12*T12 | W12: =U12-V12 | X12: 0 | Y12: =K12*X12 | AA12: =Y12-Z12 | AB12: 0.05 | AC12: =K12*AB12 | AE12: =AC12-AD12 | AF12: 0.02 | AG12: =K12*AF12 | AI12: =AG12-AH12 | AJ12: 0 | AK12: =K12*AJ12 | AM12: =AK12-AL12 | AN12: 0.03 | AO12: =K12*AN12 | AQ12: =AO12-AP12 | AR12: 0 | AS12: =K12*AR12 | AU12: =AS12-AT12 | AV12: 0 | AW12: =K12*AV12 | AY12: =AW12-AX12 | AZ12: 按实 | BA12: =BB12 | BC12: =BA12-BB12 | BD12: 0 | BE12: =K12*BD12 | BG12: =BE12-BF12 | BH12: 0 | BI12: =K12*BH12 | BK12: =BI12-BJ12 | BL12: 按实 | BM12: =BN12 | BO12: =BM12-BN12 | BP12: =N12+Q12+U12+Y12+AC12+AG12+AK12+AO12+AS12+AW12+BA12+BE12+BI12+BM12 | BQ12: =N12+R12+V12+Z12+AD12+AH12+AL12+AP12+AT12+AX12+BB12+BF12+BJ12+BN12 | BR12: =BP12-BQ12 | BS12: / | BT12: / | BU12: 1、服务费：包含卫生费、能源费，不单独分摊
A13: 16 | B13: KQCY0016 | C13: 餐饮一分部 | D13: CF272 | E13: 苏州工学院南一食堂 | F13: 强责 | G13: 郑虎 | H13: / | I13: / | J13: / | K13: =LET(k,D13&"|"&E13&"|"&H13&"|"&I13&"|"&J13,sk,tblRevenueInput[项目代码]&"|"&tblRevenueInput[项目名称]&"|"&tblRevenueInput[分组作业名称]&"|"&tblRevenueInput[分组作业窗口名称]&"|"&tblRevenueInput[签订人],ok,tblRevenueOverride[项目代码]&"|"&tblRevenueOverride[项目名称]&"|"&tblRevenueOverride[分组作业名称]&"|"&tblRevenueOverride[分组作业窗口名称]&"|"&tblRevenueOverride[责任人],ov,IFERROR(XLOOKUP(k,ok,tblRevenueOverride[营业额覆盖],""),""),IF(ov<>"",ov,IFERROR(XLOOKUP(k,sk,tblRevenueInput[全额营业额合计],""),""))) | O13: 0 | P13: 0 | Q13: =K13*P13 | S13: =Q13-R13 | U13: =K13*T13 | W13: =U13-V13 | Y13: =K13*X13 | AA13: =Y13-Z13 | AC13: =K13*AB13 | AE13: =AC13-AD13 | AF13: 0 | AG13: =K13*AF13 | AI13: =AG13-AH13 | AJ13: 0 | AK13: =K13*AJ13 | AM13: =AK13-AL13 | AN13: 0 | AO13: =K13*AN13 | AQ13: =AO13-AP13 | AS13: =K13*AR13 | AU13: =AS13-AT13 | AW13: =K13*AV13 | AY13: =AW13-AX13 | BA13: =K13*AZ13 | BC13: =BA13-BB13 | BE13: =K13*BD13 | BG13: =BE13-BF13 | BI13: =K13*BH13 | BK13: =BI13-BJ13 | BM13: =K13*BL13 | BO13: =BM13-BN13 | BP13: =N13+Q13+U13+Y13+AC13+AG13+AK13+AO13+AS13+AW13+BA13+BE13+BI13+BM13 | BQ13: =N13+R13+V13+Z13+AD13+AH13+AL13+AP13+AT13+AX13+BB13+BF13+BJ13+BN13 | BR13: =BP13-BQ13 | BS13: 0.02 | BT13: / | BU13: 1、自营未实际经营；
A14: 17 | B14: KQCY0017 | C14: 餐饮一分部 | D14: CF272 | E14: 苏州工学院南一食堂 | F14: 强责 | G14: 郑虎 | H14: / | I14: 饼铺 | J14: 纪洪强 | K14: =LET(k,D14&"|"&E14&"|"&H14&"|"&I14&"|"&J14,sk,tblRevenueInput[项目代码]&"|"&tblRevenueInput[项目名称]&"|"&tblRevenueInput[分组作业名称]&"|"&tblRevenueInput[分组作业窗口名称]&"|"&tblRevenueInput[签订人],ok,tblRevenueOverride[项目代码]&"|"&tblRevenueOverride[项目名称]&"|"&tblRevenueOverride[分组作业名称]&"|"&tblRevenueOverride[分组作业窗口名称]&"|"&tblRevenueOverride[责任人],ov,IFERROR(XLOOKUP(k,ok,tblRevenueOverride[营业额覆盖],""),""),IF(ov<>"",ov,IFERROR(XLOOKUP(k,sk,tblRevenueInput[全额营业额合计],""),""))) | N14: 1698.59 | O14: 460000 | P14: 0.08 | Q14: =K14*P14 | R14: 444.3624 | S14: =Q14-R14 | T14: 0 | U14: =K14*T14 | W14: =U14-V14 | X14: 0 | Y14: =K14*X14 | AA14: =Y14-Z14 | AB14: 0.065 | AC14: =K14*AB14 | AD14: 361.04445 | AE14: =AC14-AD14 | AF14: 0.02 | AG14: =K14*AF14 | AH14: 111.0906 | AI14: =AG14-AH14 | AJ14: 0.035 | AK14: =K14*AJ14 | AL14: 194.40855 | AM14: =AK14-AL14 | AN14: 0 | AO14: =K14*AN14 | AQ14: =AO14-AP14 | AR14: 0.03 | AS14: =K14*AR14 | AT14: 166.6359 | AU14: =AS14-AT14 | AV14: 0.06 | AW14: =K14*AV14 | AX14: 333.2718 | AY14: =AW14-AX14 | AZ14: 按实 | BA14: =BB14 | BC14: =BA14-BB14 | BD14: 按实 | BE14: =BF14 | BG14: =BE14-BF14 | BH14: 按实 | BI14: =BJ14 | BK14: =BI14-BJ14 | BL14: 按实 | BM14: =BN14 | BO14: =BM14-BN14 | BP14: =N14+Q14+U14+Y14+AC14+AG14+AK14+AO14+AS14+AW14+BA14+BE14+BI14+BM14 | BQ14: =N14+R14+V14+Z14+AD14+AH14+AL14+AP14+AT14+AX14+BB14+BF14+BJ14+BN14 | BR14: =BP14-BQ14 | BS14: / | BT14: / | BU14: 1、甲方捐赠：35万/年，分组作业未分摊，服务费已包含； 2、采购费：1.35万/年，分组作业未分摊，服务费已包含； | BV14: 1、签订期间：2026.2.25-2026.7.19； 2、指标按照全年换算；
A15: 18 | B15: KQCY0018 | C15: 餐饮一分部 | D15: CF272 | E15: 苏州工学院南一食堂 | F15: 强责 | G15: 郑虎 | H15: / | I15: 粥铺 | J15: 贺明 | K15: =LET(k,D15&"|"&E15&"|"&H15&"|"&I15&"|"&J15,sk,tblRevenueInput[项目代码]&"|"&tblRevenueInput[项目名称]&"|"&tblRevenueInput[分组作业名称]&"|"&tblRevenueInput[分组作业窗口名称]&"|"&tblRevenueInput[签订人],ok,tblRevenueOverride[项目代码]&"|"&tblRevenueOverride[项目名称]&"|"&tblRevenueOverride[分组作业名称]&"|"&tblRevenueOverride[分组作业窗口名称]&"|"&tblRevenueOverride[责任人],ov,IFERROR(XLOOKUP(k,ok,tblRevenueOverride[营业额覆盖],""),""),IF(ov<>"",ov,IFERROR(XLOOKUP(k,sk,tblRevenueInput[全额营业额合计],""),""))) | N15: 1698.59 | O15: 384000 | P15: 0.08 | Q15: =K15*P15 | R15: 417.92 | S15: =Q15-R15 | T15: 0 | U15: =K15*T15 | W15: =U15-V15 | X15: 0 | Y15: =K15*X15 | AA15: =Y15-Z15 | AB15: 0.065 | AC15: =K15*AB15 | AD15: 339.56 | AE15: =AC15-AD15 | AF15: 0.02 | AG15: =K15*AF15 | AH15: 104.48 | AI15: =AG15-AH15 | AJ15: 0.035 | AK15: =K15*AJ15 | AL15: 182.84 | AM15: =AK15-AL15 | AN15: 0 | AO15: =K15*AN15 | AQ15: =AO15-AP15 | AR15: 0.03 | AS15: =K15*AR15 | AT15: 156.72 | AU15: =AS15-AT15 | AV15: 0.06 | AW15: =K15*AV15 | AX15: 313.44 | AY15: =AW15-AX15 | AZ15: 按实 | BA15: =BB15 | BC15: =BA15-BB15 | BD15: 按实 | BE15: =BF15 | BG15: =BE15-BF15 | BH15: 按实 | BI15: =BJ15 | BK15: =BI15-BJ15 | BL15: 按实 | BM15: =BN15 | BO15: =BM15-BN15 | BP15: =N15+Q15+U15+Y15+AC15+AG15+AK15+AO15+AS15+AW15+BA15+BE15+BI15+BM15 | BQ15: =N15+R15+V15+Z15+AD15+AH15+AL15+AP15+AT15+AX15+BB15+BF15+BJ15+BN15 | BR15: =BP15-BQ15 | BS15: / | BT15: / | BU15: 1、甲方捐赠：35万/年，分组作业未分摊，服务费已包含； 2、采购费：1.35万/年，分组作业未分摊，服务费已包含； | BV15: 1、签订期间：2026.2.25-2026.7.19； 2、指标按照全年换算；
A16: 19 | B16: KQCY0019 | C16: 餐饮一分部 | D16: CF272 | E16: 苏州工学院南一食堂 | F16: 强责 | G16: 郑虎 | H16: / | I16: 老乡邨 | J16: 刘少军 | K16: =LET(k,D16&"|"&E16&"|"&H16&"|"&I16&"|"&J16,sk,tblRevenueInput[项目代码]&"|"&tblRevenueInput[项目名称]&"|"&tblRevenueInput[分组作业名称]&"|"&tblRevenueInput[分组作业窗口名称]&"|"&tblRevenueInput[签订人],ok,tblRevenueOverride[项目代码]&"|"&tblRevenueOverride[项目名称]&"|"&tblRevenueOverride[分组作业名称]&"|"&tblRevenueOverride[分组作业窗口名称]&"|"&tblRevenueOverride[责任人],ov,IFERROR(XLOOKUP(k,ok,tblRevenueOverride[营业额覆盖],""),""),IF(ov<>"",ov,IFERROR(XLOOKUP(k,sk,tblRevenueInput[全额营业额合计],""),""))) | N16: 1698.59 | O16: 930000 | P16: 0.08 | Q16: =K16*P16 | R16: 766.96 | S16: =Q16-R16 | T16: 0 | U16: =K16*T16 | W16: =U16-V16 | X16: 0 | Y16: =K16*X16 | AA16: =Y16-Z16 | AB16: 0.065 | AC16: =K16*AB16 | AD16: 623.155 | AE16: =AC16-AD16 | AF16: 0.02 | AG16: =K16*AF16 | AH16: 191.74 | AI16: =AG16-AH16 | AJ16: 0.035 | AK16: =K16*AJ16 | AL16: 335.545 | AM16: =AK16-AL16 | AN16: 0 | AO16: =K16*AN16 | AQ16: =AO16-AP16 | AR16: 0.03 | AS16: =K16*AR16 | AT16: 287.61 | AU16: =AS16-AT16 | AV16: 0.06 | AW16: =K16*AV16 | AX16: 575.22 | AY16: =AW16-AX16 | AZ16: 按实 | BA16: =BB16 | BC16: =BA16-BB16 | BD16: 按实 | BE16: =BF16 | BG16: =BE16-BF16 | BH16: 按实 | BI16: =BJ16 | BK16: =BI16-BJ16 | BL16: 按实 | BM16: =BN16 | BO16: =BM16-BN16 | BP16: =N16+Q16+U16+Y16+AC16+AG16+AK16+AO16+AS16+AW16+BA16+BE16+BI16+BM16 | BQ16: =N16+R16+V16+Z16+AD16+AH16+AL16+AP16+AT16+AX16+BB16+BF16+BJ16+BN16 | BR16: =BP16-BQ16 | BS16: / | BT16: / | BU16: 1、甲方捐赠：35万/年，分组作业未分摊，服务费已包含； 2、采购费：1.35万/年，分组作业未分摊，服务费已包含； | BV16: 1、签订期间：2026.2.25-2026.7.19； 2、指标按照全年换算；
A17: 20 | B17: KQCY0020 | C17: 餐饮一分部 | D17: CF272 | E17: 苏州工学院南一食堂 | F17: 强责 | G17: 郑虎 | H17: / | I17: 科桥小厨 | J17: 吴浩 | K17: =LET(k,D17&"|"&E17&"|"&H17&"|"&I17&"|"&J17,sk,tblRevenueInput[项目代码]&"|"&tblRevenueInput[项目名称]&"|"&tblRevenueInput[分组作业名称]&"|"&tblRevenueInput[分组作业窗口名称]&"|"&tblRevenueInput[签订人],ok,tblRevenueOverride[项目代码]&"|"&tblRevenueOverride[项目名称]&"|"&tblRevenueOverride[分组作业名称]&"|"&tblRevenueOverride[分组作业窗口名称]&"|"&tblRevenueOverride[责任人],ov,IFERROR(XLOOKUP(k,ok,tblRevenueOverride[营业额覆盖],""),""),IF(ov<>"",ov,IFERROR(XLOOKUP(k,sk,tblRevenueInput[全额营业额合计],""),""))) | N17: 1698.59 | O17: 1280000 | P17: 0.06 | Q17: =K17*P17 | R17: 3048.72 | S17: =Q17-R17 | T17: 0 | U17: =K17*T17 | W17: =U17-V17 | X17: 0 | Y17: =K17*X17 | AA17: =Y17-Z17 | AB17: 0.055 | AC17: =K17*AB17 | AD17: 2794.66 | AE17: =AC17-AD17 | AF17: 0.02 | AG17: =K17*AF17 | AH17: 1016.24 | AI17: =AG17-AH17 | AJ17: 0.025 | AK17: =K17*AJ17 | AL17: 1270.3 | AM17: =AK17-AL17 | AN17: 0 | AO17: =K17*AN17 | AQ17: =AO17-AP17 | AR17: 0.03 | AS17: =K17*AR17 | AT17: 1524.36 | AU17: =AS17-AT17 | AV17: 0.06 | AW17: =K17*AV17 | AX17: 3048.72 | AY17: =AW17-AX17 | AZ17: 按实 | BA17: =BB17 | BC17: =BA17-BB17 | BD17: 按实 | BE17: =BF17 | BG17: =BE17-BF17 | BH17: 按实 | BI17: =BJ17 | BK17: =BI17-BJ17 | BL17: 按实 | BM17: =BN17 | BO17: =BM17-BN17 | BP17: =N17+Q17+U17+Y17+AC17+AG17+AK17+AO17+AS17+AW17+BA17+BE17+BI17+BM17 | BQ17: =N17+R17+V17+Z17+AD17+AH17+AL17+AP17+AT17+AX17+BB17+BF17+BJ17+BN17 | BR17: =BP17-BQ17 | BS17: / | BT17: / | BU17: 1、甲方捐赠：35万/年，分组作业未分摊，服务费已包含； 2、采购费：1.35万/年，分组作业未分摊，服务费已包含； | BV17: 1、签订期间：2026.2.25-2026.7.19； 2、指标按照全年换算；
A18: 21 | B18: KQCY0021 | C18: 餐饮一分部 | D18: CF272 | E18: 苏州工学院南一食堂 | F18: 强责 | G18: 郑虎 | H18: / | I18: 清汤米线 | J18: 张郁磊 | K18: =LET(k,D18&"|"&E18&"|"&H18&"|"&I18&"|"&J18,sk,tblRevenueInput[项目代码]&"|"&tblRevenueInput[项目名称]&"|"&tblRevenueInput[分组作业名称]&"|"&tblRevenueInput[分组作业窗口名称]&"|"&tblRevenueInput[签订人],ok,tblRevenueOverride[项目代码]&"|"&tblRevenueOverride[项目名称]&"|"&tblRevenueOverride[分组作业名称]&"|"&tblRevenueOverride[分组作业窗口名称]&"|"&tblRevenueOverride[责任人],ov,IFERROR(XLOOKUP(k,ok,tblRevenueOverride[营业额覆盖],""),""),IF(ov<>"",ov,IFERROR(XLOOKUP(k,sk,tblRevenueInput[全额营业额合计],""),""))) | N18: 1698.59 | O18: 264000 | P18: 0.08 | Q18: =K18*P18 | R18: 92.68 | S18: =Q18-R18 | T18: 0 | U18: =K18*T18 | W18: =U18-V18 | X18: 0 | Y18: =K18*X18 | AA18: =Y18-Z18 | AB18: 0.065 | AC18: =K18*AB18 | AD18: 75.3025 | AE18: =AC18-AD18 | AF18: 0.02 | AG18: =K18*AF18 | AH18: 23.17 | AI18: =AG18-AH18 | AJ18: 0.035 | AK18: =K18*AJ18 | AL18: 40.5475 | AM18: =AK18-AL18 | AN18: 0 | AO18: =K18*AN18 | AQ18: =AO18-AP18 | AR18: 0.03 | AS18: =K18*AR18 | AT18: 34.755 | AU18: =AS18-AT18 | AV18: 0.06 | AW18: =K18*AV18 | AX18: 69.51 | AY18: =AW18-AX18 | AZ18: 按实 | BA18: =BB18 | BC18: =BA18-BB18 | BD18: 按实 | BE18: =BF18 | BG18: =BE18-BF18 | BH18: 按实 | BI18: =BJ18 | BK18: =BI18-BJ18 | BL18: 按实 | BM18: =BN18 | BO18: =BM18-BN18 | BP18: =N18+Q18+U18+Y18+AC18+AG18+AK18+AO18+AS18+AW18+BA18+BE18+BI18+BM18 | BQ18: =N18+R18+V18+Z18+AD18+AH18+AL18+AP18+AT18+AX18+BB18+BF18+BJ18+BN18 | BR18: =BP18-BQ18 | BS18: / | BT18: / | BU18: 1、甲方捐赠：35万/年，分组作业未分摊，服务费已包含； 2、采购费：1.35万/年，分组作业未分摊，服务费已包含； | BV18: 1、签订期间：2026.2.25-2026.7.19； 2、指标按照全年换算；
A19: 22 | B19: KQCY0022 | C19: 餐饮一分部 | D19: CF272 | E19: 苏州工学院南一食堂 | F19: 强责 | G19: 郑虎 | H19: / | I19: 黑鸭堡 | J19: 张郁磊 | K19: =LET(k,D19&"|"&E19&"|"&H19&"|"&I19&"|"&J19,sk,tblRevenueInput[项目代码]&"|"&tblRevenueInput[项目名称]&"|"&tblRevenueInput[分组作业名称]&"|"&tblRevenueInput[分组作业窗口名称]&"|"&tblRevenueInput[签订人],ok,tblRevenueOverride[项目代码]&"|"&tblRevenueOverride[项目名称]&"|"&tblRevenueOverride[分组作业名称]&"|"&tblRevenueOverride[分组作业窗口名称]&"|"&tblRevenueOverride[责任人],ov,IFERROR(XLOOKUP(k,ok,tblRevenueOverride[营业额覆盖],""),""),IF(ov<>"",ov,IFERROR(XLOOKUP(k,sk,tblRevenueInput[全额营业额合计],""),""))) | N19: 0 | O19: 290000 | P19: 0.08 | Q19: =K19*P19 | R19: 75.84 | S19: =Q19-R19 | T19: 0 | U19: =K19*T19 | W19: =U19-V19 | X19: 0 | Y19: =K19*X19 | AA19: =Y19-Z19 | AB19: 0.065 | AC19: =K19*AB19 | AD19: 61.62 | AE19: =AC19-AD19 | AF19: 0.02 | AG19: =K19*AF19 | AH19: 18.96 | AI19: =AG19-AH19 | AJ19: 0.035 | AK19: =K19*AJ19 | AL19: 33.18 | AM19: =AK19-AL19 | AN19: 0 | AO19: =K19*AN19 | AQ19: =AO19-AP19 | AR19: 0.03 | AS19: =K19*AR19 | AT19: 28.44 | AU19: =AS19-AT19 | AV19: 0.06 | AW19: =K19*AV19 | AX19: 56.88 | AY19: =AW19-AX19 | AZ19: 按实 | BA19: =BB19 | BC19: =BA19-BB19 | BD19: 按实 | BE19: =BF19 | BG19: =BE19-BF19 | BH19: 按实 | BI19: =BJ19 | BK19: =BI19-BJ19 | BL19: 按实 | BM19: =BN19 | BO19: =BM19-BN19 | BP19: =N19+Q19+U19+Y19+AC19+AG19+AK19+AO19+AS19+AW19+BA19+BE19+BI19+BM19 | BQ19: =N19+R19+V19+Z19+AD19+AH19+AL19+AP19+AT19+AX19+BB19+BF19+BJ19+BN19 | BR19: =BP19-BQ19 | BS19: / | BT19: / | BU19: 1、甲方捐赠：35万/年，分组作业未分摊，服务费已包含； 2、采购费：1.35万/年，分组作业未分摊，服务费已包含； | BV19: 1、签订期间：2026.2.25-2026.7.19； 2、指标按照全年换算；
A20: 23 | B20: KQCY0023 | C20: 餐饮一分部 | D20: CF272 | E20: 苏州工学院南一食堂 | F20: 强责 | G20: 郑虎 | H20: / | I20: 7分甜 | J20: 纪洪强 | K20: =LET(k,D20&"|"&E20&"|"&H20&"|"&I20&"|"&J20,sk,tblRevenueInput[项目代码]&"|"&tblRevenueInput[项目名称]&"|"&tblRevenueInput[分组作业名称]&"|"&tblRevenueInput[分组作业窗口名称]&"|"&tblRevenueInput[签订人],ok,tblRevenueOverride[项目代码]&"|"&tblRevenueOverride[项目名称]&"|"&tblRevenueOverride[分组作业名称]&"|"&tblRevenueOverride[分组作业窗口名称]&"|"&tblRevenueOverride[责任人],ov,IFERROR(XLOOKUP(k,ok,tblRevenueOverride[营业额覆盖],""),""),IF(ov<>"",ov,IFERROR(XLOOKUP(k,sk,tblRevenueInput[全额营业额合计],""),""))) | N20: 1698.59 | O20: 222000 | P20: 0 | Q20: =K20*P20 | R20: 0 | S20: =Q20-R20 | T20: 0 | U20: =K20*T20 | W20: =U20-V20 | X20: 0 | Y20: =K20*X20 | AA20: =Y20-Z20 | AB20: 0 | AC20: =K20*AB20 | AD20: 0 | AE20: =AC20-AD20 | AF20: 0 | AG20: =K20*AF20 | AH20: 0 | AI20: =AG20-AH20 | AJ20: 0 | AK20: =K20*AJ20 | AL20: 0 | AM20: =AK20-AL20 | AN20: 0 | AO20: =K20*AN20 | AQ20: =AO20-AP20 | AR20: 0 | AS20: =K20*AR20 | AT20: 0 | AU20: =AS20-AT20 | AV20: 按实 | AW20: 522.28 | AX20: 522.28 | AY20: =AW20-AX20 | AZ20: 按实 | BA20: =BB20 | BC20: =BA20-BB20 | BD20: 按实 | BE20: =BF20 | BG20: =BE20-BF20 | BH20: 按实 | BI20: =BJ20 | BK20: =BI20-BJ20 | BL20: 按实 | BM20: =BN20 | BO20: =BM20-BN20 | BP20: =N20+Q20+U20+Y20+AC20+AG20+AK20+AO20+AS20+AW20+BA20+BE20+BI20+BM20 | BQ20: =N20+R20+V20+Z20+AD20+AH20+AL20+AP20+AT20+AX20+BB20+BF20+BJ20+BN20 | BR20: =BP20-BQ20 | BS20: / | BT20: / | BU20: 1、甲方捐赠：35万/年，分组作业未分摊，服务费已包含； 2、采购费：1.35万/年，分组作业未分摊，服务费已包含； | BV20: 1、签订期间：2026.2.25-2026.7.19； 2、指标按照全年换算；
A21: 24 | B21: KQCY0024 | C21: 餐饮一分部 | D21: CF272 | E21: 苏州工学院南一食堂 | F21: 强责 | G21: 郑虎 | H21: / | I21: 药膳鸡 | J21: 匡正娟 | K21: =LET(k,D21&"|"&E21&"|"&H21&"|"&I21&"|"&J21,sk,tblRevenueInput[项目代码]&"|"&tblRevenueInput[项目名称]&"|"&tblRevenueInput[分组作业名称]&"|"&tblRevenueInput[分组作业窗口名称]&"|"&tblRevenueInput[签订人],ok,tblRevenueOverride[项目代码]&"|"&tblRevenueOverride[项目名称]&"|"&tblRevenueOverride[分组作业名称]&"|"&tblRevenueOverride[分组作业窗口名称]&"|"&tblRevenueOverride[责任人],ov,IFERROR(XLOOKUP(k,ok,tblRevenueOverride[营业额覆盖],""),""),IF(ov<>"",ov,IFERROR(XLOOKUP(k,sk,tblRevenueInput[全额营业额合计],""),""))) | N21: 1698.59 | O21: 234000 | P21: 房租4万元/学期，3月一次性付款 | Q21: =R21 | R21: 0 | S21: =Q21-R21 | T21: 0 | U21: =K21*T21 | W21: =U21-V21 | X21: 0 | Y21: =K21*X21 | AA21: =Y21-Z21 | AB21: 0 | AC21: =K21*AB21 | AD21: 0 | AE21: =AC21-AD21 | AF21: 0 | AG21: =K21*AF21 | AH21: 0 | AI21: =AG21-AH21 | AJ21: 0 | AK21: =K21*AJ21 | AL21: 0 | AM21: =AK21-AL21 | AN21: 0 | AO21: =K21*AN21 | AQ21: =AO21-AP21 | AR21: 0.025 | AS21: =K21*AR21 | AT21: 342.4 | AU21: =AS21-AT21 | AV21: 0.055 | AW21: =K21*AV21 | AX21: 753.28 | AY21: =AW21-AX21 | AZ21: 按实 | BA21: =BB21 | BC21: =BA21-BB21 | BD21: 按实 | BE21: =BF21 | BG21: =BE21-BF21 | BH21: 按实 | BI21: =BJ21 | BK21: =BI21-BJ21 | BL21: 按实 | BM21: =BN21 | BO21: =BM21-BN21 | BP21: =N21+Q21+U21+Y21+AC21+AG21+AK21+AO21+AS21+AW21+BA21+BE21+BI21+BM21 | BQ21: =N21+R21+V21+Z21+AD21+AH21+AL21+AP21+AT21+AX21+BB21+BF21+BJ21+BN21 | BR21: =BP21-BQ21 | BS21: / | BT21: / | BU21: 1、甲方捐赠：35万/年，分组作业未分摊，服务费已包含； 2、采购费：1.35万/年，分组作业未分摊，服务费已包含； | BV21: 1、签订期间：2026.2.25-2026.7.19； 2、指标按照全年换算；
A22: 25 | B22: KQCY0025 | C22: 餐饮一分部 | D22: CF272 | E22: 苏州工学院南一食堂 | F22: 强责 | G22: 郑虎 | H22: / | I22: 麻辣香锅 | J22: 纪洪强 | K22: =LET(k,D22&"|"&E22&"|"&H22&"|"&I22&"|"&J22,sk,tblRevenueInput[项目代码]&"|"&tblRevenueInput[项目名称]&"|"&tblRevenueInput[分组作业名称]&"|"&tblRevenueInput[分组作业窗口名称]&"|"&tblRevenueInput[签订人],ok,tblRevenueOverride[项目代码]&"|"&tblRevenueOverride[项目名称]&"|"&tblRevenueOverride[分组作业名称]&"|"&tblRevenueOverride[分组作业窗口名称]&"|"&tblRevenueOverride[责任人],ov,IFERROR(XLOOKUP(k,ok,tblRevenueOverride[营业额覆盖],""),""),IF(ov<>"",ov,IFERROR(XLOOKUP(k,sk,tblRevenueInput[全额营业额合计],""),""))) | N22: 1698.59 | O22: 514000 | P22: 0.08 | Q22: =K22*P22 | R22: 1575.776 | S22: =Q22-R22 | T22: 0 | U22: =K22*T22 | W22: =U22-V22 | X22: 0 | Y22: =K22*X22 | AA22: =Y22-Z22 | AB22: 0.065 | AC22: =K22*AB22 | AD22: 1280.318 | AE22: =AC22-AD22 | AF22: 0.02 | AG22: =K22*AF22 | AH22: 393.944 | AI22: =AG22-AH22 | AJ22: 0.035 | AK22: =K22*AJ22 | AL22: 689.402 | AM22: =AK22-AL22 | AN22: 0 | AO22: =K22*AN22 | AQ22: =AO22-AP22 | AR22: 0.03 | AS22: =K22*AR22 | AT22: 590.916 | AU22: =AS22-AT22 | AV22: 0.06 | AW22: =K22*AV22 | AX22: 1181.832 | AY22: =AW22-AX22 | AZ22: 按实 | BA22: =BB22 | BC22: =BA22-BB22 | BD22: 按实 | BE22: =BF22 | BG22: =BE22-BF22 | BH22: 按实 | BI22: =BJ22 | BK22: =BI22-BJ22 | BL22: 按实 | BM22: =BN22 | BO22: =BM22-BN22 | BP22: =N22+Q22+U22+Y22+AC22+AG22+AK22+AO22+AS22+AW22+BA22+BE22+BI22+BM22 | BQ22: =N22+R22+V22+Z22+AD22+AH22+AL22+AP22+AT22+AX22+BB22+BF22+BJ22+BN22 | BR22: =BP22-BQ22 | BS22: / | BT22: / | BU22: 1、甲方捐赠：35万/年，分组作业未分摊，服务费已包含； 2、采购费：1.35万/年，分组作业未分摊，服务费已包含； | BV22: 1、签订期间：2026.2.25-2026.7.19； 2、指标按照全年换算；
A23: 26 | B23: KQCY0026 | C23: 餐饮一分部 | D23: CF272 | E23: 苏州工学院南一食堂 | F23: 强责 | G23: 郑虎 | H23: / | I23: 生煎牛肉汤 | J23: 徐雪晗 | K23: =LET(k,D23&"|"&E23&"|"&H23&"|"&I23&"|"&J23,sk,tblRevenueInput[项目代码]&"|"&tblRevenueInput[项目名称]&"|"&tblRevenueInput[分组作业名称]&"|"&tblRevenueInput[分组作业窗口名称]&"|"&tblRevenueInput[签订人],ok,tblRevenueOverride[项目代码]&"|"&tblRevenueOverride[项目名称]&"|"&tblRevenueOverride[分组作业名称]&"|"&tblRevenueOverride[分组作业窗口名称]&"|"&tblRevenueOverride[责任人],ov,IFERROR(XLOOKUP(k,ok,tblRevenueOverride[营业额覆盖],""),""),IF(ov<>"",ov,IFERROR(XLOOKUP(k,sk,tblRevenueInput[全额营业额合计],""),""))) | N23: 2956.4 | O23: 316000 | P23: 0.08 | Q23: =K23*P23 | R23: 509.56 | S23: =Q23-R23 | T23: 0 | U23: =K23*T23 | W23: =U23-V23 | X23: 0 | Y23: =K23*X23 | AA23: =Y23-Z23 | AB23: 0.065 | AC23: =K23*AB23 | AD23: 414.0175 | AE23: =AC23-AD23 | AF23: 0.02 | AG23: =K23*AF23 | AH23: 127.39 | AI23: =AG23-AH23 | AJ23: 0.035 | AK23: =K23*AJ23 | AL23: 222.9325 | AM23: =AK23-AL23 | AN23: 0 | AO23: =K23*AN23 | AQ23: =AO23-AP23 | AR23: 0.03 | AS23: =K23*AR23 | AT23: 191.085 | AU23: =AS23-AT23 | AV23: 0.06 | AW23: =K23*AV23 | AX23: 382.17 | AY23: =AW23-AX23 | AZ23: 按实 | BA23: =BB23 | BC23: =BA23-BB23 | BD23: 按实 | BE23: =BF23 | BG23: =BE23-BF23 | BH23: 按实 | BI23: =BJ23 | BK23: =BI23-BJ23 | BL23: 按实 | BM23: =BN23 | BO23: =BM23-BN23 | BP23: =N23+Q23+U23+Y23+AC23+AG23+AK23+AO23+AS23+AW23+BA23+BE23+BI23+BM23 | BQ23: =N23+R23+V23+Z23+AD23+AH23+AL23+AP23+AT23+AX23+BB23+BF23+BJ23+BN23 | BR23: =BP23-BQ23 | BS23: / | BT23: / | BU23: 1、甲方捐赠：35万/年，分组作业未分摊，服务费已包含； 2、采购费：1.35万/年，分组作业未分摊，服务费已包含； | BV23: 1、签订期间：2026.2.25-2026.7.19； 2、指标按照全年换算；
A24: 27 | B24: KQCY0027 | C24: 餐饮一分部 | D24: CF272 | E24: 苏州工学院南一食堂 | F24: 强责 | G24: 郑虎 | H24: / | I24: 西式简餐 | J24: 李明发 | K24: =LET(k,D24&"|"&E24&"|"&H24&"|"&I24&"|"&J24,sk,tblRevenueInput[项目代码]&"|"&tblRevenueInput[项目名称]&"|"&tblRevenueInput[分组作业名称]&"|"&tblRevenueInput[分组作业窗口名称]&"|"&tblRevenueInput[签订人],ok,tblRevenueOverride[项目代码]&"|"&tblRevenueOverride[项目名称]&"|"&tblRevenueOverride[分组作业名称]&"|"&tblRevenueOverride[分组作业窗口名称]&"|"&tblRevenueOverride[责任人],ov,IFERROR(XLOOKUP(k,ok,tblRevenueOverride[营业额覆盖],""),""),IF(ov<>"",ov,IFERROR(XLOOKUP(k,sk,tblRevenueInput[全额营业额合计],""),""))) | N24: 1698.59 | O24: 310000 | P24: 0.08 | Q24: =K24*P24 | R24: 445.12 | S24: =Q24-R24 | T24: 0 | U24: =K24*T24 | W24: =U24-V24 | X24: 0 | Y24: =K24*X24 | AA24: =Y24-Z24 | AB24: 0.065 | AC24: =K24*AB24 | AD24: 361.66 | AE24: =AC24-AD24 | AF24: 0.02 | AG24: =K24*AF24 | AH24: 111.28 | AI24: =AG24-AH24 | AJ24: 0.035 | AK24: =K24*AJ24 | AL24: 194.74 | AM24: =AK24-AL24 | AN24: 0 | AO24: =K24*AN24 | AQ24: =AO24-AP24 | AR24: 0.03 | AS24: =K24*AR24 | AT24: 166.92 | AU24: =AS24-AT24 | AV24: 0.06 | AW24: =K24*AV24 | AX24: 333.84 | AY24: =AW24-AX24 | AZ24: 按实 | BA24: =BB24 | BC24: =BA24-BB24 | BD24: 按实 | BE24: =BF24 | BG24: =BE24-BF24 | BH24: 按实 | BI24: =BJ24 | BK24: =BI24-BJ24 | BL24: 按实 | BM24: =BN24 | BO24: =BM24-BN24 | BP24: =N24+Q24+U24+Y24+AC24+AG24+AK24+AO24+AS24+AW24+BA24+BE24+BI24+BM24 | BQ24: =N24+R24+V24+Z24+AD24+AH24+AL24+AP24+AT24+AX24+BB24+BF24+BJ24+BN24 | BR24: =BP24-BQ24 | BS24: / | BT24: / | BU24: 1、甲方捐赠：35万/年，分组作业未分摊，服务费已包含； 2、采购费：1.35万/年，分组作业未分摊，服务费已包含； | BV24: 1、签订期间：2026.2.25-2026.7.19； 2、指标按照全年换算；
A25: 28 | B25: KQCY0028 | C25: 餐饮一分部 | D25: CF272 | E25: 苏州工学院南一食堂 | F25: 强责 | G25: 郑虎 | H25: / | I25: 苏式面 | J25: 许正芳 | K25: =LET(k,D25&"|"&E25&"|"&H25&"|"&I25&"|"&J25,sk,tblRevenueInput[项目代码]&"|"&tblRevenueInput[项目名称]&"|"&tblRevenueInput[分组作业名称]&"|"&tblRevenueInput[分组作业窗口名称]&"|"&tblRevenueInput[签订人],ok,tblRevenueOverride[项目代码]&"|"&tblRevenueOverride[项目名称]&"|"&tblRevenueOverride[分组作业名称]&"|"&tblRevenueOverride[分组作业窗口名称]&"|"&tblRevenueOverride[责任人],ov,IFERROR(XLOOKUP(k,ok,tblRevenueOverride[营业额覆盖],""),""),IF(ov<>"",ov,IFERROR(XLOOKUP(k,sk,tblRevenueInput[全额营业额合计],""),""))) | N25: 28 | O25: 530000 | P25: 0.08 | Q25: =K25*P25 | R25: 769.72 | S25: =Q25-R25 | T25: 0 | U25: =K25*T25 | W25: =U25-V25 | X25: 0 | Y25: =K25*X25 | AA25: =Y25-Z25 | AB25: 0.065 | AC25: =K25*AB25 | AD25: 625.3975 | AE25: =AC25-AD25 | AF25: 0.02 | AG25: =K25*AF25 | AH25: 192.43 | AI25: =AG25-AH25 | AJ25: 0.035 | AK25: =K25*AJ25 | AL25: 336.7525 | AM25: =AK25-AL25 | AN25: 0 | AO25: =K25*AN25 | AQ25: =AO25-AP25 | AR25: 0.03 | AS25: =K25*AR25 | AT25: 288.645 | AU25: =AS25-AT25 | AV25: 0.06 | AW25: =K25*AV25 | AX25: 577.29 | AY25: =AW25-AX25 | AZ25: 按实 | BA25: =BB25 | BC25: =BA25-BB25 | BD25: 按实 | BE25: =BF25 | BG25: =BE25-BF25 | BH25: 按实 | BI25: =BJ25 | BK25: =BI25-BJ25 | BL25: 按实 | BM25: =BN25 | BO25: =BM25-BN25 | BP25: =N25+Q25+U25+Y25+AC25+AG25+AK25+AO25+AS25+AW25+BA25+BE25+BI25+BM25 | BQ25: =N25+R25+V25+Z25+AD25+AH25+AL25+AP25+AT25+AX25+BB25+BF25+BJ25+BN25 | BR25: =BP25-BQ25 | BS25: / | BT25: / | BU25: 1、甲方捐赠：35万/年，分组作业未分摊，服务费已包含； 2、采购费：1.35万/年，分组作业未分摊，服务费已包含； | BV25: 1、签订期间：2026.2.25-2026.7.19； 2、指标按照全年换算；
A26: 29 | B26: KQCY0029 | C26: 餐饮一分部 | D26: CF272 | E26: 苏州工学院南一食堂 | F26: 强责 | G26: 郑虎 | H26: / | I26: 王记炒饭 | J26: 王梓骏 | K26: =LET(k,D26&"|"&E26&"|"&H26&"|"&I26&"|"&J26,sk,tblRevenueInput[项目代码]&"|"&tblRevenueInput[项目名称]&"|"&tblRevenueInput[分组作业名称]&"|"&tblRevenueInput[分组作业窗口名称]&"|"&tblRevenueInput[签订人],ok,tblRevenueOverride[项目代码]&"|"&tblRevenueOverride[项目名称]&"|"&tblRevenueOverride[分组作业名称]&"|"&tblRevenueOverride[分组作业窗口名称]&"|"&tblRevenueOverride[责任人],ov,IFERROR(XLOOKUP(k,ok,tblRevenueOverride[营业额覆盖],""),""),IF(ov<>"",ov,IFERROR(XLOOKUP(k,sk,tblRevenueInput[全额营业额合计],""),""))) | N26: 3397.18 | O26: 526000 | P26: 0.08 | Q26: =K26*P26 | R26: 1282.24 | S26: =Q26-R26 | T26: 0 | U26: =K26*T26 | W26: =U26-V26 | X26: 0 | Y26: =K26*X26 | AA26: =Y26-Z26 | AB26: 0.065 | AC26: =K26*AB26 | AD26: 1041.82 | AE26: =AC26-AD26 | AF26: 0.02 | AG26: =K26*AF26 | AH26: 320.56 | AI26: =AG26-AH26 | AJ26: 0.035 | AK26: =K26*AJ26 | AL26: 560.98 | AM26: =AK26-AL26 | AN26: 0 | AO26: =K26*AN26 | AQ26: =AO26-AP26 | AR26: 0.03 | AS26: =K26*AR26 | AT26: 480.84 | AU26: =AS26-AT26 | AV26: 0.06 | AW26: =K26*AV26 | AX26: 961.68 | AY26: =AW26-AX26 | AZ26: 按实 | BA26: =BB26 | BC26: =BA26-BB26 | BD26: 按实 | BE26: =BF26 | BG26: =BE26-BF26 | BH26: 按实 | BI26: =BJ26 | BK26: =BI26-BJ26 | BL26: 按实 | BM26: =BN26 | BO26: =BM26-BN26 | BP26: =N26+Q26+U26+Y26+AC26+AG26+AK26+AO26+AS26+AW26+BA26+BE26+BI26+BM26 | BQ26: =N26+R26+V26+Z26+AD26+AH26+AL26+AP26+AT26+AX26+BB26+BF26+BJ26+BN26 | BR26: =BP26-BQ26 | BS26: / | BT26: / | BU26: 1、甲方捐赠：35万/年，分组作业未分摊，服务费已包含； 2、采购费：1.35万/年，分组作业未分摊，服务费已包含； | BV26: 1、签订期间：2026.2.25-2026.7.19； 2、指标按照全年换算；
A27: 30 | B27: KQCY0030 | C27: 餐饮一分部 | D27: CF272 | E27: 苏州工学院南一食堂 | F27: 强责 | G27: 郑虎 | H27: / | I27: 烤鸭 | J27: 王鑫 | K27: =LET(k,D27&"|"&E27&"|"&H27&"|"&I27&"|"&J27,sk,tblRevenueInput[项目代码]&"|"&tblRevenueInput[项目名称]&"|"&tblRevenueInput[分组作业名称]&"|"&tblRevenueInput[分组作业窗口名称]&"|"&tblRevenueInput[签订人],ok,tblRevenueOverride[项目代码]&"|"&tblRevenueOverride[项目名称]&"|"&tblRevenueOverride[分组作业名称]&"|"&tblRevenueOverride[分组作业窗口名称]&"|"&tblRevenueOverride[责任人],ov,IFERROR(XLOOKUP(k,ok,tblRevenueOverride[营业额覆盖],""),""),IF(ov<>"",ov,IFERROR(XLOOKUP(k,sk,tblRevenueInput[全额营业额合计],""),""))) | N27: 1698.59 | O27: 530000 | P27: 0.08 | Q27: =K27*P27 | R27: 1305.12 | S27: =Q27-R27 | T27: 0 | U27: =K27*T27 | W27: =U27-V27 | X27: 0 | Y27: =K27*X27 | AA27: =Y27-Z27 | AB27: 0.065 | AC27: =K27*AB27 | AD27: 1060.41 | AE27: =AC27-AD27 | AF27: 0.02 | AG27: =K27*AF27 | AH27: 326.28 | AI27: =AG27-AH27 | AJ27: 0.035 | AK27: =K27*AJ27 | AL27: 570.99 | AM27: =AK27-AL27 | AN27: 0 | AO27: =K27*AN27 | AQ27: =AO27-AP27 | AR27: 0.03 | AS27: =K27*AR27 | AT27: 489.42 | AU27: =AS27-AT27 | AV27: 0.06 | AW27: =K27*AV27 | AX27: 978.84 | AY27: =AW27-AX27 | AZ27: 按实 | BA27: =BB27 | BC27: =BA27-BB27 | BD27: 按实 | BE27: =BF27 | BG27: =BE27-BF27 | BH27: 按实 | BI27: =BJ27 | BK27: =BI27-BJ27 | BL27: 按实 | BM27: =BN27 | BO27: =BM27-BN27 | BP27: =N27+Q27+U27+Y27+AC27+AG27+AK27+AO27+AS27+AW27+BA27+BE27+BI27+BM27 | BQ27: =N27+R27+V27+Z27+AD27+AH27+AL27+AP27+AT27+AX27+BB27+BF27+BJ27+BN27 | BR27: =BP27-BQ27 | BS27: / | BT27: / | BU27: 1、甲方捐赠：35万/年，分组作业未分摊，服务费已包含； 2、采购费：1.35万/年，分组作业未分摊，服务费已包含； | BV27: 1、签订期间：2026.2.25-2026.7.19； 2、指标按照全年换算；
A28: 31 | B28: KQCY0031 | C28: 餐饮一分部 | D28: CF272 | E28: 苏州工学院南一食堂 | F28: 强责 | G28: 郑虎 | H28: / | I28: 小街胡同牛杂面 | J28: 黄雨 | K28: =LET(k,D28&"|"&E28&"|"&H28&"|"&I28&"|"&J28,sk,tblRevenueInput[项目代码]&"|"&tblRevenueInput[项目名称]&"|"&tblRevenueInput[分组作业名称]&"|"&tblRevenueInput[分组作业窗口名称]&"|"&tblRevenueInput[签订人],ok,tblRevenueOverride[项目代码]&"|"&tblRevenueOverride[项目名称]&"|"&tblRevenueOverride[分组作业名称]&"|"&tblRevenueOverride[分组作业窗口名称]&"|"&tblRevenueOverride[责任人],ov,IFERROR(XLOOKUP(k,ok,tblRevenueOverride[营业额覆盖],""),""),IF(ov<>"",ov,IFERROR(XLOOKUP(k,sk,tblRevenueInput[全额营业额合计],""),""))) | N28: 1698.59 | O28: 360000 | P28: 0.08 | Q28: =K28*P28 | R28: 1520.88 | S28: =Q28-R28 | T28: 0 | U28: =K28*T28 | W28: =U28-V28 | X28: 0 | Y28: =K28*X28 | AA28: =Y28-Z28 | AB28: 0.065 | AC28: =K28*AB28 | AD28: 1235.715 | AE28: =AC28-AD28 | AF28: 0.02 | AG28: =K28*AF28 | AH28: 380.22 | AI28: =AG28-AH28 | AJ28: 0.035 | AK28: =K28*AJ28 | AL28: 665.385 | AM28: =AK28-AL28 | AN28: 0 | AO28: =K28*AN28 | AQ28: =AO28-AP28 | AR28: 0.03 | AS28: =K28*AR28 | AT28: 570.33 | AU28: =AS28-AT28 | AV28: 0.06 | AW28: =K28*AV28 | AX28: 1140.66 | AY28: =AW28-AX28 | AZ28: 按实 | BA28: =BB28 | BC28: =BA28-BB28 | BD28: 按实 | BE28: =BF28 | BG28: =BE28-BF28 | BH28: 按实 | BI28: =BJ28 | BK28: =BI28-BJ28 | BL28: 按实 | BM28: =BN28 | BO28: =BM28-BN28 | BP28: =N28+Q28+U28+Y28+AC28+AG28+AK28+AO28+AS28+AW28+BA28+BE28+BI28+BM28 | BQ28: =N28+R28+V28+Z28+AD28+AH28+AL28+AP28+AT28+AX28+BB28+BF28+BJ28+BN28 | BR28: =BP28-BQ28 | BS28: / | BT28: / | BU28: 1、甲方捐赠：35万/年，分组作业未分摊，服务费已包含； 2、采购费：1.35万/年，分组作业未分摊，服务费已包含； | BV28: 1、签订期间：2026.2.25-2026.7.19； 2、指标按照全年换算；
A29: 32 | B29: KQCY0032 | C29: 餐饮一分部 | D29: CF272 | E29: 苏州工学院南一食堂 | F29: 强责 | G29: 郑虎 | H29: / | I29: 汉堡炸鸡 | J29: 陆林峰 | K29: =LET(k,D29&"|"&E29&"|"&H29&"|"&I29&"|"&J29,sk,tblRevenueInput[项目代码]&"|"&tblRevenueInput[项目名称]&"|"&tblRevenueInput[分组作业名称]&"|"&tblRevenueInput[分组作业窗口名称]&"|"&tblRevenueInput[签订人],ok,tblRevenueOverride[项目代码]&"|"&tblRevenueOverride[项目名称]&"|"&tblRevenueOverride[分组作业名称]&"|"&tblRevenueOverride[分组作业窗口名称]&"|"&tblRevenueOverride[责任人],ov,IFERROR(XLOOKUP(k,ok,tblRevenueOverride[营业额覆盖],""),""),IF(ov<>"",ov,IFERROR(XLOOKUP(k,sk,tblRevenueInput[全额营业额合计],""),""))) | N29: 0 | O29: 366000 | P29: 0.08 | Q29: =K29*P29 | R29: 0 | S29: =Q29-R29 | T29: 0 | U29: =K29*T29 | W29: =U29-V29 | X29: 0 | Y29: =K29*X29 | AA29: =Y29-Z29 | AB29: 0.065 | AC29: =K29*AB29 | AD29: 0 | AE29: =AC29-AD29 | AF29: 0.02 | AG29: =K29*AF29 | AH29: 0 | AI29: =AG29-AH29 | AJ29: 0.035 | AK29: =K29*AJ29 | AL29: 0 | AM29: =AK29-AL29 | AN29: 0 | AO29: =K29*AN29 | AQ29: =AO29-AP29 | AR29: 0.03 | AS29: =K29*AR29 | AT29: 0 | AU29: =AS29-AT29 | AV29: 0.06 | AW29: =K29*AV29 | AX29: 0 | AY29: =AW29-AX29 | AZ29: 按实 | BA29: =BB29 | BC29: =BA29-BB29 | BD29: 按实 | BE29: =BF29 | BG29: =BE29-BF29 | BH29: 按实 | BI29: =BJ29 | BK29: =BI29-BJ29 | BL29: 按实 | BM29: =BN29 | BO29: =BM29-BN29 | BP29: =N29+Q29+U29+Y29+AC29+AG29+AK29+AO29+AS29+AW29+BA29+BE29+BI29+BM29 | BQ29: =N29+R29+V29+Z29+AD29+AH29+AL29+AP29+AT29+AX29+BB29+BF29+BJ29+BN29 | BR29: =BP29-BQ29 | BS29: / | BT29: / | BU29: 1、甲方捐赠：35万/年，分组作业未分摊，服务费已包含； 2、采购费：1.35万/年，分组作业未分摊，服务费已包含； | BV29: 1、签订期间：2026.2.25-2026.7.19； 2、指标按照全年换算；
A30: 33 | B30: KQCY0033 | C30: 餐饮一分部 | D30: CF272 | E30: 苏州工学院南一食堂 | F30: 强责 | G30: 郑虎 | H30: / | I30: 旋转小火锅 | J30: 潘祥 | K30: =LET(k,D30&"|"&E30&"|"&H30&"|"&I30&"|"&J30,sk,tblRevenueInput[项目代码]&"|"&tblRevenueInput[项目名称]&"|"&tblRevenueInput[分组作业名称]&"|"&tblRevenueInput[分组作业窗口名称]&"|"&tblRevenueInput[签订人],ok,tblRevenueOverride[项目代码]&"|"&tblRevenueOverride[项目名称]&"|"&tblRevenueOverride[分组作业名称]&"|"&tblRevenueOverride[分组作业窗口名称]&"|"&tblRevenueOverride[责任人],ov,IFERROR(XLOOKUP(k,ok,tblRevenueOverride[营业额覆盖],""),""),IF(ov<>"",ov,IFERROR(XLOOKUP(k,sk,tblRevenueInput[全额营业额合计],""),""))) | N30: 0 | O30: 284000 | P30: 0.06 | Q30: =K30*P30 | R30: 0 | S30: =Q30-R30 | T30: 0 | U30: =K30*T30 | W30: =U30-V30 | X30: 0 | Y30: =K30*X30 | AA30: =Y30-Z30 | AB30: 0.065 | AC30: =K30*AB30 | AD30: 0 | AE30: =AC30-AD30 | AF30: 0.02 | AG30: =K30*AF30 | AH30: 0 | AI30: =AG30-AH30 | AJ30: 0.025 | AK30: =K30*AJ30 | AL30: 0 | AM30: =AK30-AL30 | AN30: 0 | AO30: =K30*AN30 | AQ30: =AO30-AP30 | AR30: 0.03 | AS30: =K30*AR30 | AT30: 0 | AU30: =AS30-AT30 | AV30: 0.06 | AW30: =K30*AV30 | AX30: 0 | AY30: =AW30-AX30 | AZ30: 按实 | BA30: =BB30 | BC30: =BA30-BB30 | BD30: 按实 | BE30: =BF30 | BG30: =BE30-BF30 | BH30: 按实 | BI30: =BJ30 | BK30: =BI30-BJ30 | BL30: 按实 | BM30: 36324 | BN30: 36324 | BO30: =BM30-BN30 | BP30: =N30+Q30+U30+Y30+AC30+AG30+AK30+AO30+AS30+AW30+BA30+BE30+BI30+BM30 | BQ30: =N30+R30+V30+Z30+AD30+AH30+AL30+AP30+AT30+AX30+BB30+BF30+BJ30+BN30 | BR30: =BP30-BQ30 | BS30: / | BT30: / | BU30: 1、甲方捐赠：35万/年，分组作业未分摊，服务费已包含； 2、采购费：1.35万/年，分组作业未分摊，服务费已包含； | BV30: 1、签订期间：2026.2.25-2026.7.19； 2、指标按照全年换算； 3、已撤场（2026年3月）；
A31: 43 | B31: KQCY0043 | C31: 餐饮二分部 | D31: CF125 | E31: 西浦大学宏愿食堂（南） | F31: 分组作业 | G31: 徐敏娟 | H31: / | I31: 麻辣烫 | J31: 何军军 | K31: =LET(k,D31&"|"&E31&"|"&H31&"|"&I31&"|"&J31,sk,tblRevenueInput[项目代码]&"|"&tblRevenueInput[项目名称]&"|"&tblRevenueInput[分组作业名称]&"|"&tblRevenueInput[分组作业窗口名称]&"|"&tblRevenueInput[签订人],ok,tblRevenueOverride[项目代码]&"|"&tblRevenueOverride[项目名称]&"|"&tblRevenueOverride[分组作业名称]&"|"&tblRevenueOverride[分组作业窗口名称]&"|"&tblRevenueOverride[责任人],ov,IFERROR(XLOOKUP(k,ok,tblRevenueOverride[营业额覆盖],""),""),IF(ov<>"",ov,IFERROR(XLOOKUP(k,sk,tblRevenueInput[全额营业额合计],""),""))) | N31: 20433.09 | O31: 850000 | P31: 0.12 | Q31: =K31*P31 | R31: 4953.55 | S31: =Q31-R31 | T31: 按照实际收取 | U31: =V31 | W31: =U31-V31 | X31: 0.02 | Y31: =K31*X31 | Z31: 825 | AA31: =Y31-Z31 | AB31: 0 | AC31: =K31*AB31 | AE31: =AC31-AD31 | AF31: 0 | AG31: =K31*AF31 | AI31: =AG31-AH31 | AJ31: 0 | AK31: =K31*AJ31 | AM31: =AK31-AL31 | AN31: 0 | AO31: =K31*AN31 | AQ31: =AO31-AP31 | AR31: 按照实际收取 | AS31: =AT31 | AT31: 4577 | AU31: =AS31-AT31 | AV31: 按照实际收取 | AW31: =AX31 | AX31: 0 | AY31: =AW31-AX31 | AZ31: 按实 | BA31: =BB31 | BB31: 0 | BC31: =BA31-BB31 | BD31: 0.035 | BE31: =K31*BD31 | BF31: 0 | BG31: =BE31-BF31 | BH31: 0 | BI31: =K31*BH31 | BK31: =BI31-BJ31 | BL31: 按实 | BM31: =BN31 | BN31: 10604.51 | BO31: =BM31-BN31 | BP31: =N31+Q31+U31+Y31+AC31+AG31+AK31+AO31+AS31+AW31+BA31+BE31+BI31+BM31 | BQ31: =N31+R31+V31+Z31+AD31+AH31+AL31+AP31+AT31+AX31+BB31+BF31+BJ31+BN31 | BR31: =BP31-BQ31 | BS31: / | BT31: / | BU31: 1、装修折旧费：项目反馈不收取，包含在服务费中； | BV31: 1、签订期间：2025.9-2026.8； 2、指标按照全年换算；
A32: 44 | B32: KQCY0044 | C32: 餐饮二分部 | D32: CF125 | E32: 西浦大学宏愿食堂（南） | F32: 分组作业 | G32: 徐敏娟 | H32: / | I32: 小炒 | J32: 王成龙 | K32: =LET(k,D32&"|"&E32&"|"&H32&"|"&I32&"|"&J32,sk,tblRevenueInput[项目代码]&"|"&tblRevenueInput[项目名称]&"|"&tblRevenueInput[分组作业名称]&"|"&tblRevenueInput[分组作业窗口名称]&"|"&tblRevenueInput[签订人],ok,tblRevenueOverride[项目代码]&"|"&tblRevenueOverride[项目名称]&"|"&tblRevenueOverride[分组作业名称]&"|"&tblRevenueOverride[分组作业窗口名称]&"|"&tblRevenueOverride[责任人],ov,IFERROR(XLOOKUP(k,ok,tblRevenueOverride[营业额覆盖],""),""),IF(ov<>"",ov,IFERROR(XLOOKUP(k,sk,tblRevenueInput[全额营业额合计],""),""))) | O32: 1500000 | P32: 0.12 | Q32: =K32*P32 | S32: =Q32-R32 | T32: 按照实际收取 | U32: =V32 | W32: =U32-V32 | X32: 0.02 | Y32: =K32*X32 | AA32: =Y32-Z32 | AB32: 0 | AC32: =K32*AB32 | AE32: =AC32-AD32 | AF32: 0 | AG32: =K32*AF32 | AI32: =AG32-AH32 | AJ32: 0 | AK32: =K32*AJ32 | AM32: =AK32-AL32 | AN32: 0 | AO32: =K32*AN32 | AQ32: =AO32-AP32 | AR32: 按照实际收取 | AS32: =AT32 | AU32: =AS32-AT32 | AV32: 按照实际收取 | AW32: =AX32 | AY32: =AW32-AX32 | AZ32: 按实 | BA32: =BB32 | BC32: =BA32-BB32 | BD32: 0.035 | BE32: =K32*BD32 | BG32: =BE32-BF32 | BH32: 0 | BI32: =K32*BH32 | BK32: =BI32-BJ32 | BL32: 按实 | BM32: =BN32 | BO32: =BM32-BN32 | BP32: =N32+Q32+U32+Y32+AC32+AG32+AK32+AO32+AS32+AW32+BA32+BE32+BI32+BM32 | BQ32: =N32+R32+V32+Z32+AD32+AH32+AL32+AP32+AT32+AX32+BB32+BF32+BJ32+BN32 | BR32: =BP32-BQ32 | BS32: / | BT32: / | BU32: 1、装修折旧费：项目反馈不收取，包含在服务费中； | BV32: 1、签订期间：2025.9-2026.8； 2、指标按照全年换算；
A33: 45 | B33: KQCY0045 | C33: 餐饮二分部 | D33: CF125 | E33: 西浦大学宏愿食堂（南） | F33: 分组作业 | G33: 徐敏娟 | H33: / | I33: 枣糕 | J33: 杜松松 | K33: =LET(k,D33&"|"&E33&"|"&H33&"|"&I33&"|"&J33,sk,tblRevenueInput[项目代码]&"|"&tblRevenueInput[项目名称]&"|"&tblRevenueInput[分组作业名称]&"|"&tblRevenueInput[分组作业窗口名称]&"|"&tblRevenueInput[签订人],ok,tblRevenueOverride[项目代码]&"|"&tblRevenueOverride[项目名称]&"|"&tblRevenueOverride[分组作业名称]&"|"&tblRevenueOverride[分组作业窗口名称]&"|"&tblRevenueOverride[责任人],ov,IFERROR(XLOOKUP(k,ok,tblRevenueOverride[营业额覆盖],""),""),IF(ov<>"",ov,IFERROR(XLOOKUP(k,sk,tblRevenueInput[全额营业额合计],""),""))) | O33: 340000 | P33: 0.12 | Q33: =K33*P33 | S33: =Q33-R33 | T33: 按照实际收取 | U33: =V33 | W33: =U33-V33 | X33: 0.02 | Y33: =K33*X33 | AA33: =Y33-Z33 | AB33: 0 | AC33: =K33*AB33 | AE33: =AC33-AD33 | AF33: 0 | AG33: =K33*AF33 | AI33: =AG33-AH33 | AJ33: 0 | AK33: =K33*AJ33 | AM33: =AK33-AL33 | AN33: 0 | AO33: =K33*AN33 | AQ33: =AO33-AP33 | AR33: 按照实际收取 | AS33: =AT33 | AU33: =AS33-AT33 | AV33: 按照实际收取 | AW33: =AX33 | AY33: =AW33-AX33 | AZ33: 按实 | BA33: =BB33 | BC33: =BA33-BB33 | BD33: 0.035 | BE33: =K33*BD33 | BG33: =BE33-BF33 | BH33: 0 | BI33: =K33*BH33 | BK33: =BI33-BJ33 | BL33: 按实 | BM33: =BN33 | BO33: =BM33-BN33 | BP33: =N33+Q33+U33+Y33+AC33+AG33+AK33+AO33+AS33+AW33+BA33+BE33+BI33+BM33 | BQ33: =N33+R33+V33+Z33+AD33+AH33+AL33+AP33+AT33+AX33+BB33+BF33+BJ33+BN33 | BR33: =BP33-BQ33 | BS33: / | BT33: / | BU33: 1、装修折旧费：项目反馈不收取，包含在服务费中； | BV33: 1、签订期间：2025.9-2026.8； 2、指标按照全年换算；
A34: 46 | B34: KQCY0046 | C34: 餐饮二分部 | D34: CF125 | E34: 西浦大学宏愿食堂（南） | F34: 分组作业 | G34: 徐敏娟 | H34: / | I34: 面条 | J34: 葛文静 | K34: =LET(k,D34&"|"&E34&"|"&H34&"|"&I34&"|"&J34,sk,tblRevenueInput[项目代码]&"|"&tblRevenueInput[项目名称]&"|"&tblRevenueInput[分组作业名称]&"|"&tblRevenueInput[分组作业窗口名称]&"|"&tblRevenueInput[签订人],ok,tblRevenueOverride[项目代码]&"|"&tblRevenueOverride[项目名称]&"|"&tblRevenueOverride[分组作业名称]&"|"&tblRevenueOverride[分组作业窗口名称]&"|"&tblRevenueOverride[责任人],ov,IFERROR(XLOOKUP(k,ok,tblRevenueOverride[营业额覆盖],""),""),IF(ov<>"",ov,IFERROR(XLOOKUP(k,sk,tblRevenueInput[全额营业额合计],""),""))) | O34: 365000 | P34: 0.12 | Q34: =K34*P34 | S34: =Q34-R34 | T34: 按照实际收取 | U34: =V34 | W34: =U34-V34 | X34: 0.02 | Y34: =K34*X34 | AA34: =Y34-Z34 | AB34: 0 | AC34: =K34*AB34 | AE34: =AC34-AD34 | AF34: 0 | AG34: =K34*AF34 | AI34: =AG34-AH34 | AJ34: 0 | AK34: =K34*AJ34 | AM34: =AK34-AL34 | AN34: 0 | AO34: =K34*AN34 | AQ34: =AO34-AP34 | AR34: 按照实际收取 | AS34: =AT34 | AU34: =AS34-AT34 | AV34: 按照实际收取 | AW34: =AX34 | AY34: =AW34-AX34 | AZ34: 按实 | BA34: =BB34 | BC34: =BA34-BB34 | BD34: 0.035 | BE34: =K34*BD34 | BG34: =BE34-BF34 | BH34: 0 | BI34: =K34*BH34 | BK34: =BI34-BJ34 | BL34: 按实 | BM34: =BN34 | BO34: =BM34-BN34 | BP34: =N34+Q34+U34+Y34+AC34+AG34+AK34+AO34+AS34+AW34+BA34+BE34+BI34+BM34 | BQ34: =N34+R34+V34+Z34+AD34+AH34+AL34+AP34+AT34+AX34+BB34+BF34+BJ34+BN34 | BR34: =BP34-BQ34 | BS34: / | BT34: / | BU34: 1、装修折旧费：项目反馈不收取，包含在服务费中； | BV34: 1、签订期间：2025.9-2026.8； 2、指标按照全年换算；
A35: 47 | B35: KQCY0047 | C35: 餐饮二分部 | D35: CF125 | E35: 西浦大学宏愿食堂（南） | F35: 分组作业 | G35: 徐敏娟 | H35: / | I35: 烤肉 | J35: 杜松松 | K35: =LET(k,D35&"|"&E35&"|"&H35&"|"&I35&"|"&J35,sk,tblRevenueInput[项目代码]&"|"&tblRevenueInput[项目名称]&"|"&tblRevenueInput[分组作业名称]&"|"&tblRevenueInput[分组作业窗口名称]&"|"&tblRevenueInput[签订人],ok,tblRevenueOverride[项目代码]&"|"&tblRevenueOverride[项目名称]&"|"&tblRevenueOverride[分组作业名称]&"|"&tblRevenueOverride[分组作业窗口名称]&"|"&tblRevenueOverride[责任人],ov,IFERROR(XLOOKUP(k,ok,tblRevenueOverride[营业额覆盖],""),""),IF(ov<>"",ov,IFERROR(XLOOKUP(k,sk,tblRevenueInput[全额营业额合计],""),""))) | O35: 370000 | P35: 0.12 | Q35: =K35*P35 | S35: =Q35-R35 | T35: 按照实际收取 | U35: =V35 | W35: =U35-V35 | X35: 0.02 | Y35: =K35*X35 | AA35: =Y35-Z35 | AB35: 0 | AC35: =K35*AB35 | AE35: =AC35-AD35 | AF35: 0 | AG35: =K35*AF35 | AI35: =AG35-AH35 | AJ35: 0 | AK35: =K35*AJ35 | AM35: =AK35-AL35 | AN35: 0 | AO35: =K35*AN35 | AQ35: =AO35-AP35 | AR35: 按照实际收取 | AS35: =AT35 | AU35: =AS35-AT35 | AV35: 按照实际收取 | AW35: =AX35 | AY35: =AW35-AX35 | AZ35: 按实 | BA35: =BB35 | BC35: =BA35-BB35 | BD35: 0.035 | BE35: =K35*BD35 | BG35: =BE35-BF35 | BH35: 0 | BI35: =K35*BH35 | BK35: =BI35-BJ35 | BL35: 按实 | BM35: =BN35 | BO35: =BM35-BN35 | BP35: =N35+Q35+U35+Y35+AC35+AG35+AK35+AO35+AS35+AW35+BA35+BE35+BI35+BM35 | BQ35: =N35+R35+V35+Z35+AD35+AH35+AL35+AP35+AT35+AX35+BB35+BF35+BJ35+BN35 | BR35: =BP35-BQ35 | BS35: / | BT35: / | BU35: 1、装修折旧费：项目反馈不收取，包含在服务费中； | BV35: 1、签订期间：2025.9-2026.8； 2、指标按照全年换算；
A36: 48 | B36: KQCY0048 | C36: 餐饮二分部 | D36: CF125 | E36: 西浦大学宏愿食堂（南） | F36: 分组作业 | G36: 徐敏娟 | H36: / | I36: 粉丝汤 | J36: 李鑫 | K36: =LET(k,D36&"|"&E36&"|"&H36&"|"&I36&"|"&J36,sk,tblRevenueInput[项目代码]&"|"&tblRevenueInput[项目名称]&"|"&tblRevenueInput[分组作业名称]&"|"&tblRevenueInput[分组作业窗口名称]&"|"&tblRevenueInput[签订人],ok,tblRevenueOverride[项目代码]&"|"&tblRevenueOverride[项目名称]&"|"&tblRevenueOverride[分组作业名称]&"|"&tblRevenueOverride[分组作业窗口名称]&"|"&tblRevenueOverride[责任人],ov,IFERROR(XLOOKUP(k,ok,tblRevenueOverride[营业额覆盖],""),""),IF(ov<>"",ov,IFERROR(XLOOKUP(k,sk,tblRevenueInput[全额营业额合计],""),""))) | O36: 440000 | P36: 0.12 | Q36: =K36*P36 | S36: =Q36-R36 | T36: 按照实际收取 | U36: =V36 | W36: =U36-V36 | X36: 0.02 | Y36: =K36*X36 | AA36: =Y36-Z36 | AB36: 0 | AC36: =K36*AB36 | AE36: =AC36-AD36 | AF36: 0 | AG36: =K36*AF36 | AI36: =AG36-AH36 | AJ36: 0 | AK36: =K36*AJ36 | AM36: =AK36-AL36 | AN36: 0 | AO36: =K36*AN36 | AQ36: =AO36-AP36 | AR36: 按照实际收取 | AS36: =AT36 | AU36: =AS36-AT36 | AV36: 按照实际收取 | AW36: =AX36 | AY36: =AW36-AX36 | AZ36: 按实 | BA36: =BB36 | BC36: =BA36-BB36 | BD36: 0.035 | BE36: =K36*BD36 | BG36: =BE36-BF36 | BH36: 0 | BI36: =K36*BH36 | BK36: =BI36-BJ36 | BL36: 按实 | BM36: =BN36 | BO36: =BM36-BN36 | BP36: =N36+Q36+U36+Y36+AC36+AG36+AK36+AO36+AS36+AW36+BA36+BE36+BI36+BM36 | BQ36: =N36+R36+V36+Z36+AD36+AH36+AL36+AP36+AT36+AX36+BB36+BF36+BJ36+BN36 | BR36: =BP36-BQ36 | BS36: / | BT36: / | BU36: 1、装修折旧费：项目反馈不收取，包含在服务费中； | BV36: 1、签订期间：2025.9-2026.8； 2、指标按照全年换算；
A37: 50 | B37: KQCY0050 | C37: 餐饮二分部 | D37: CF137 | E37: 西浦大学宏愿食堂（北） | F37: 分组作业 | G37: 徐敏娟 | H37: / | I37: 滑蛋饭 | J37: 赵广伟 | K37: =LET(k,D37&"|"&E37&"|"&H37&"|"&I37&"|"&J37,sk,tblRevenueInput[项目代码]&"|"&tblRevenueInput[项目名称]&"|"&tblRevenueInput[分组作业名称]&"|"&tblRevenueInput[分组作业窗口名称]&"|"&tblRevenueInput[签订人],ok,tblRevenueOverride[项目代码]&"|"&tblRevenueOverride[项目名称]&"|"&tblRevenueOverride[分组作业名称]&"|"&tblRevenueOverride[分组作业窗口名称]&"|"&tblRevenueOverride[责任人],ov,IFERROR(XLOOKUP(k,ok,tblRevenueOverride[营业额覆盖],""),""),IF(ov<>"",ov,IFERROR(XLOOKUP(k,sk,tblRevenueInput[全额营业额合计],""),""))) | N37: 13454.15 | O37: 345000 | P37: 0.14 | Q37: =K37*P37 | R37: 0 | S37: =Q37-R37 | T37: 0 | U37: =K37*T37 | W37: =U37-V37 | X37: 0.02 | Y37: =K37*X37 | Z37: 0 | AA37: =Y37-Z37 | AB37: 0 | AC37: =K37*AB37 | AE37: =AC37-AD37 | AF37: 0 | AG37: =K37*AF37 | AI37: =AG37-AH37 | AJ37: 0 | AK37: =K37*AJ37 | AM37: =AK37-AL37 | AN37: 0 | AO37: =K37*AN37 | AQ37: =AO37-AP37 | AR37: 0.05 | AS37: =K37*AR37 | AT37: 0 | AU37: =AS37-AT37 | AV37: 0.06 | AW37: =K37*AV37 | AX37: 0 | AY37: =AW37-AX37 | AZ37: 0.01 | BA37: =K37*AZ37 | BB37: 0 | BC37: =BA37-BB37 | BD37: 0 | BE37: =K37*BD37 | BG37: =BE37-BF37 | BH37: 0 | BI37: =K37*BH37 | BK37: =BI37-BJ37 | BL37: 按实 | BM37: =BN37 | BN37: 0 | BO37: =BM37-BN37 | BP37: =N37+Q37+U37+Y37+AC37+AG37+AK37+AO37+AS37+AW37+BA37+BE37+BI37+BM37 | BQ37: =N37+R37+V37+Z37+AD37+AH37+AL37+AP37+AT37+AX37+BB37+BF37+BJ37+BN37 | BR37: =BP37-BQ37 | BS37: / | BT37: / | BU37: 1、装修折旧费：项目反馈不收取，包含在服务费中； 2、甲方房租：项目反馈不收取，包含在服务费中； | BV37: 1、签订期间：2025.10-2026.9； 2、指标按照全年换算；
A38: 51 | B38: KQCY0051 | C38: 餐饮二分部 | D38: CF137 | E38: 西浦大学宏愿食堂（北） | F38: 分组作业 | G38: 徐敏娟 | H38: / | I38: 手工水饺 | J38: 赵玉才 | K38: =LET(k,D38&"|"&E38&"|"&H38&"|"&I38&"|"&J38,sk,tblRevenueInput[项目代码]&"|"&tblRevenueInput[项目名称]&"|"&tblRevenueInput[分组作业名称]&"|"&tblRevenueInput[分组作业窗口名称]&"|"&tblRevenueInput[签订人],ok,tblRevenueOverride[项目代码]&"|"&tblRevenueOverride[项目名称]&"|"&tblRevenueOverride[分组作业名称]&"|"&tblRevenueOverride[分组作业窗口名称]&"|"&tblRevenueOverride[责任人],ov,IFERROR(XLOOKUP(k,ok,tblRevenueOverride[营业额覆盖],""),""),IF(ov<>"",ov,IFERROR(XLOOKUP(k,sk,tblRevenueInput[全额营业额合计],""),""))) | O38: 475000 | P38: 0.14 | Q38: =K38*P38 | S38: =Q38-R38 | T38: 0 | U38: =K38*T38 | W38: =U38-V38 | X38: 0.02 | Y38: =K38*X38 | AA38: =Y38-Z38 | AB38: 0 | AC38: =K38*AB38 | AE38: =AC38-AD38 | AF38: 0 | AG38: =K38*AF38 | AI38: =AG38-AH38 | AJ38: 0 | AK38: =K38*AJ38 | AM38: =AK38-AL38 | AN38: 0 | AO38: =K38*AN38 | AQ38: =AO38-AP38 | AR38: 0.05 | AS38: =K38*AR38 | AU38: =AS38-AT38 | AV38: 0.06 | AW38: =K38*AV38 | AY38: =AW38-AX38 | AZ38: 0.01 | BA38: =K38*AZ38 | BC38: =BA38-BB38 | BD38: 0 | BE38: =K38*BD38 | BG38: =BE38-BF38 | BH38: 0 | BI38: =K38*BH38 | BK38: =BI38-BJ38 | BL38: 按实 | BM38: =BN38 | BO38: =BM38-BN38 | BP38: =N38+Q38+U38+Y38+AC38+AG38+AK38+AO38+AS38+AW38+BA38+BE38+BI38+BM38 | BQ38: =N38+R38+V38+Z38+AD38+AH38+AL38+AP38+AT38+AX38+BB38+BF38+BJ38+BN38 | BR38: =BP38-BQ38 | BS38: / | BT38: / | BU38: 1、装修折旧费：项目反馈不收取，包含在服务费中； 2、甲方房租：项目反馈不收取，包含在服务费中； | BV38: 1、签订期间：2025.10-2026.9； 2、指标按照全年换算；
A39: 52 | B39: KQCY0052 | C39: 餐饮二分部 | D39: CF137 | E39: 西浦大学宏愿食堂（北） | F39: 分组作业 | G39: 徐敏娟 | H39: / | I39: 烤盘饭 | J39: 付昌杰 | K39: =LET(k,D39&"|"&E39&"|"&H39&"|"&I39&"|"&J39,sk,tblRevenueInput[项目代码]&"|"&tblRevenueInput[项目名称]&"|"&tblRevenueInput[分组作业名称]&"|"&tblRevenueInput[分组作业窗口名称]&"|"&tblRevenueInput[签订人],ok,tblRevenueOverride[项目代码]&"|"&tblRevenueOverride[项目名称]&"|"&tblRevenueOverride[分组作业名称]&"|"&tblRevenueOverride[分组作业窗口名称]&"|"&tblRevenueOverride[责任人],ov,IFERROR(XLOOKUP(k,ok,tblRevenueOverride[营业额覆盖],""),""),IF(ov<>"",ov,IFERROR(XLOOKUP(k,sk,tblRevenueInput[全额营业额合计],""),""))) | O39: 875000 | P39: 0.14 | Q39: =K39*P39 | S39: =Q39-R39 | T39: 0 | U39: =K39*T39 | W39: =U39-V39 | X39: 0.02 | Y39: =K39*X39 | AA39: =Y39-Z39 | AB39: 0 | AC39: =K39*AB39 | AE39: =AC39-AD39 | AF39: 0 | AG39: =K39*AF39 | AI39: =AG39-AH39 | AJ39: 0 | AK39: =K39*AJ39 | AM39: =AK39-AL39 | AN39: 0 | AO39: =K39*AN39 | AQ39: =AO39-AP39 | AR39: 0.05 | AS39: =K39*AR39 | AU39: =AS39-AT39 | AV39: 0.06 | AW39: =K39*AV39 | AY39: =AW39-AX39 | AZ39: 0.01 | BA39: =K39*AZ39 | BC39: =BA39-BB39 | BD39: 0 | BE39: =K39*BD39 | BG39: =BE39-BF39 | BH39: 0 | BI39: =K39*BH39 | BK39: =BI39-BJ39 | BL39: 按实 | BM39: =BN39 | BO39: =BM39-BN39 | BP39: =N39+Q39+U39+Y39+AC39+AG39+AK39+AO39+AS39+AW39+BA39+BE39+BI39+BM39 | BQ39: =N39+R39+V39+Z39+AD39+AH39+AL39+AP39+AT39+AX39+BB39+BF39+BJ39+BN39 | BR39: =BP39-BQ39 | BS39: / | BT39: / | BU39: 1、装修折旧费：项目反馈不收取，包含在服务费中； 2、甲方房租：项目反馈不收取，包含在服务费中； | BV39: 1、签订期间：2025.10-2026.9； 2、指标按照全年换算；
A40: 53 | B40: KQCY0053 | C40: 餐饮二分部 | D40: CF137 | E40: 西浦大学宏愿食堂（北） | F40: 分组作业 | G40: 徐敏娟 | H40: / | I40: 大花米线 | J40: 钱卫军 | K40: =LET(k,D40&"|"&E40&"|"&H40&"|"&I40&"|"&J40,sk,tblRevenueInput[项目代码]&"|"&tblRevenueInput[项目名称]&"|"&tblRevenueInput[分组作业名称]&"|"&tblRevenueInput[分组作业窗口名称]&"|"&tblRevenueInput[签订人],ok,tblRevenueOverride[项目代码]&"|"&tblRevenueOverride[项目名称]&"|"&tblRevenueOverride[分组作业名称]&"|"&tblRevenueOverride[分组作业窗口名称]&"|"&tblRevenueOverride[责任人],ov,IFERROR(XLOOKUP(k,ok,tblRevenueOverride[营业额覆盖],""),""),IF(ov<>"",ov,IFERROR(XLOOKUP(k,sk,tblRevenueInput[全额营业额合计],""),""))) | O40: 485000 | P40: 0.14 | Q40: =K40*P40 | S40: =Q40-R40 | T40: 0 | U40: =K40*T40 | W40: =U40-V40 | X40: 0.02 | Y40: =K40*X40 | AA40: =Y40-Z40 | AB40: 0 | AC40: =K40*AB40 | AE40: =AC40-AD40 | AF40: 0 | AG40: =K40*AF40 | AI40: =AG40-AH40 | AJ40: 0 | AK40: =K40*AJ40 | AM40: =AK40-AL40 | AN40: 0 | AO40: =K40*AN40 | AQ40: =AO40-AP40 | AR40: 0.05 | AS40: =K40*AR40 | AU40: =AS40-AT40 | AV40: 0.06 | AW40: =K40*AV40 | AY40: =AW40-AX40 | AZ40: 0.01 | BA40: =K40*AZ40 | BC40: =BA40-BB40 | BD40: 0 | BE40: =K40*BD40 | BG40: =BE40-BF40 | BH40: 0 | BI40: =K40*BH40 | BK40: =BI40-BJ40 | BL40: 按实 | BM40: =BN40 | BO40: =BM40-BN40 | BP40: =N40+Q40+U40+Y40+AC40+AG40+AK40+AO40+AS40+AW40+BA40+BE40+BI40+BM40 | BQ40: =N40+R40+V40+Z40+AD40+AH40+AL40+AP40+AT40+AX40+BB40+BF40+BJ40+BN40 | BR40: =BP40-BQ40 | BS40: / | BT40: / | BU40: 1、装修折旧费：项目反馈不收取，包含在服务费中； 2、甲方房租：项目反馈不收取，包含在服务费中； | BV40: 1、签订期间：2025.10-2026.9； 2、指标按照全年换算；
A41: 54 | B41: KQCY0054 | C41: 餐饮二分部 | D41: CF137 | E41: 西浦大学宏愿食堂（北） | F41: 分组作业 | G41: 徐敏娟 | H41: / | I41: 石锅饭 | J41: 葛颖 | K41: =LET(k,D41&"|"&E41&"|"&H41&"|"&I41&"|"&J41,sk,tblRevenueInput[项目代码]&"|"&tblRevenueInput[项目名称]&"|"&tblRevenueInput[分组作业名称]&"|"&tblRevenueInput[分组作业窗口名称]&"|"&tblRevenueInput[签订人],ok,tblRevenueOverride[项目代码]&"|"&tblRevenueOverride[项目名称]&"|"&tblRevenueOverride[分组作业名称]&"|"&tblRevenueOverride[分组作业窗口名称]&"|"&tblRevenueOverride[责任人],ov,IFERROR(XLOOKUP(k,ok,tblRevenueOverride[营业额覆盖],""),""),IF(ov<>"",ov,IFERROR(XLOOKUP(k,sk,tblRevenueInput[全额营业额合计],""),""))) | O41: 600000 | P41: 0.14 | Q41: =K41*P41 | S41: =Q41-R41 | T41: 0 | U41: =K41*T41 | W41: =U41-V41 | X41: 0.02 | Y41: =K41*X41 | AA41: =Y41-Z41 | AB41: 0 | AC41: =K41*AB41 | AE41: =AC41-AD41 | AF41: 0 | AG41: =K41*AF41 | AI41: =AG41-AH41 | AJ41: 0 | AK41: =K41*AJ41 | AM41: =AK41-AL41 | AN41: 0 | AO41: =K41*AN41 | AQ41: =AO41-AP41 | AR41: 0.05 | AS41: =K41*AR41 | AU41: =AS41-AT41 | AV41: 0.06 | AW41: =K41*AV41 | AY41: =AW41-AX41 | AZ41: 0.01 | BA41: =K41*AZ41 | BC41: =BA41-BB41 | BD41: 0 | BE41: =K41*BD41 | BG41: =BE41-BF41 | BH41: 0 | BI41: =K41*BH41 | BK41: =BI41-BJ41 | BL41: 按实 | BM41: =BN41 | BO41: =BM41-BN41 | BP41: =N41+Q41+U41+Y41+AC41+AG41+AK41+AO41+AS41+AW41+BA41+BE41+BI41+BM41 | BQ41: =N41+R41+V41+Z41+AD41+AH41+AL41+AP41+AT41+AX41+BB41+BF41+BJ41+BN41 | BR41: =BP41-BQ41 | BS41: / | BT41: / | BU41: 1、装修折旧费：项目反馈不收取，包含在服务费中； 2、甲方房租：项目反馈不收取，包含在服务费中； | BV41: 1、签订期间：2025.10-2026.9； 2、指标按照全年换算；
A42: 55 | B42: KQCY0055 | C42: 餐饮二分部 | D42: CF137 | E42: 西浦大学宏愿食堂（北） | F42: 分组作业 | G42: 徐敏娟 | H42: / | I42: 一鸣鲜奶吧 | J42: 黎欢 | K42: =LET(k,D42&"|"&E42&"|"&H42&"|"&I42&"|"&J42,sk,tblRevenueInput[项目代码]&"|"&tblRevenueInput[项目名称]&"|"&tblRevenueInput[分组作业名称]&"|"&tblRevenueInput[分组作业窗口名称]&"|"&tblRevenueInput[签订人],ok,tblRevenueOverride[项目代码]&"|"&tblRevenueOverride[项目名称]&"|"&tblRevenueOverride[分组作业名称]&"|"&tblRevenueOverride[分组作业窗口名称]&"|"&tblRevenueOverride[责任人],ov,IFERROR(XLOOKUP(k,ok,tblRevenueOverride[营业额覆盖],""),""),IF(ov<>"",ov,IFERROR(XLOOKUP(k,sk,tblRevenueInput[全额营业额合计],""),""))) | O42: 615000 | P42: 0 | Q42: =K42*P42 | S42: =Q42-R42 | T42: 0 | U42: =K42*T42 | W42: =U42-V42 | X42: 0 | Y42: =K42*X42 | AA42: =Y42-Z42 | AB42: 0 | AC42: =K42*AB42 | AE42: =AC42-AD42 | AF42: 0 | AG42: =K42*AF42 | AI42: =AG42-AH42 | AJ42: 0 | AK42: =K42*AJ42 | AM42: =AK42-AL42 | AN42: 0 | AO42: =K42*AN42 | AQ42: =AO42-AP42 | AR42: 0.03 | AS42: =K42*AR42 | AU42: =AS42-AT42 | AV42: 0.05 | AW42: =K42*AV42 | AY42: =AW42-AX42 | AZ42: 0.005 | BA42: =K42*AZ42 | BC42: =BA42-BB42 | BD42: 15000 | BE42: =15000 | BF42: 0 | BG42: =BE42-BF42 | BH42: 0 | BI42: =K42*BH42 | BK42: =BI42-BJ42 | BL42: 按实 | BM42: =BN42 | BO42: =BM42-BN42 | BP42: =N42+Q42+U42+Y42+AC42+AG42+AK42+AO42+AS42+AW42+BA42+BE42+BI42+BM42 | BQ42: =N42+R42+V42+Z42+AD42+AH42+AL42+AP42+AT42+AX42+BB42+BF42+BJ42+BN42 | BR42: =BP42-BQ42 | BS42: / | BT42: / | BU42: 1、服务费：12万/年；固定租金12万元/年，除1、2、7、8月外每月1.5万元 2、采购费：项目反馈不收取，包含在服务费中； 3、装修折旧费：项目反馈不收取，包含在服务费中； 4、甲方房租：项目反馈不收取，包含在服务费中； | BV42: 1、签订期间：2025.10-2026.9； 2、指标按照全年换算；
A43: 57 | B43: KQCY0057 | C43: 餐饮二分部 | D43: CF140 | E43: 西浦大学太仓校区食堂 | F43: 分组作业 | G43: 徐敏娟 | H43: 第一班组 | I43: 蛋包饭(肥牛米线、水饺、烤盘饭) | J43: 赵广伟 | K43: =LET(k,D43&"|"&E43&"|"&H43&"|"&I43&"|"&J43,sk,tblRevenueInput[项目代码]&"|"&tblRevenueInput[项目名称]&"|"&tblRevenueInput[分组作业名称]&"|"&tblRevenueInput[分组作业窗口名称]&"|"&tblRevenueInput[签订人],ok,tblRevenueOverride[项目代码]&"|"&tblRevenueOverride[项目名称]&"|"&tblRevenueOverride[分组作业名称]&"|"&tblRevenueOverride[分组作业窗口名称]&"|"&tblRevenueOverride[责任人],ov,IFERROR(XLOOKUP(k,ok,tblRevenueOverride[营业额覆盖],""),""),IF(ov<>"",ov,IFERROR(XLOOKUP(k,sk,tblRevenueInput[全额营业额合计],""),""))) | N43: 21285.63 | O43: 450000 | P43: 0.03 | Q43: =K43*P43 | R43: 1982 | S43: =Q43-R43 | T43: 0 | U43: =K43*T43 | W43: =U43-V43 | X43: 0.02 | Y43: =K43*X43 | Z43: 1321.34 | AA43: =Y43-Z43 | AB43: 0 | AC43: =K43*AB43 | AE43: =AC43-AD43 | AF43: 0 | AG43: =K43*AF43 | AI43: =AG43-AH43 | AJ43: 0 | AK43: =K43*AJ43 | AM43: =AK43-AL43 | AN43: 0 | AO43: =K43*AN43 | AQ43: =AO43-AP43 | AR43: 0.02 | AS43: =K43*AR43 | AT43: 1321.34 | AU43: =AS43-AT43 | AV43: 0 | AW43: =K43*AV43 | AY43: =AW43-AX43 | AZ43: 按实 | BA43: =BB43 | BC43: =BA43-BB43 | BD43: 0.01 | BE43: =K43*BD43 | BF43: 660.67 | BG43: =BE43-BF43 | BH43: 0 | BI43: =K43*BH43 | BK43: =BI43-BJ43 | BL43: 按实 | BM43: =BN43 | BN43: 26188.37 | BO43: =BM43-BN43 | BP43: =N43+Q43+U43+Y43+AC43+AG43+AK43+AO43+AS43+AW43+BA43+BE43+BI43+BM43 | BQ43: =N43+R43+V43+Z43+AD43+AH43+AL43+AP43+AT43+AX43+BB43+BF43+BJ43+BN43 | BR43: =BP43-BQ43 | BS43: / | BT43: / | BU43: 1、虫害消杀：项目反馈不收取，包含在服务费中； 2、卫生费：项目反馈不收取，包含在服务费中； | BV43: 1、签订期间：2025.9-2026.8； 2、指标按照全年换算；
A44: 58 | B44: KQCY0058 | C44: 餐饮二分部 | D44: CF140 | E44: 西浦大学太仓校区食堂 | F44: 分组作业 | G44: 徐敏娟 | H44: 第二班组 | I44: 枣糕&热饮(韩式拌饭) | J44: 杜松松 | K44: =LET(k,D44&"|"&E44&"|"&H44&"|"&I44&"|"&J44,sk,tblRevenueInput[项目代码]&"|"&tblRevenueInput[项目名称]&"|"&tblRevenueInput[分组作业名称]&"|"&tblRevenueInput[分组作业窗口名称]&"|"&tblRevenueInput[签订人],ok,tblRevenueOverride[项目代码]&"|"&tblRevenueOverride[项目名称]&"|"&tblRevenueOverride[分组作业名称]&"|"&tblRevenueOverride[分组作业窗口名称]&"|"&tblRevenueOverride[责任人],ov,IFERROR(XLOOKUP(k,ok,tblRevenueOverride[营业额覆盖],""),""),IF(ov<>"",ov,IFERROR(XLOOKUP(k,sk,tblRevenueInput[全额营业额合计],""),""))) | O44: 145000 | P44: 0.03 | Q44: =K44*P44 | S44: =Q44-R44 | T44: 0 | U44: =K44*T44 | W44: =U44-V44 | X44: 0.02 | Y44: =K44*X44 | AA44: =Y44-Z44 | AB44: 0 | AC44: =K44*AB44 | AE44: =AC44-AD44 | AF44: 0 | AG44: =K44*AF44 | AI44: =AG44-AH44 | AJ44: 0 | AK44: =K44*AJ44 | AM44: =AK44-AL44 | AN44: 0 | AO44: =K44*AN44 | AQ44: =AO44-AP44 | AR44: 0.02 | AS44: =K44*AR44 | AU44: =AS44-AT44 | AV44: 0 | AW44: =K44*AV44 | AY44: =AW44-AX44 | AZ44: 按实 | BA44: =BB44 | BC44: =BA44-BB44 | BD44: 0.01 | BE44: =K44*BD44 | BG44: =BE44-BF44 | BH44: 0 | BI44: =K44*BH44 | BK44: =BI44-BJ44 | BL44: 按实 | BM44: =BN44 | BO44: =BM44-BN44 | BP44: =N44+Q44+U44+Y44+AC44+AG44+AK44+AO44+AS44+AW44+BA44+BE44+BI44+BM44 | BQ44: =N44+R44+V44+Z44+AD44+AH44+AL44+AP44+AT44+AX44+BB44+BF44+BJ44+BN44 | BR44: =BP44-BQ44 | BS44: / | BT44: / | BU44: 1、虫害消杀：项目反馈不收取，包含在服务费中； 2、卫生费：项目反馈不收取，包含在服务费中； | BV44: 1、签订期间：2025.9-2026.8； 2、指标按照全年换算；
A45: 60 | B45: KQCY0060 | C45: 餐饮二分部 | D45: CF182 | E45: 无锡工艺第二食堂 | F45: 分组作业 | G45: 徐敏娟 | H45: / | I45: 快餐 | J45: 林见锋 | K45: =LET(k,D45&"|"&E45&"|"&H45&"|"&I45&"|"&J45,sk,tblRevenueInput[项目代码]&"|"&tblRevenueInput[项目名称]&"|"&tblRevenueInput[分组作业名称]&"|"&tblRevenueInput[分组作业窗口名称]&"|"&tblRevenueInput[签订人],ok,tblRevenueOverride[项目代码]&"|"&tblRevenueOverride[项目名称]&"|"&tblRevenueOverride[分组作业名称]&"|"&tblRevenueOverride[分组作业窗口名称]&"|"&tblRevenueOverride[责任人],ov,IFERROR(XLOOKUP(k,ok,tblRevenueOverride[营业额覆盖],""),""),IF(ov<>"",ov,IFERROR(XLOOKUP(k,sk,tblRevenueInput[全额营业额合计],""),""))) | N45: 19888.37 | O45: 6000000 | P45: 0.035 | Q45: =(K45+K46+K48+K49+K50+K51+K52+K53)*P45-R46 | R45: 0 | S45: =Q45-R45 | T45: 按实 | U45: =V45 | V45: 0 | W45: =U45-V45 | X45: 0 | Y45: =K45*X45 | AA45: =Y45-Z45 | AB45: 165万元分3年分摊，多退少补 | AC45: =AD45 | AD45: 0 | AE45: =AC45-AD45 | AF45: 一名管理人员费用，按实际产生费用列入项目处成本 | AG45: =AH45 | AI45: =AG45-AH45 | AJ45: 0 | AK45: =K45*AJ45 | AM45: =AK45-AL45 | AN45: 0 | AO45: =K45*AN45 | AQ45: =AO45-AP45 | AR45: 0 | AS45: =K45*AR45 | AU45: =AS45-AT45 | AV45: 按实 | AW45: =AX45 | AX45: 0 | AY45: =AW45-AX45 | AZ45: 按实 | BA45: =BB45 | BC45: =BA45-BB45 | BD45: 排烟机清洗费：按实 | BE45: =BF45 | BG45: =BE45-BF45 | BH45: 0 | BI45: =K45*BH45 | BK45: =BI45-BJ45 | BL45: 按实 | BM45: =BN45 | BN45: 0 | BO45: =BM45-BN45 | BP45: =N45+Q45+U45+Y45+AC45+AG45+AK45+AO45+AS45+AW45+BA45+BE45+BI45+BM45 | BQ45: =N45+R45+V45+Z45+AD45+AH45+AL45+AP45+AT45+AX45+BB45+BF45+BJ45+BN45 | BR45: =BP45-BQ45 | BS45: / | BT45: / | BU45: 1、装修折旧费：按165万，分三年期限分摊，多退少补 | BV45: 1、签订期间：2026.1-2026.12； 2、指标按照全年换算；
A46: 61 | B46: KQCY0061 | C46: 餐饮二分部 | D46: CF182 | E46: 无锡工艺第二食堂 | F46: 分组作业 | G46: 徐敏娟 | H46: 第二班组 | I46: 烤鸭饭 | J46: 徐其国 | K46: =LET(k,D46&"|"&E46&"|"&H46&"|"&I46&"|"&J46,sk,tblRevenueInput[项目代码]&"|"&tblRevenueInput[项目名称]&"|"&tblRevenueInput[分组作业名称]&"|"&tblRevenueInput[分组作业窗口名称]&"|"&tblRevenueInput[签订人],ok,tblRevenueOverride[项目代码]&"|"&tblRevenueOverride[项目名称]&"|"&tblRevenueOverride[分组作业名称]&"|"&tblRevenueOverride[分组作业窗口名称]&"|"&tblRevenueOverride[责任人],ov,IFERROR(XLOOKUP(k,ok,tblRevenueOverride[营业额覆盖],""),""),IF(ov<>"",ov,IFERROR(XLOOKUP(k,sk,tblRevenueInput[全额营业额合计],""),""))) | P46: 0.26 | Q46: =K46*P46 | S46: =Q46-R46 | T46: 0 | U46: =K46*T46 | W46: =U46-V46 | X46: 0 | Y46: =K46*X46 | AA46: =Y46-Z46 | AB46: 0 | AC46: =K46*AB46 | AE46: =AC46-AD46 | AF46: 0 | AG46: =K46*AF46 | AI46: =AG46-AH46 | AJ46: 0 | AK46: =K46*AJ46 | AM46: =AK46-AL46 | AN46: 0 | AO46: =K46*AN46 | AQ46: =AO46-AP46 | AR46: 0 | AS46: =K46*AR46 | AU46: =AS46-AT46 | AV46: 0 | AW46: =K46*AV46 | AY46: =AW46-AX46 | AZ46: 按实 | BA46: =BB46 | BC46: =BA46-BB46 | BD46: 排烟机清洗费：0 | BE46: =BF46 | BG46: =BE46-BF46 | BH46: 0 | BI46: =K46*BH46 | BK46: =BI46-BJ46 | BL46: 按实 | BM46: =BN46 | BN46: 0 | BO46: =BM46-BN46 | BP46: =N46+Q46+U46+Y46+AC46+AG46+AK46+AO46+AS46+AW46+BA46+BE46+BI46+BM46 | BQ46: =N46+R46+V46+Z46+AD46+AH46+AL46+AP46+AT46+AX46+BB46+BF46+BJ46+BN46 | BR46: =BP46-BQ46
A47: 62 | B47: KQCY0062 | C47: 餐饮二分部 | D47: CF182 | E47: 无锡工艺第二食堂 | F47: 分组作业 | G47: 徐敏娟 | H47: 第三班组 | I47: 营养粥、小笼包 | J47: 朱德保 | K47: =LET(k,D47&"|"&E47&"|"&H47&"|"&I47&"|"&J47,sk,tblRevenueInput[项目代码]&"|"&tblRevenueInput[项目名称]&"|"&tblRevenueInput[分组作业名称]&"|"&tblRevenueInput[分组作业窗口名称]&"|"&tblRevenueInput[签订人],ok,tblRevenueOverride[项目代码]&"|"&tblRevenueOverride[项目名称]&"|"&tblRevenueOverride[分组作业名称]&"|"&tblRevenueOverride[分组作业窗口名称]&"|"&tblRevenueOverride[责任人],ov,IFERROR(XLOOKUP(k,ok,tblRevenueOverride[营业额覆盖],""),""),IF(ov<>"",ov,IFERROR(XLOOKUP(k,sk,tblRevenueInput[全额营业额合计],""),""))) | P47: 0.28 | Q47: =K47*P47 | S47: =Q47-R47 | T47: 0 | U47: =K47*T47 | W47: =U47-V47 | X47: 0 | Y47: =K47*X47 | AA47: =Y47-Z47 | AB47: 0 | AC47: =K47*AB47 | AE47: =AC47-AD47 | AF47: 0 | AG47: =K47*AF47 | AI47: =AG47-AH47 | AJ47: 0 | AK47: =K47*AJ47 | AM47: =AK47-AL47 | AN47: 0 | AO47: =K47*AN47 | AQ47: =AO47-AP47 | AR47: 0 | AS47: =K47*AR47 | AU47: =AS47-AT47 | AV47: 0 | AW47: =K47*AV47 | AY47: =AW47-AX47 | AZ47: 按实 | BA47: =BB47 | BC47: =BA47-BB47 | BD47: 0 | BE47: =K47*BD47 | BG47: =BE47-BF47 | BH47: 0 | BI47: =K47*BH47 | BK47: =BI47-BJ47 | BL47: 按实 | BM47: =BN47 | BO47: =BM47-BN47 | BP47: =N47+Q47+U47+Y47+AC47+AG47+AK47+AO47+AS47+AW47+BA47+BE47+BI47+BM47 | BQ47: =N47+R47+V47+Z47+AD47+AH47+AL47+AP47+AT47+AX47+BB47+BF47+BJ47+BN47 | BR47: =BP47-BQ47
A48: 63 | B48: KQCY0063 | C48: 餐饮二分部 | D48: CF182 | E48: 无锡工艺第二食堂 | F48: 分组作业 | G48: 徐敏娟 | H48: 第四班组 | I48: 武汉热干面、隆江猪脚饭 | J48: 田振 | K48: =LET(k,D48&"|"&E48&"|"&H48&"|"&I48&"|"&J48,sk,tblRevenueInput[项目代码]&"|"&tblRevenueInput[项目名称]&"|"&tblRevenueInput[分组作业名称]&"|"&tblRevenueInput[分组作业窗口名称]&"|"&tblRevenueInput[签订人],ok,tblRevenueOverride[项目代码]&"|"&tblRevenueOverride[项目名称]&"|"&tblRevenueOverride[分组作业名称]&"|"&tblRevenueOverride[分组作业窗口名称]&"|"&tblRevenueOverride[责任人],ov,IFERROR(XLOOKUP(k,ok,tblRevenueOverride[营业额覆盖],""),""),IF(ov<>"",ov,IFERROR(XLOOKUP(k,sk,tblRevenueInput[全额营业额合计],""),""))) | P48: 0.27 | Q48: =K48*P48 | S48: =Q48-R48 | T48: 0 | U48: =K48*T48 | W48: =U48-V48 | X48: 0 | Y48: =K48*X48 | AA48: =Y48-Z48 | AB48: 0 | AC48: =K48*AB48 | AE48: =AC48-AD48 | AF48: 0 | AG48: =K48*AF48 | AI48: =AG48-AH48 | AJ48: 0 | AK48: =K48*AJ48 | AM48: =AK48-AL48 | AN48: 0 | AO48: =K48*AN48 | AQ48: =AO48-AP48 | AR48: 0 | AS48: =K48*AR48 | AU48: =AS48-AT48 | AV48: 0 | AW48: =K48*AV48 | AY48: =AW48-AX48 | AZ48: 按实 | BA48: =BB48 | BC48: =BA48-BB48 | BD48: 0 | BE48: =K48*BD48 | BG48: =BE48-BF48 | BH48: 0 | BI48: =K48*BH48 | BK48: =BI48-BJ48 | BL48: 按实 | BM48: =BN48 | BO48: =BM48-BN48 | BP48: =N48+Q48+U48+Y48+AC48+AG48+AK48+AO48+AS48+AW48+BA48+BE48+BI48+BM48 | BQ48: =N48+R48+V48+Z48+AD48+AH48+AL48+AP48+AT48+AX48+BB48+BF48+BJ48+BN48 | BR48: =BP48-BQ48
A49: 64 | B49: KQCY0064 | C49: 餐饮二分部 | D49: CF182 | E49: 无锡工艺第二食堂 | F49: 分组作业 | G49: 徐敏娟 | H49: 第六班组 | I49: 称重水饺、馄饨 | J49: 张宜轩 | K49: =LET(k,D49&"|"&E49&"|"&H49&"|"&I49&"|"&J49,sk,tblRevenueInput[项目代码]&"|"&tblRevenueInput[项目名称]&"|"&tblRevenueInput[分组作业名称]&"|"&tblRevenueInput[分组作业窗口名称]&"|"&tblRevenueInput[签订人],ok,tblRevenueOverride[项目代码]&"|"&tblRevenueOverride[项目名称]&"|"&tblRevenueOverride[分组作业名称]&"|"&tblRevenueOverride[分组作业窗口名称]&"|"&tblRevenueOverride[责任人],ov,IFERROR(XLOOKUP(k,ok,tblRevenueOverride[营业额覆盖],""),""),IF(ov<>"",ov,IFERROR(XLOOKUP(k,sk,tblRevenueInput[全额营业额合计],""),""))) | P49: 0.28 | Q49: =K49*P49 | S49: =Q49-R49 | T49: 0 | U49: =K49*T49 | W49: =U49-V49 | X49: 0 | Y49: =K49*X49 | AA49: =Y49-Z49 | AB49: 0 | AC49: =K49*AB49 | AE49: =AC49-AD49 | AF49: 0 | AG49: =K49*AF49 | AI49: =AG49-AH49 | AJ49: 0 | AK49: =K49*AJ49 | AM49: =AK49-AL49 | AN49: 0 | AO49: =K49*AN49 | AQ49: =AO49-AP49 | AR49: 0 | AS49: =K49*AR49 | AU49: =AS49-AT49 | AV49: 0 | AW49: =K49*AV49 | AY49: =AW49-AX49 | AZ49: 按实 | BA49: =BB49 | BC49: =BA49-BB49 | BD49: 0 | BE49: =K49*BD49 | BG49: =BE49-BF49 | BH49: 0 | BI49: =K49*BH49 | BK49: =BI49-BJ49 | BL49: 按实 | BM49: =BN49 | BO49: =BM49-BN49 | BP49: =N49+Q49+U49+Y49+AC49+AG49+AK49+AO49+AS49+AW49+BA49+BE49+BI49+BM49 | BQ49: =N49+R49+V49+Z49+AD49+AH49+AL49+AP49+AT49+AX49+BB49+BF49+BJ49+BN49 | BR49: =BP49-BQ49
A50: 65 | B50: KQCY0065 | C50: 餐饮二分部 | D50: CF182 | E50: 无锡工艺第二食堂 | F50: 分组作业 | G50: 徐敏娟 | H50: 第七班组 | I50: 掉渣饼、徐州米线、鸡汤饭 | J50: 武玉柳 | K50: =LET(k,D50&"|"&E50&"|"&H50&"|"&I50&"|"&J50,sk,tblRevenueInput[项目代码]&"|"&tblRevenueInput[项目名称]&"|"&tblRevenueInput[分组作业名称]&"|"&tblRevenueInput[分组作业窗口名称]&"|"&tblRevenueInput[签订人],ok,tblRevenueOverride[项目代码]&"|"&tblRevenueOverride[项目名称]&"|"&tblRevenueOverride[分组作业名称]&"|"&tblRevenueOverride[分组作业窗口名称]&"|"&tblRevenueOverride[责任人],ov,IFERROR(XLOOKUP(k,ok,tblRevenueOverride[营业额覆盖],""),""),IF(ov<>"",ov,IFERROR(XLOOKUP(k,sk,tblRevenueInput[全额营业额合计],""),""))) | P50: 0.28 | Q50: =K50*P50 | S50: =Q50-R50 | T50: 0 | U50: =K50*T50 | W50: =U50-V50 | X50: 0 | Y50: =K50*X50 | AA50: =Y50-Z50 | AB50: 0 | AC50: =K50*AB50 | AE50: =AC50-AD50 | AF50: 0 | AG50: =K50*AF50 | AI50: =AG50-AH50 | AJ50: 0 | AK50: =K50*AJ50 | AM50: =AK50-AL50 | AN50: 0 | AO50: =K50*AN50 | AQ50: =AO50-AP50 | AR50: 0 | AS50: =K50*AR50 | AU50: =AS50-AT50 | AV50: 0 | AW50: =K50*AV50 | AY50: =AW50-AX50 | AZ50: 按实 | BA50: =BB50 | BC50: =BA50-BB50 | BD50: 0 | BE50: =K50*BD50 | BG50: =BE50-BF50 | BH50: 0 | BI50: =K50*BH50 | BK50: =BI50-BJ50 | BL50: 按实 | BM50: =BN50 | BO50: =BM50-BN50 | BP50: =N50+Q50+U50+Y50+AC50+AG50+AK50+AO50+AS50+AW50+BA50+BE50+BI50+BM50 | BQ50: =N50+R50+V50+Z50+AD50+AH50+AL50+AP50+AT50+AX50+BB50+BF50+BJ50+BN50 | BR50: =BP50-BQ50
A51: 66 | B51: KQCY0066 | C51: 餐饮二分部 | D51: CF182 | E51: 无锡工艺第二食堂 | F51: 分组作业 | G51: 徐敏娟 | H51: 第八班组 | I51: 爆炒盖浇饭、套餐饭 | J51: 赵裕旭 | K51: =LET(k,D51&"|"&E51&"|"&H51&"|"&I51&"|"&J51,sk,tblRevenueInput[项目代码]&"|"&tblRevenueInput[项目名称]&"|"&tblRevenueInput[分组作业名称]&"|"&tblRevenueInput[分组作业窗口名称]&"|"&tblRevenueInput[签订人],ok,tblRevenueOverride[项目代码]&"|"&tblRevenueOverride[项目名称]&"|"&tblRevenueOverride[分组作业名称]&"|"&tblRevenueOverride[分组作业窗口名称]&"|"&tblRevenueOverride[责任人],ov,IFERROR(XLOOKUP(k,ok,tblRevenueOverride[营业额覆盖],""),""),IF(ov<>"",ov,IFERROR(XLOOKUP(k,sk,tblRevenueInput[全额营业额合计],""),""))) | P51: 0.28 | Q51: =K51*P51 | S51: =Q51-R51 | T51: 0 | U51: =K51*T51 | W51: =U51-V51 | X51: 0 | Y51: =K51*X51 | AA51: =Y51-Z51 | AB51: 0 | AC51: =K51*AB51 | AE51: =AC51-AD51 | AF51: 0 | AG51: =K51*AF51 | AI51: =AG51-AH51 | AJ51: 0 | AK51: =K51*AJ51 | AM51: =AK51-AL51 | AN51: 0 | AO51: =K51*AN51 | AQ51: =AO51-AP51 | AR51: 0 | AS51: =K51*AR51 | AU51: =AS51-AT51 | AV51: 0 | AW51: =K51*AV51 | AY51: =AW51-AX51 | AZ51: 按实 | BA51: =BB51 | BC51: =BA51-BB51 | BD51: 0 | BE51: =K51*BD51 | BG51: =BE51-BF51 | BH51: 0 | BI51: =K51*BH51 | BK51: =BI51-BJ51 | BL51: 按实 | BM51: =BN51 | BO51: =BM51-BN51 | BP51: =N51+Q51+U51+Y51+AC51+AG51+AK51+AO51+AS51+AW51+BA51+BE51+BI51+BM51 | BQ51: =N51+R51+V51+Z51+AD51+AH51+AL51+AP51+AT51+AX51+BB51+BF51+BJ51+BN51 | BR51: =BP51-BQ51
A52: 67 | B52: KQCY0067 | C52: 餐饮二分部 | D52: CF182 | E52: 无锡工艺第二食堂 | F52: 分组作业 | G52: 徐敏娟 | H52: 第九班组 | I52: 休闲水吧、水果 | J52: 党玉真 | K52: =LET(k,D52&"|"&E52&"|"&H52&"|"&I52&"|"&J52,sk,tblRevenueInput[项目代码]&"|"&tblRevenueInput[项目名称]&"|"&tblRevenueInput[分组作业名称]&"|"&tblRevenueInput[分组作业窗口名称]&"|"&tblRevenueInput[签订人],ok,tblRevenueOverride[项目代码]&"|"&tblRevenueOverride[项目名称]&"|"&tblRevenueOverride[分组作业名称]&"|"&tblRevenueOverride[分组作业窗口名称]&"|"&tblRevenueOverride[责任人],ov,IFERROR(XLOOKUP(k,ok,tblRevenueOverride[营业额覆盖],""),""),IF(ov<>"",ov,IFERROR(XLOOKUP(k,sk,tblRevenueInput[全额营业额合计],""),""))) | P52: 0.13 | Q52: =K52*P52 | S52: =Q52-R52 | T52: 0 | U52: =K52*T52 | W52: =U52-V52 | X52: 0 | Y52: =K52*X52 | AA52: =Y52-Z52 | AB52: 0 | AC52: =K52*AB52 | AE52: =AC52-AD52 | AF52: 0 | AG52: =K52*AF52 | AI52: =AG52-AH52 | AJ52: 0 | AK52: =K52*AJ52 | AM52: =AK52-AL52 | AN52: 0 | AO52: =K52*AN52 | AQ52: =AO52-AP52 | AR52: 0 | AS52: =K52*AR52 | AU52: =AS52-AT52 | AV52: 0 | AW52: =K52*AV52 | AY52: =AW52-AX52 | AZ52: 按实 | BA52: =BB52 | BC52: =BA52-BB52 | BD52: 0 | BE52: =K52*BD52 | BG52: =BE52-BF52 | BH52: 0 | BI52: =K52*BH52 | BK52: =BI52-BJ52 | BL52: 按实 | BM52: =BN52 | BO52: =BM52-BN52 | BP52: =N52+Q52+U52+Y52+AC52+AG52+AK52+AO52+AS52+AW52+BA52+BE52+BI52+BM52 | BQ52: =N52+R52+V52+Z52+AD52+AH52+AL52+AP52+AT52+AX52+BB52+BF52+BJ52+BN52 | BR52: =BP52-BQ52
A53: 68 | B53: KQCY0068 | C53: 餐饮二分部 | D53: CF182 | E53: 无锡工艺第二食堂 | F53: 分组作业 | G53: 徐敏娟 | H53: 第十一班组 | I53: （二楼特色小吃）汉堡、炸鸡、自主称重快餐、千里香馄饨、手擀面 | J53: 常霞 | K53: =LET(k,D53&"|"&E53&"|"&H53&"|"&I53&"|"&J53,sk,tblRevenueInput[项目代码]&"|"&tblRevenueInput[项目名称]&"|"&tblRevenueInput[分组作业名称]&"|"&tblRevenueInput[分组作业窗口名称]&"|"&tblRevenueInput[签订人],ok,tblRevenueOverride[项目代码]&"|"&tblRevenueOverride[项目名称]&"|"&tblRevenueOverride[分组作业名称]&"|"&tblRevenueOverride[分组作业窗口名称]&"|"&tblRevenueOverride[责任人],ov,IFERROR(XLOOKUP(k,ok,tblRevenueOverride[营业额覆盖],""),""),IF(ov<>"",ov,IFERROR(XLOOKUP(k,sk,tblRevenueInput[全额营业额合计],""),""))) | P53: 0.06 | Q53: =K53*P53 | S53: =Q53-R53 | T53: 0 | U53: =K53*T53 | W53: =U53-V53 | X53: 0 | Y53: =K53*X53 | AA53: =Y53-Z53 | AB53: 0 | AC53: =K53*AB53 | AE53: =AC53-AD53 | AF53: 0 | AG53: =K53*AF53 | AI53: =AG53-AH53 | AJ53: 0 | AK53: =K53*AJ53 | AM53: =AK53-AL53 | AN53: 0 | AO53: =K53*AN53 | AQ53: =AO53-AP53 | AR53: 0 | AS53: =K53*AR53 | AU53: =AS53-AT53 | AV53: 0 | AW53: =AX53 | AX53: 0 | AY53: =AW53-AX53 | AZ53: 按实 | BA53: =BB53 | BC53: =BA53-BB53 | BD53: 水费、电费、燃气费、保洁费自行承担 | BE53: =BF53 | BG53: =BE53-BF53 | BH53: 0 | BI53: =K53*BH53 | BK53: =BI53-BJ53 | BL53: 按实 | BM53: =BN53 | BO53: =BM53-BN53 | BP53: =N53+Q53+U53+Y53+AC53+AG53+AK53+AO53+AS53+AW53+BA53+BE53+BI53+BM53 | BQ53: =N53+R53+V53+Z53+AD53+AH53+AL53+AP53+AT53+AX53+BB53+BF53+BJ53+BN53 | BR53: =BP53-BQ53
A54: 70 | B54: KQCY0070 | C54: 餐饮二分部 | D54: CF360 | E54: 南通师专新校区食堂 | F54: 分组作业 | G54: 郑虎 | H54: 第一班组 | I54: 琳榆炸鸡腿 | J54: 王友强 | K54: =LET(k,D54&"|"&E54&"|"&H54&"|"&I54&"|"&J54,sk,tblRevenueInput[项目代码]&"|"&tblRevenueInput[项目名称]&"|"&tblRevenueInput[分组作业名称]&"|"&tblRevenueInput[分组作业窗口名称]&"|"&tblRevenueInput[签订人],ok,tblRevenueOverride[项目代码]&"|"&tblRevenueOverride[项目名称]&"|"&tblRevenueOverride[分组作业名称]&"|"&tblRevenueOverride[分组作业窗口名称]&"|"&tblRevenueOverride[责任人],ov,IFERROR(XLOOKUP(k,ok,tblRevenueOverride[营业额覆盖],""),""),IF(ov<>"",ov,IFERROR(XLOOKUP(k,sk,tblRevenueInput[全额营业额合计],""),""))) | N54: 0 | O54: 800000 | P54: 0.2 | Q54: =K54*P54 | S54: =Q54-R54 | T54: 0 | U54: =K54*T54 | W54: =U54-V54 | X54: 0 | Y54: =K54*X54 | AA54: =Y54-Z54 | AB54: 0 | AC54: =K54*AB54 | AE54: =AC54-AD54 | AF54: 0 | AG54: =K54*AF54 | AI54: =AG54-AH54 | AJ54: 0 | AK54: =K54*AJ54 | AM54: =AK54-AL54 | AN54: 0 | AO54: =K54*AN54 | AQ54: =AO54-AP54 | AR54: 0.03 | AS54: =K54*AR54 | AU54: =AS54-AT54 | AV54: 0.04 | AW54: =K54*AV54 | AY54: =AW54-AX54 | AZ54: 按实 | BA54: =BB54 | BC54: =BA54-BB54 | BD54: 0 | BE54: =K54*BD54 | BG54: =BE54-BF54 | BH54: 0 | BI54: =K54*BH54 | BK54: =BI54-BJ54 | BL54: 按实 | BM54: =BN54 | BO54: =BM54-BN54 | BP54: =N54+Q54+U54+Y54+AC54+AG54+AK54+AO54+AS54+AW54+BA54+BE54+BI54+BM54 | BQ54: =N54+R54+V54+Z54+AD54+AH54+AL54+AP54+AT54+AX54+BB54+BF54+BJ54+BN54 | BR54: =BP54-BQ54 | BS54: / | BT54: / | BU54: 1、装修折旧费：25万/年，分组作业未分摊，服务费已包含 | BV54: 1、签订期间：2026.3.1-2026.7.31； 2、指标按照全年换算；
A55: 71 | B55: KQCY0071 | C55: 餐饮二分部 | D55: CF360 | E55: 南通师专新校区食堂 | F55: 分组作业 | G55: 郑虎 | H55: 第二班组 | I55: 中式早点 | J55: 何小杏 | K55: =LET(k,D55&"|"&E55&"|"&H55&"|"&I55&"|"&J55,sk,tblRevenueInput[项目代码]&"|"&tblRevenueInput[项目名称]&"|"&tblRevenueInput[分组作业名称]&"|"&tblRevenueInput[分组作业窗口名称]&"|"&tblRevenueInput[签订人],ok,tblRevenueOverride[项目代码]&"|"&tblRevenueOverride[项目名称]&"|"&tblRevenueOverride[分组作业名称]&"|"&tblRevenueOverride[分组作业窗口名称]&"|"&tblRevenueOverride[责任人],ov,IFERROR(XLOOKUP(k,ok,tblRevenueOverride[营业额覆盖],""),""),IF(ov<>"",ov,IFERROR(XLOOKUP(k,sk,tblRevenueInput[全额营业额合计],""),""))) | N55: 228 | O55: 880000 | P55: 0.18 | Q55: =K55*P55 | S55: =Q55-R55 | T55: 0 | U55: =K55*T55 | W55: =U55-V55 | X55: 0 | Y55: =K55*X55 | AA55: =Y55-Z55 | AB55: 0 | AC55: =K55*AB55 | AE55: =AC55-AD55 | AF55: 0 | AG55: =K55*AF55 | AI55: =AG55-AH55 | AJ55: 0 | AK55: =K55*AJ55 | AM55: =AK55-AL55 | AN55: 0 | AO55: =K55*AN55 | AQ55: =AO55-AP55 | AR55: 0.02 | AS55: =K55*AR55 | AU55: =AS55-AT55 | AV55: 0.03 | AW55: =K55*AV55 | AY55: =AW55-AX55 | AZ55: 按实 | BA55: =BB55 | BC55: =BA55-BB55 | BD55: 0 | BE55: =K55*BD55 | BG55: =BE55-BF55 | BH55: 0 | BI55: =K55*BH55 | BK55: =BI55-BJ55 | BL55: 按实 | BM55: =BN55 | BO55: =BM55-BN55 | BP55: =N55+Q55+U55+Y55+AC55+AG55+AK55+AO55+AS55+AW55+BA55+BE55+BI55+BM55 | BQ55: =N55+R55+V55+Z55+AD55+AH55+AL55+AP55+AT55+AX55+BB55+BF55+BJ55+BN55 | BR55: =BP55-BQ55 | BS55: / | BT55: / | BU55: 1、装修折旧费：25万/年，分组作业未分摊，服务费已包含 | BV55: 1、签订期间：2026.3.1-2026.7.31； 2、指标按照全年换算；
A56: 72 | B56: KQCY0072 | C56: 餐饮二分部 | D56: CF360 | E56: 南通师专新校区食堂 | F56: 分组作业 | G56: 郑虎 | H56: 第三班组 | I56: 土耳其烤肉饭 | J56: 薛小勇 | K56: =LET(k,D56&"|"&E56&"|"&H56&"|"&I56&"|"&J56,sk,tblRevenueInput[项目代码]&"|"&tblRevenueInput[项目名称]&"|"&tblRevenueInput[分组作业名称]&"|"&tblRevenueInput[分组作业窗口名称]&"|"&tblRevenueInput[签订人],ok,tblRevenueOverride[项目代码]&"|"&tblRevenueOverride[项目名称]&"|"&tblRevenueOverride[分组作业名称]&"|"&tblRevenueOverride[分组作业窗口名称]&"|"&tblRevenueOverride[责任人],ov,IFERROR(XLOOKUP(k,ok,tblRevenueOverride[营业额覆盖],""),""),IF(ov<>"",ov,IFERROR(XLOOKUP(k,sk,tblRevenueInput[全额营业额合计],""),""))) | N56: 0 | O56: 800000 | P56: 0.18 | Q56: =K56*P56 | S56: =Q56-R56 | T56: 0 | U56: =K56*T56 | W56: =U56-V56 | X56: 0 | Y56: =K56*X56 | AA56: =Y56-Z56 | AB56: 0 | AC56: =K56*AB56 | AE56: =AC56-AD56 | AF56: 0 | AG56: =K56*AF56 | AI56: =AG56-AH56 | AJ56: 0 | AK56: =K56*AJ56 | AM56: =AK56-AL56 | AN56: 0 | AO56: =K56*AN56 | AQ56: =AO56-AP56 | AR56: 0.03 | AS56: =K56*AR56 | AU56: =AS56-AT56 | AV56: 0.03 | AW56: =K56*AV56 | AY56: =AW56-AX56 | AZ56: 按实 | BA56: =BB56 | BC56: =BA56-BB56 | BD56: 0 | BE56: =K56*BD56 | BG56: =BE56-BF56 | BH56: 0 | BI56: =K56*BH56 | BK56: =BI56-BJ56 | BL56: 按实 | BM56: =BN56 | BO56: =BM56-BN56 | BP56: =N56+Q56+U56+Y56+AC56+AG56+AK56+AO56+AS56+AW56+BA56+BE56+BI56+BM56 | BQ56: =N56+R56+V56+Z56+AD56+AH56+AL56+AP56+AT56+AX56+BB56+BF56+BJ56+BN56 | BR56: =BP56-BQ56 | BS56: / | BT56: / | BU56: 1、装修折旧费：25万/年，分组作业未分摊，服务费已包含 | BV56: 1、签订期间：2026.3.1-2026.7.31； 2、指标按照全年换算；
A57: 73 | B57: KQCY0073 | C57: 餐饮二分部 | D57: CF360 | E57: 南通师专新校区食堂 | F57: 分组作业 | G57: 郑虎 | H57: 第四班组 | I57: 营养粥小笼包 | J57: 沈玲 | K57: =LET(k,D57&"|"&E57&"|"&H57&"|"&I57&"|"&J57,sk,tblRevenueInput[项目代码]&"|"&tblRevenueInput[项目名称]&"|"&tblRevenueInput[分组作业名称]&"|"&tblRevenueInput[分组作业窗口名称]&"|"&tblRevenueInput[签订人],ok,tblRevenueOverride[项目代码]&"|"&tblRevenueOverride[项目名称]&"|"&tblRevenueOverride[分组作业名称]&"|"&tblRevenueOverride[分组作业窗口名称]&"|"&tblRevenueOverride[责任人],ov,IFERROR(XLOOKUP(k,ok,tblRevenueOverride[营业额覆盖],""),""),IF(ov<>"",ov,IFERROR(XLOOKUP(k,sk,tblRevenueInput[全额营业额合计],""),""))) | N57: 1741.59 | O57: 800000 | P57: 0.2 | Q57: =K57*P57 | S57: =Q57-R57 | T57: 0 | U57: =K57*T57 | W57: =U57-V57 | X57: 0 | Y57: =K57*X57 | AA57: =Y57-Z57 | AB57: 0 | AC57: =K57*AB57 | AE57: =AC57-AD57 | AF57: 0 | AG57: =K57*AF57 | AI57: =AG57-AH57 | AJ57: 0 | AK57: =K57*AJ57 | AM57: =AK57-AL57 | AN57: 0 | AO57: =K57*AN57 | AQ57: =AO57-AP57 | AR57: 0.03 | AS57: =K57*AR57 | AU57: =AS57-AT57 | AV57: 0.04 | AW57: =K57*AV57 | AY57: =AW57-AX57 | AZ57: 按实 | BA57: =BB57 | BC57: =BA57-BB57 | BD57: 0 | BE57: =K57*BD57 | BG57: =BE57-BF57 | BH57: 0 | BI57: =K57*BH57 | BK57: =BI57-BJ57 | BL57: 按实 | BM57: =BN57 | BO57: =BM57-BN57 | BP57: =N57+Q57+U57+Y57+AC57+AG57+AK57+AO57+AS57+AW57+BA57+BE57+BI57+BM57 | BQ57: =N57+R57+V57+Z57+AD57+AH57+AL57+AP57+AT57+AX57+BB57+BF57+BJ57+BN57 | BR57: =BP57-BQ57 | BS57: / | BT57: / | BU57: 1、装修折旧费：25万/年，分组作业未分摊，服务费已包含 | BV57: 1、签订期间：2026.3.1-2026.7.31； 2、指标按照全年换算；
A58: 74 | B58: KQCY0074 | C58: 餐饮二分部 | D58: CF360 | E58: 南通师专新校区食堂 | F58: 分组作业 | G58: 郑虎 | H58: 第五班组 | I58: 生烫牛肉米线 | J58: 刘海霞 | K58: =LET(k,D58&"|"&E58&"|"&H58&"|"&I58&"|"&J58,sk,tblRevenueInput[项目代码]&"|"&tblRevenueInput[项目名称]&"|"&tblRevenueInput[分组作业名称]&"|"&tblRevenueInput[分组作业窗口名称]&"|"&tblRevenueInput[签订人],ok,tblRevenueOverride[项目代码]&"|"&tblRevenueOverride[项目名称]&"|"&tblRevenueOverride[分组作业名称]&"|"&tblRevenueOverride[分组作业窗口名称]&"|"&tblRevenueOverride[责任人],ov,IFERROR(XLOOKUP(k,ok,tblRevenueOverride[营业额覆盖],""),""),IF(ov<>"",ov,IFERROR(XLOOKUP(k,sk,tblRevenueInput[全额营业额合计],""),""))) | N58: 56 | O58: 800000 | P58: 0.2 | Q58: =K58*P58 | S58: =Q58-R58 | T58: 0 | U58: =K58*T58 | W58: =U58-V58 | X58: 0 | Y58: =K58*X58 | AA58: =Y58-Z58 | AB58: 0 | AC58: =K58*AB58 | AE58: =AC58-AD58 | AF58: 0 | AG58: =K58*AF58 | AI58: =AG58-AH58 | AJ58: 0 | AK58: =K58*AJ58 | AM58: =AK58-AL58 | AN58: 0 | AO58: =K58*AN58 | AQ58: =AO58-AP58 | AR58: 0.03 | AS58: =K58*AR58 | AU58: =AS58-AT58 | AV58: 0.04 | AW58: =K58*AV58 | AY58: =AW58-AX58 | AZ58: 按实 | BA58: =BB58 | BC58: =BA58-BB58 | BD58: 0 | BE58: =K58*BD58 | BG58: =BE58-BF58 | BH58: 0 | BI58: =K58*BH58 | BK58: =BI58-BJ58 | BL58: 按实 | BM58: =BN58 | BO58: =BM58-BN58 | BP58: =N58+Q58+U58+Y58+AC58+AG58+AK58+AO58+AS58+AW58+BA58+BE58+BI58+BM58 | BQ58: =N58+R58+V58+Z58+AD58+AH58+AL58+AP58+AT58+AX58+BB58+BF58+BJ58+BN58 | BR58: =BP58-BQ58 | BS58: / | BT58: / | BU58: 1、装修折旧费：25万/年，分组作业未分摊，服务费已包含 | BV58: 1、签订期间：2026.3.1-2026.7.31； 2、指标按照全年换算；
A59: 75 | B59: KQCY0075 | C59: 餐饮二分部 | D59: CF360 | E59: 南通师专新校区食堂 | F59: 分组作业 | G59: 郑虎 | H59: 第六班组 | I59: 咖喱蛋包饭 | J59: 余娇 | K59: =LET(k,D59&"|"&E59&"|"&H59&"|"&I59&"|"&J59,sk,tblRevenueInput[项目代码]&"|"&tblRevenueInput[项目名称]&"|"&tblRevenueInput[分组作业名称]&"|"&tblRevenueInput[分组作业窗口名称]&"|"&tblRevenueInput[签订人],ok,tblRevenueOverride[项目代码]&"|"&tblRevenueOverride[项目名称]&"|"&tblRevenueOverride[分组作业名称]&"|"&tblRevenueOverride[分组作业窗口名称]&"|"&tblRevenueOverride[责任人],ov,IFERROR(XLOOKUP(k,ok,tblRevenueOverride[营业额覆盖],""),""),IF(ov<>"",ov,IFERROR(XLOOKUP(k,sk,tblRevenueInput[全额营业额合计],""),""))) | N59: 0 | O59: 800000 | P59: 0.2 | Q59: =K59*P59 | S59: =Q59-R59 | T59: 0 | U59: =K59*T59 | W59: =U59-V59 | X59: 0 | Y59: =K59*X59 | AA59: =Y59-Z59 | AB59: 0 | AC59: =K59*AB59 | AE59: =AC59-AD59 | AF59: 0 | AG59: =K59*AF59 | AI59: =AG59-AH59 | AJ59: 0 | AK59: =K59*AJ59 | AM59: =AK59-AL59 | AN59: 0 | AO59: =K59*AN59 | AQ59: =AO59-AP59 | AR59: 0.03 | AS59: =K59*AR59 | AU59: =AS59-AT59 | AV59: 0.04 | AW59: =K59*AV59 | AY59: =AW59-AX59 | AZ59: 按实 | BA59: =BB59 | BC59: =BA59-BB59 | BD59: 0 | BE59: =K59*BD59 | BG59: =BE59-BF59 | BH59: 0 | BI59: =K59*BH59 | BK59: =BI59-BJ59 | BL59: 按实 | BM59: =BN59 | BO59: =BM59-BN59 | BP59: =N59+Q59+U59+Y59+AC59+AG59+AK59+AO59+AS59+AW59+BA59+BE59+BI59+BM59 | BQ59: =N59+R59+V59+Z59+AD59+AH59+AL59+AP59+AT59+AX59+BB59+BF59+BJ59+BN59 | BR59: =BP59-BQ59 | BS59: / | BT59: / | BU59: 1、装修折旧费：25万/年，分组作业未分摊，服务费已包含 | BV59: 1、签订期间：2026.3.1-2026.7.31； 2、指标按照全年换算；
A60: 76 | B60: KQCY0076 | C60: 餐饮二分部 | D60: CF360 | E60: 南通师专新校区食堂 | F60: 分组作业 | G60: 郑虎 | H60: 第七班组 | I60: 麻辣烫麻辣拌 | J60: 虞冬梅 | K60: =LET(k,D60&"|"&E60&"|"&H60&"|"&I60&"|"&J60,sk,tblRevenueInput[项目代码]&"|"&tblRevenueInput[项目名称]&"|"&tblRevenueInput[分组作业名称]&"|"&tblRevenueInput[分组作业窗口名称]&"|"&tblRevenueInput[签订人],ok,tblRevenueOverride[项目代码]&"|"&tblRevenueOverride[项目名称]&"|"&tblRevenueOverride[分组作业名称]&"|"&tblRevenueOverride[分组作业窗口名称]&"|"&tblRevenueOverride[责任人],ov,IFERROR(XLOOKUP(k,ok,tblRevenueOverride[营业额覆盖],""),""),IF(ov<>"",ov,IFERROR(XLOOKUP(k,sk,tblRevenueInput[全额营业额合计],""),""))) | N60: 1741.59 | O60: 800000 | P60: 0.18 | Q60: =K60*P60 | S60: =Q60-R60 | T60: 0 | U60: =K60*T60 | W60: =U60-V60 | X60: 0 | Y60: =K60*X60 | AA60: =Y60-Z60 | AB60: 0 | AC60: =K60*AB60 | AE60: =AC60-AD60 | AF60: 0 | AG60: =K60*AF60 | AI60: =AG60-AH60 | AJ60: 0 | AK60: =K60*AJ60 | AM60: =AK60-AL60 | AN60: 0 | AO60: =K60*AN60 | AQ60: =AO60-AP60 | AR60: 0.03 | AS60: =K60*AR60 | AU60: =AS60-AT60 | AV60: 0.03 | AW60: =K60*AV60 | AY60: =AW60-AX60 | AZ60: 按实 | BA60: =BB60 | BC60: =BA60-BB60 | BD60: 0 | BE60: =K60*BD60 | BG60: =BE60-BF60 | BH60: 0 | BI60: =K60*BH60 | BK60: =BI60-BJ60 | BL60: 按实 | BM60: =BN60 | BO60: =BM60-BN60 | BP60: =N60+Q60+U60+Y60+AC60+AG60+AK60+AO60+AS60+AW60+BA60+BE60+BI60+BM60 | BQ60: =N60+R60+V60+Z60+AD60+AH60+AL60+AP60+AT60+AX60+BB60+BF60+BJ60+BN60 | BR60: =BP60-BQ60 | BS60: / | BT60: / | BU60: 1、装修折旧费：25万/年，分组作业未分摊，服务费已包含 | BV60: 1、签订期间：2026.3.1-2026.7.31； 2、指标按照全年换算；
A61: 77 | B61: KQCY0077 | C61: 餐饮二分部 | D61: CF360 | E61: 南通师专新校区食堂 | F61: 分组作业 | G61: 郑虎 | H61: 第八班组 | I61: 真老大手工云吞 | J61: 彭晴 | K61: =LET(k,D61&"|"&E61&"|"&H61&"|"&I61&"|"&J61,sk,tblRevenueInput[项目代码]&"|"&tblRevenueInput[项目名称]&"|"&tblRevenueInput[分组作业名称]&"|"&tblRevenueInput[分组作业窗口名称]&"|"&tblRevenueInput[签订人],ok,tblRevenueOverride[项目代码]&"|"&tblRevenueOverride[项目名称]&"|"&tblRevenueOverride[分组作业名称]&"|"&tblRevenueOverride[分组作业窗口名称]&"|"&tblRevenueOverride[责任人],ov,IFERROR(XLOOKUP(k,ok,tblRevenueOverride[营业额覆盖],""),""),IF(ov<>"",ov,IFERROR(XLOOKUP(k,sk,tblRevenueInput[全额营业额合计],""),""))) | N61: 1726.59 | O61: 800000 | P61: 0.2 | Q61: =K61*P61 | S61: =Q61-R61 | T61: 0 | U61: =K61*T61 | W61: =U61-V61 | X61: 0 | Y61: =K61*X61 | AA61: =Y61-Z61 | AB61: 0 | AC61: =K61*AB61 | AE61: =AC61-AD61 | AF61: 0 | AG61: =K61*AF61 | AI61: =AG61-AH61 | AJ61: 0 | AK61: =K61*AJ61 | AM61: =AK61-AL61 | AN61: 0 | AO61: =K61*AN61 | AQ61: =AO61-AP61 | AR61: 0.03 | AS61: =K61*AR61 | AU61: =AS61-AT61 | AV61: 0.04 | AW61: =K61*AV61 | AY61: =AW61-AX61 | AZ61: 按实 | BA61: =BB61 | BC61: =BA61-BB61 | BD61: 0 | BE61: =K61*BD61 | BG61: =BE61-BF61 | BH61: 0 | BI61: =K61*BH61 | BK61: =BI61-BJ61 | BL61: 按实 | BM61: =BN61 | BO61: =BM61-BN61 | BP61: =N61+Q61+U61+Y61+AC61+AG61+AK61+AO61+AS61+AW61+BA61+BE61+BI61+BM61 | BQ61: =N61+R61+V61+Z61+AD61+AH61+AL61+AP61+AT61+AX61+BB61+BF61+BJ61+BN61 | BR61: =BP61-BQ61 | BS61: / | BT61: / | BU61: 1、装修折旧费：25万/年，分组作业未分摊，服务费已包含 | BV61: 1、签订期间：2026.3.1-2026.7.31； 2、指标按照全年换算；
A62: 78 | B62: KQCY0078 | C62: 餐饮二分部 | D62: CF360 | E62: 南通师专新校区食堂 | F62: 分组作业 | G62: 郑虎 | H62: 第九班组 | I62: 朱家小馆羊杂面 | J62: 薛桂中 | K62: =LET(k,D62&"|"&E62&"|"&H62&"|"&I62&"|"&J62,sk,tblRevenueInput[项目代码]&"|"&tblRevenueInput[项目名称]&"|"&tblRevenueInput[分组作业名称]&"|"&tblRevenueInput[分组作业窗口名称]&"|"&tblRevenueInput[签订人],ok,tblRevenueOverride[项目代码]&"|"&tblRevenueOverride[项目名称]&"|"&tblRevenueOverride[分组作业名称]&"|"&tblRevenueOverride[分组作业窗口名称]&"|"&tblRevenueOverride[责任人],ov,IFERROR(XLOOKUP(k,ok,tblRevenueOverride[营业额覆盖],""),""),IF(ov<>"",ov,IFERROR(XLOOKUP(k,sk,tblRevenueInput[全额营业额合计],""),""))) | N62: 1769.59 | O62: 960000 | P62: 0.2 | Q62: =K62*P62 | S62: =Q62-R62 | T62: 0 | U62: =K62*T62 | W62: =U62-V62 | X62: 0 | Y62: =K62*X62 | AA62: =Y62-Z62 | AB62: 0 | AC62: =K62*AB62 | AE62: =AC62-AD62 | AF62: 0 | AG62: =K62*AF62 | AI62: =AG62-AH62 | AJ62: 0 | AK62: =K62*AJ62 | AM62: =AK62-AL62 | AN62: 0 | AO62: =K62*AN62 | AQ62: =AO62-AP62 | AR62: 0.03 | AS62: =K62*AR62 | AU62: =AS62-AT62 | AV62: 0.04 | AW62: =K62*AV62 | AY62: =AW62-AX62 | AZ62: 按实 | BA62: =BB62 | BC62: =BA62-BB62 | BD62: 0 | BE62: =K62*BD62 | BG62: =BE62-BF62 | BH62: 0 | BI62: =K62*BH62 | BK62: =BI62-BJ62 | BL62: 按实 | BM62: =BN62 | BO62: =BM62-BN62 | BP62: =N62+Q62+U62+Y62+AC62+AG62+AK62+AO62+AS62+AW62+BA62+BE62+BI62+BM62 | BQ62: =N62+R62+V62+Z62+AD62+AH62+AL62+AP62+AT62+AX62+BB62+BF62+BJ62+BN62 | BR62: =BP62-BQ62 | BS62: / | BT62: / | BU62: 1、装修折旧费：25万/年，分组作业未分摊，服务费已包含 | BV62: 1、签订期间：2026.3.1-2026.7.31； 2、指标按照全年换算；
A63: 79 | B63: KQCY0079 | C63: 餐饮二分部 | D63: CF360 | E63: 南通师专新校区食堂 | F63: 分组作业 | G63: 郑虎 | H63: 第十班组 | I63: 奶茶 | J63: 王艳 | K63: =LET(k,D63&"|"&E63&"|"&H63&"|"&I63&"|"&J63,sk,tblRevenueInput[项目代码]&"|"&tblRevenueInput[项目名称]&"|"&tblRevenueInput[分组作业名称]&"|"&tblRevenueInput[分组作业窗口名称]&"|"&tblRevenueInput[签订人],ok,tblRevenueOverride[项目代码]&"|"&tblRevenueOverride[项目名称]&"|"&tblRevenueOverride[分组作业名称]&"|"&tblRevenueOverride[分组作业窗口名称]&"|"&tblRevenueOverride[责任人],ov,IFERROR(XLOOKUP(k,ok,tblRevenueOverride[营业额覆盖],""),""),IF(ov<>"",ov,IFERROR(XLOOKUP(k,sk,tblRevenueInput[全额营业额合计],""),""))) | N63: 43 | O63: 480000 | P63: 0.18 | Q63: =K63*P63 | S63: =Q63-R63 | T63: 0 | U63: =K63*T63 | W63: =U63-V63 | X63: 0 | Y63: =K63*X63 | AA63: =Y63-Z63 | AB63: 0 | AC63: =K63*AB63 | AE63: =AC63-AD63 | AF63: 0 | AG63: =K63*AF63 | AI63: =AG63-AH63 | AJ63: 0 | AK63: =K63*AJ63 | AM63: =AK63-AL63 | AN63: 0 | AO63: =K63*AN63 | AQ63: =AO63-AP63 | AR63: 0 | AS63: =K63*AR63 | AU63: =AS63-AT63 | AV63: 按实 | AY63: =AW63-AX63 | AZ63: 按实 | BA63: =BB63 | BC63: =BA63-BB63 | BD63: 0 | BE63: =K63*BD63 | BG63: =BE63-BF63 | BH63: 0 | BI63: =K63*BH63 | BK63: =BI63-BJ63 | BL63: 按实 | BO63: =BM63-BN63 | BP63: =N63+Q63+U63+Y63+AC63+AG63+AK63+AO63+AS63+AW63+BA63+BE63+BI63+BM63 | BQ63: =N63+R63+V63+Z63+AD63+AH63+AL63+AP63+AT63+AX63+BB63+BF63+BJ63+BN63 | BR63: =BP63-BQ63 | BS63: / | BT63: / | BU63: 1、装修折旧费：25万/年，分组作业未分摊，服务费已包含； 2、卫生费：分组作业不在食堂内，未分摊，服务费已包含； | BV63: 1、签订期间：2026.3.1-2026.7.31； 2、指标按照全年换算；
A64: 82 | B64: KQCY0082 | C64: 餐饮二分部 | D64: CF364 | E64: 江苏航运思本轩食堂 | F64: 分组作业 | G64: 郑虎 | H64: 第二班组 | I64: 粉丝汤（牛肉、老母鸡、牛杂、拆骨） | J64: 满超 | K64: =LET(k,D64&"|"&E64&"|"&H64&"|"&I64&"|"&J64,sk,tblRevenueInput[项目代码]&"|"&tblRevenueInput[项目名称]&"|"&tblRevenueInput[分组作业名称]&"|"&tblRevenueInput[分组作业窗口名称]&"|"&tblRevenueInput[签订人],ok,tblRevenueOverride[项目代码]&"|"&tblRevenueOverride[项目名称]&"|"&tblRevenueOverride[分组作业名称]&"|"&tblRevenueOverride[分组作业窗口名称]&"|"&tblRevenueOverride[责任人],ov,IFERROR(XLOOKUP(k,ok,tblRevenueOverride[营业额覆盖],""),""),IF(ov<>"",ov,IFERROR(XLOOKUP(k,sk,tblRevenueInput[全额营业额合计],""),""))) | N64: 2216.63 | O64: 590000 | P64: 0.12 | Q64: =K64*P64 | R64: 841.272 | S64: =Q64-R64 | T64: 0.01 | U64: =K64*T64 | V64: 70.106 | W64: =U64-V64 | X64: 按实 | Y64: =Z64 | AA64: =Y64-Z64 | AB64: 0.01 | AC64: =K64*AB64 | AD64: 70.106 | AE64: =AC64-AD64 | AF64: 0.01 | AG64: =K64*AF64 | AH64: 70.106 | AI64: =AG64-AH64 | AJ64: 0.01 | AK64: =K64*AJ64 | AL64: 70.106 | AM64: =AK64-AL64 | AN64: 0.02 | AO64: =K64*AN64 | AP64: 140.212 | AQ64: =AO64-AP64 | AR64: 按实 | AS64: 690.59 | AT64: 690.59 | AU64: =AS64-AT64 | AV64: 按实 | AW64: 421.86655 | AX64: 421.86655 | AY64: =AW64-AX64 | AZ64: 按实 | BA64: =BB64 | BC64: =BA64-BB64 | BD64: 0 | BE64: =K64*BD64 | BG64: =BE64-BF64 | BH64: 0 | BI64: =K64*BH64 | BK64: =BI64-BJ64 | BL64: 按实 | BM64: =BN64 | BO64: =BM64-BN64 | BP64: =N64+Q64+U64+Y64+AC64+AG64+AK64+AO64+AS64+AW64+BA64+BE64+BI64+BM64 | BQ64: =N64+R64+V64+Z64+AD64+AH64+AL64+AP64+AT64+AX64+BB64+BF64+BJ64+BN64 | BR64: 0 | BS64: / | BT64: / | BU64: 1、甲方管理费：甲方每月按上月营业额的2%暂扣考核返还金、按营业额的1%暂扣公共维修金，分组作业应分摊未分摊，已补分摊，服务费比例应做相应调整； 2、甲方捐赠：乙方承诺资助30000元/年，分组作业未分摊，服务费已包含； | BV64: 1、签订期间：2025.9.1-2026.8.31； 2、指标按照全年换算；
A65: 83 | B65: KQCY0083 | C65: 餐饮二分部 | D65: CF364 | E65: 江苏航运思本轩食堂 | F65: 分组作业 | G65: 郑虎 | H65: 第三班组 | I65: 拌饭（鸡腿饭、酸梅鸭饭） | J65: 唐德生 | K65: =LET(k,D65&"|"&E65&"|"&H65&"|"&I65&"|"&J65,sk,tblRevenueInput[项目代码]&"|"&tblRevenueInput[项目名称]&"|"&tblRevenueInput[分组作业名称]&"|"&tblRevenueInput[分组作业窗口名称]&"|"&tblRevenueInput[签订人],ok,tblRevenueOverride[项目代码]&"|"&tblRevenueOverride[项目名称]&"|"&tblRevenueOverride[分组作业名称]&"|"&tblRevenueOverride[分组作业窗口名称]&"|"&tblRevenueOverride[责任人],ov,IFERROR(XLOOKUP(k,ok,tblRevenueOverride[营业额覆盖],""),""),IF(ov<>"",ov,IFERROR(XLOOKUP(k,sk,tblRevenueInput[全额营业额合计],""),""))) | N65: 2173.63 | O65: 400000 | P65: 0.12 | Q65: =K65*P65 | R65: 1404.0108 | S65: =Q65-R65 | T65: 0.01 | U65: =K65*T65 | V65: 117.0009 | W65: =U65-V65 | X65: 按实 | Y65: =Z65 | AA65: =Y65-Z65 | AB65: 0.01 | AC65: =K65*AB65 | AD65: 117.0009 | AE65: =AC65-AD65 | AF65: 0.01 | AG65: =K65*AF65 | AH65: 117.0009 | AI65: =AG65-AH65 | AJ65: 0.01 | AK65: =K65*AJ65 | AL65: 117.0009 | AM65: =AK65-AL65 | AN65: 0.02 | AO65: =K65*AN65 | AP65: 234.0018 | AQ65: =AO65-AP65 | AR65: 0.03 | AS65: 351.0027 | AT65: 351.0027 | AU65: =AS65-AT65 | AV65: 0.03 | AW65: 351.0027 | AX65: 351.0027 | AY65: =AW65-AX65 | AZ65: 按实 | BA65: =BB65 | BC65: =BA65-BB65 | BD65: 0 | BE65: =K65*BD65 | BG65: =BE65-BF65 | BH65: 0 | BI65: =K65*BH65 | BK65: =BI65-BJ65 | BL65: 按实 | BM65: =BN65 | BO65: =BM65-BN65 | BP65: =N65+Q65+U65+Y65+AC65+AG65+AK65+AO65+AS65+AW65+BA65+BE65+BI65+BM65 | BQ65: =N65+R65+V65+Z65+AD65+AH65+AL65+AP65+AT65+AX65+BB65+BF65+BJ65+BN65 | BR65: 0 | BS65: / | BT65: / | BU65: 1、甲方管理费：甲方每月按上月营业额的2%暂扣考核返还金、按营业额的1%暂扣公共维修金，分组作业应分摊未分摊，已补分摊，服务费比例应做相应调整； 2、甲方捐赠：乙方承诺资助30000元/年，分组作业未分摊，服务费已包含； | BV65: 1、签订期间：2025.9.1-2026.8.31； 2、指标按照全年换算；
A66: 84 | B66: KQCY0084 | C66: 餐饮二分部 | D66: CF364 | E66: 江苏航运思本轩食堂 | F66: 分组作业 | G66: 郑虎 | H66: 第五班组 | I66: 早餐 | J66: 潘捷 | K66: =LET(k,D66&"|"&E66&"|"&H66&"|"&I66&"|"&J66,sk,tblRevenueInput[项目代码]&"|"&tblRevenueInput[项目名称]&"|"&tblRevenueInput[分组作业名称]&"|"&tblRevenueInput[分组作业窗口名称]&"|"&tblRevenueInput[签订人],ok,tblRevenueOverride[项目代码]&"|"&tblRevenueOverride[项目名称]&"|"&tblRevenueOverride[分组作业名称]&"|"&tblRevenueOverride[分组作业窗口名称]&"|"&tblRevenueOverride[责任人],ov,IFERROR(XLOOKUP(k,ok,tblRevenueOverride[营业额覆盖],""),""),IF(ov<>"",ov,IFERROR(XLOOKUP(k,sk,tblRevenueInput[全额营业额合计],""),""))) | O66: 240000 | P66: 0.05 | Q66: =K66*P66 | S66: =Q66-R66 | T66: 0.01 | U66: =K66*T66 | V66: 0 | W66: =U66-V66 | X66: 按实 | Y66: =Z66 | AA66: =Y66-Z66 | AB66: 0.01 | AC66: =K66*AB66 | AD66: 0 | AE66: =AC66-AD66 | AF66: 0.01 | AG66: =K66*AF66 | AH66: 0 | AI66: =AG66-AH66 | AJ66: 0.01 | AK66: =K66*AJ66 | AL66: 0 | AM66: =AK66-AL66 | AN66: 0.01 | AO66: =K66*AN66 | AP66: 0 | AQ66: =AO66-AP66 | AR66: 按实 | AS66: 0 | AT66: 0 | AU66: =AS66-AT66 | AV66: 按实 | AW66: 0 | AX66: 0 | AY66: =AW66-AX66 | AZ66: 按实 | BA66: =BB66 | BC66: =BA66-BB66 | BD66: 0 | BE66: =K66*BD66 | BG66: =BE66-BF66 | BH66: 0 | BI66: =K66*BH66 | BK66: =BI66-BJ66 | BL66: 按实 | BM66: =BN66 | BO66: =BM66-BN66 | BP66: =N66+Q66+U66+Y66+AC66+AG66+AK66+AO66+AS66+AW66+BA66+BE66+BI66+BM66 | BQ66: =N66+R66+V66+Z66+AD66+AH66+AL66+AP66+AT66+AX66+BB66+BF66+BJ66+BN66 | BR66: 0 | BS66: / | BT66: / | BU66: 1、甲方管理费：甲方每月按上月营业额的2%暂扣考核返还金、按营业额的1%暂扣公共维修金，分组作业应分摊未分摊，已补分摊，服务费比例应做相应调整； 2、甲方捐赠：乙方承诺资助30000元/年，分组作业未分摊，服务费已包含； | BV66: 1、签订期间：2025.9.1-2026.8.31； 2、指标按照全年换算；
A67: 86 | B67: KQCY0086 | C67: 餐饮二分部 | D67: CF364 | E67: 江苏航运思本轩食堂 | F67: 分组作业 | G67: 郑虎 | H67: 第七班组 | I67: 锡纸饭 | J67: 陈芳 | K67: =LET(k,D67&"|"&E67&"|"&H67&"|"&I67&"|"&J67,sk,tblRevenueInput[项目代码]&"|"&tblRevenueInput[项目名称]&"|"&tblRevenueInput[分组作业名称]&"|"&tblRevenueInput[分组作业窗口名称]&"|"&tblRevenueInput[签订人],ok,tblRevenueOverride[项目代码]&"|"&tblRevenueOverride[项目名称]&"|"&tblRevenueOverride[分组作业名称]&"|"&tblRevenueOverride[分组作业窗口名称]&"|"&tblRevenueOverride[责任人],ov,IFERROR(XLOOKUP(k,ok,tblRevenueOverride[营业额覆盖],""),""),IF(ov<>"",ov,IFERROR(XLOOKUP(k,sk,tblRevenueInput[全额营业额合计],""),""))) | N67: 2638.97 | O67: 365000 | P67: 0.12 | Q67: =K67*P67 | R67: 375.5364 | S67: =Q67-R67 | T67: 0.01 | U67: =K67*T67 | V67: 31.2947 | W67: =U67-V67 | X67: 按实 | Y67: =Z67 | AA67: =Y67-Z67 | AB67: 0.01 | AC67: =K67*AB67 | AD67: 31.2947 | AE67: =AC67-AD67 | AF67: 0.01 | AG67: =K67*AF67 | AH67: 31.2947 | AI67: =AG67-AH67 | AJ67: 0.01 | AK67: =K67*AJ67 | AL67: 31.2947 | AM67: =AK67-AL67 | AN67: 0.02 | AO67: =K67*AN67 | AP67: 62.5894 | AQ67: =AO67-AP67 | AR67: 按实 | AS67: 690.59 | AT67: 690.59 | AU67: =AS67-AT67 | AV67: 按实 | AW67: 188.31751 | AX67: 188.31751 | AY67: =AW67-AX67 | AZ67: 按实 | BA67: =BB67 | BC67: =BA67-BB67 | BD67: 0 | BE67: =K67*BD67 | BG67: =BE67-BF67 | BH67: 0 | BI67: =K67*BH67 | BK67: =BI67-BJ67 | BL67: 按实 | BM67: =BN67 | BO67: =BM67-BN67 | BP67: =N67+Q67+U67+Y67+AC67+AG67+AK67+AO67+AS67+AW67+BA67+BE67+BI67+BM67 | BQ67: =N67+R67+V67+Z67+AD67+AH67+AL67+AP67+AT67+AX67+BB67+BF67+BJ67+BN67 | BR67: 0 | BS67: / | BT67: / | BU67: 1、甲方管理费：甲方每月按上月营业额的2%暂扣考核返还金、按营业额的1%暂扣公共维修金，分组作业应分摊未分摊，已补分摊，服务费比例应做相应调整； 2、甲方捐赠：乙方承诺资助30000元/年，分组作业未分摊，服务费已包含； | BV67: 1、签订期间：2025.9.1-2026.8.31； 2、指标按照全年换算；
A68: 89 | B68: KQCY0089 | C68: 餐饮二分部 | D68: CF364 | E68: 江苏航运思本轩食堂 | F68: 分组作业 | G68: 郑虎 | H68: 第十班组 | I68: 烤鸭饭 | J68: 蒋继承 | K68: =LET(k,D68&"|"&E68&"|"&H68&"|"&I68&"|"&J68,sk,tblRevenueInput[项目代码]&"|"&tblRevenueInput[项目名称]&"|"&tblRevenueInput[分组作业名称]&"|"&tblRevenueInput[分组作业窗口名称]&"|"&tblRevenueInput[签订人],ok,tblRevenueOverride[项目代码]&"|"&tblRevenueOverride[项目名称]&"|"&tblRevenueOverride[分组作业名称]&"|"&tblRevenueOverride[分组作业窗口名称]&"|"&tblRevenueOverride[责任人],ov,IFERROR(XLOOKUP(k,ok,tblRevenueOverride[营业额覆盖],""),""),IF(ov<>"",ov,IFERROR(XLOOKUP(k,sk,tblRevenueInput[全额营业额合计],""),""))) | N68: 2638.97 | O68: 1440000 | P68: 0.12 | Q68: =K68*P68 | R68: 1261.5984 | S68: =Q68-R68 | T68: 0.01 | U68: =K68*T68 | V68: 105.1332 | W68: =U68-V68 | X68: 按实 | Y68: =Z68 | AA68: =Y68-Z68 | AB68: 0.01 | AC68: =K68*AB68 | AD68: 105.1332 | AE68: =AC68-AD68 | AF68: 0.01 | AG68: =K68*AF68 | AH68: 105.1332 | AI68: =AG68-AH68 | AJ68: 0.01 | AK68: =K68*AJ68 | AL68: 105.1332 | AM68: =AK68-AL68 | AN68: 0.02 | AO68: =K68*AN68 | AP68: 210.2664 | AQ68: =AO68-AP68 | AR68: 0.03 | AS68: 315.3996 | AT68: 315.3996 | AU68: =AS68-AT68 | AV68: 0.02 | AW68: 210.2664 | AX68: 210.2664 | AY68: =AW68-AX68 | AZ68: 按实 | BA68: =BB68 | BC68: =BA68-BB68 | BD68: 0 | BE68: =K68*BD68 | BG68: =BE68-BF68 | BH68: 0 | BI68: =K68*BH68 | BK68: =BI68-BJ68 | BL68: 按实 | BM68: =BN68 | BO68: =BM68-BN68 | BP68: =N68+Q68+U68+Y68+AC68+AG68+AK68+AO68+AS68+AW68+BA68+BE68+BI68+BM68 | BQ68: =N68+R68+V68+Z68+AD68+AH68+AL68+AP68+AT68+AX68+BB68+BF68+BJ68+BN68 | BR68: 0 | BS68: / | BT68: / | BU68: 1、甲方管理费：甲方每月按上月营业额的2%暂扣考核返还金、按营业额的1%暂扣公共维修金，分组作业应分摊未分摊，已补分摊，服务费比例应做相应调整； 2、甲方捐赠：乙方承诺资助30000元/年，分组作业未分摊，服务费已包含； | BV68: 1、签订期间：2025.9.1-2026.8.31； 2、指标按照全年换算；
A69: 90 | B69: KQCY0090 | C69: 餐饮二分部 | D69: CF364 | E69: 江苏航运思本轩食堂 | F69: 分组作业 | G69: 郑虎 | H69: 第十一班组 | I69: 朱家小馆 | J69: 张慧南 | K69: =LET(k,D69&"|"&E69&"|"&H69&"|"&I69&"|"&J69,sk,tblRevenueInput[项目代码]&"|"&tblRevenueInput[项目名称]&"|"&tblRevenueInput[分组作业名称]&"|"&tblRevenueInput[分组作业窗口名称]&"|"&tblRevenueInput[签订人],ok,tblRevenueOverride[项目代码]&"|"&tblRevenueOverride[项目名称]&"|"&tblRevenueOverride[分组作业名称]&"|"&tblRevenueOverride[分组作业窗口名称]&"|"&tblRevenueOverride[责任人],ov,IFERROR(XLOOKUP(k,ok,tblRevenueOverride[营业额覆盖],""),""),IF(ov<>"",ov,IFERROR(XLOOKUP(k,sk,tblRevenueInput[全额营业额合计],""),""))) | N69: 2216.63 | O69: 560000 | P69: 0.12 | Q69: =K69*P69 | R69: 1135.95 | S69: =Q69-R69 | T69: 0.01 | U69: =K69*T69 | V69: 94.6625 | W69: =U69-V69 | X69: 按实 | Y69: =Z69 | AA69: =Y69-Z69 | AB69: 0.01 | AC69: =K69*AB69 | AD69: 94.6625 | AE69: =AC69-AD69 | AF69: 0.01 | AG69: =K69*AF69 | AH69: 94.6625 | AI69: =AG69-AH69 | AJ69: 0.01 | AK69: =K69*AJ69 | AL69: 94.6625 | AM69: =AK69-AL69 | AN69: 0.02 | AO69: =K69*AN69 | AP69: 189.325 | AQ69: =AO69-AP69 | AR69: 0.04 | AS69: 378.65 | AT69: 378.65 | AU69: =AS69-AT69 | AV69: 0.04 | AW69: 378.65 | AX69: 378.65 | AY69: =AW69-AX69 | AZ69: 按实 | BA69: =BB69 | BB69: =1000 | BC69: =BA69-BB69 | BD69: 0 | BE69: =K69*BD69 | BG69: =BE69-BF69 | BH69: 0 | BI69: =K69*BH69 | BK69: =BI69-BJ69 | BL69: 按实 | BM69: 19676.09 | BN69: 19676.09 | BO69: =BM69-BN69 | BP69: =N69+Q69+U69+Y69+AC69+AG69+AK69+AO69+AS69+AW69+BA69+BE69+BI69+BM69 | BQ69: =N69+R69+V69+Z69+AD69+AH69+AL69+AP69+AT69+AX69+BB69+BF69+BJ69+BN69 | BR69: =BP69-BQ69 | BS69: / | BT69: / | BU69: 1、甲方管理费：甲方每月按上月营业额的2%暂扣考核返还金、按营业额的1%暂扣公共维修金，分组作业应分摊未分摊，已补分摊，服务费比例应做相应调整； 2、甲方捐赠：乙方承诺资助30000元/年，分组作业未分摊，服务费已包含； | BV69: 1、签订期间：2025.9.1-2026.8.31； 2、指标按照全年换算；
A70: 95 | B70: KQCY0095 | C70: 餐饮二分部 | D70: CF363 | E70: 南通大学启东校区 | F70: 分组作业 | G70: 郑虎 | H70: 第一班组 | I70: 基本大伙 | J70: 朱寿凤 | K70: =LET(k,D70&"|"&E70&"|"&H70&"|"&I70&"|"&J70,sk,tblRevenueInput[项目代码]&"|"&tblRevenueInput[项目名称]&"|"&tblRevenueInput[分组作业名称]&"|"&tblRevenueInput[分组作业窗口名称]&"|"&tblRevenueInput[签订人],ok,tblRevenueOverride[项目代码]&"|"&tblRevenueOverride[项目名称]&"|"&tblRevenueOverride[分组作业名称]&"|"&tblRevenueOverride[分组作业窗口名称]&"|"&tblRevenueOverride[责任人],ov,IFERROR(XLOOKUP(k,ok,tblRevenueOverride[营业额覆盖],""),""),IF(ov<>"",ov,IFERROR(XLOOKUP(k,sk,tblRevenueInput[全额营业额合计],""),""))) | N70: 196 | O70: 2400000 | P70: 0.18 | Q70: =K70*P70 | R70: 6439.716 | S70: =Q70-R70 | T70: 0 | U70: =K70*T70 | W70: =U70-V70 | X70: 0 | Y70: =K70*X70 | AA70: =Y70-Z70 | AB70: 0 | AC70: =K70*AB70 | AE70: =AC70-AD70 | AF70: 0 | AG70: =K70*AF70 | AI70: =AG70-AH70 | AJ70: 按比例分摊 | AK70: =AL70 | AM70: =AK70-AL70 | AN70: 500/月，1、2、7、8月不收 | AO70: 200 | AP70: 200 | AQ70: =AO70-AP70 | AR70: 0.03 | AS70: =K70*AR70 | AT70: 1073.286 | AU70: =AS70-AT70 | AV70: 0.04 | AW70: =K70*AV70 | AX70: 1431.048 | AY70: =AW70-AX70 | AZ70: 按实 | BA70: =BB70 | BC70: =BA70-BB70 | BD70: 0 | BE70: =K70*BD70 | BG70: =BE70-BF70 | BH70: 0 | BI70: =K70*BH70 | BK70: =BI70-BJ70 | BL70: 按实 | BM70: 12049.234 | BN70: 12049.234 | BO70: =BM70-BN70 | BP70: =N70+Q70+U70+Y70+AC70+AG70+AK70+AO70+AS70+AW70+BA70+BE70+BI70+BM70 | BQ70: =N70+R70+V70+Z70+AD70+AH70+AL70+AP70+AT70+AX70+BB70+BF70+BJ70+BN70 | BR70: =BP70-BQ70 | BS70: / | BT70: / | BU70: 1、甲方管理费：校方按营业额比例13%收取，分组作业应分摊未分摊，已补分摊，服务费比例应做相应调整； | BV70: 1、签订期间：2025.9.1-2026.8.31； 2、指标按照全年换算；
A71: 96 | B71: KQCY0096 | C71: 餐饮二分部 | D71: CF363 | E71: 南通大学启东校区 | F71: 分组作业 | G71: 郑虎 | H71: 第二班组 | I71: 自选称重 | J71: 朱寿凤 | K71: =LET(k,D71&"|"&E71&"|"&H71&"|"&I71&"|"&J71,sk,tblRevenueInput[项目代码]&"|"&tblRevenueInput[项目名称]&"|"&tblRevenueInput[分组作业名称]&"|"&tblRevenueInput[分组作业窗口名称]&"|"&tblRevenueInput[签订人],ok,tblRevenueOverride[项目代码]&"|"&tblRevenueOverride[项目名称]&"|"&tblRevenueOverride[分组作业名称]&"|"&tblRevenueOverride[分组作业窗口名称]&"|"&tblRevenueOverride[责任人],ov,IFERROR(XLOOKUP(k,ok,tblRevenueOverride[营业额覆盖],""),""),IF(ov<>"",ov,IFERROR(XLOOKUP(k,sk,tblRevenueInput[全额营业额合计],""),""))) | N71: 1840.53 | O71: 1400000 | P71: 0.19 | Q71: =K71*P71 | R71: 4179.62 | S71: =Q71-R71 | T71: 0 | U71: =K71*T71 | W71: =U71-V71 | X71: 0 | Y71: =K71*X71 | AA71: =Y71-Z71 | AB71: 0 | AC71: =K71*AB71 | AE71: =AC71-AD71 | AF71: 0 | AG71: =K71*AF71 | AI71: =AG71-AH71 | AJ71: 按比例分摊 | AK71: =AL71 | AM71: =AK71-AL71 | AN71: 500/月，1、2、7、8月不收 | AO71: 200 | AP71: 200 | AQ71: =AO71-AP71 | AR71: 0.03 | AS71: =K71*AR71 | AT71: 659.94 | AU71: =AS71-AT71 | AV71: 0.04 | AW71: =K71*AV71 | AX71: 879.92 | AY71: =AW71-AX71 | AZ71: 按实 | BA71: =BB71 | BC71: =BA71-BB71 | BD71: 0 | BE71: =K71*BD71 | BG71: =BE71-BF71 | BH71: 0 | BI71: =K71*BH71 | BK71: =BI71-BJ71 | BL71: 按实 | BM71: 5553.9509 | BN71: 5553.9509 | BO71: =BM71-BN71 | BP71: =N71+Q71+U71+Y71+AC71+AG71+AK71+AO71+AS71+AW71+BA71+BE71+BI71+BM71 | BQ71: =N71+R71+V71+Z71+AD71+AH71+AL71+AP71+AT71+AX71+BB71+BF71+BJ71+BN71 | BR71: =BP71-BQ71 | BS71: / | BT71: / | BU71: 1、甲方管理费：校方按营业额比例13%收取，分组作业应分摊未分摊，已补分摊，服务费比例应做相应调整； | BV71: 1、签订期间：2025.9.1-2026.8.31； 2、指标按照全年换算；
A72: 97 | B72: KQCY0097 | C72: 餐饮二分部 | D72: CF363 | E72: 南通大学启东校区 | F72: 分组作业 | G72: 郑虎 | H72: 第三班组 | I72: 中式早点 | J72: 王正明 | K72: =LET(k,D72&"|"&E72&"|"&H72&"|"&I72&"|"&J72,sk,tblRevenueInput[项目代码]&"|"&tblRevenueInput[项目名称]&"|"&tblRevenueInput[分组作业名称]&"|"&tblRevenueInput[分组作业窗口名称]&"|"&tblRevenueInput[签订人],ok,tblRevenueOverride[项目代码]&"|"&tblRevenueOverride[项目名称]&"|"&tblRevenueOverride[分组作业名称]&"|"&tblRevenueOverride[分组作业窗口名称]&"|"&tblRevenueOverride[责任人],ov,IFERROR(XLOOKUP(k,ok,tblRevenueOverride[营业额覆盖],""),""),IF(ov<>"",ov,IFERROR(XLOOKUP(k,sk,tblRevenueInput[全额营业额合计],""),""))) | N72: 56 | O72: 2000000 | P72: 0.21 | Q72: =K72*P72 | R72: 6379.338 | S72: =Q72-R72 | T72: 0 | U72: =K72*T72 | W72: =U72-V72 | X72: 0 | Y72: =K72*X72 | AA72: =Y72-Z72 | AB72: 0 | AC72: =K72*AB72 | AE72: =AC72-AD72 | AF72: 0 | AG72: =K72*AF72 | AI72: =AG72-AH72 | AJ72: 按比例分摊 | AK72: =AL72 | AM72: =AK72-AL72 | AN72: 500/月，1、2、7、8月不收 | AO72: 200 | AP72: 200 | AQ72: =AO72-AP72 | AR72: 0.03 | AS72: =K72*AR72 | AT72: 911.334 | AU72: =AS72-AT72 | AV72: 0.04 | AW72: =K72*AV72 | AX72: 1215.112 | AY72: =AW72-AX72 | AZ72: 按实 | BA72: =BB72 | BC72: =BA72-BB72 | BD72: 0 | BE72: =K72*BD72 | BG72: =BE72-BF72 | BH72: 0 | BI72: =K72*BH72 | BK72: =BI72-BJ72 | BL72: 按实 | BM72: 5366.7514 | BN72: 5366.7514 | BO72: =BM72-BN72 | BP72: =N72+Q72+U72+Y72+AC72+AG72+AK72+AO72+AS72+AW72+BA72+BE72+BI72+BM72 | BQ72: =N72+R72+V72+Z72+AD72+AH72+AL72+AP72+AT72+AX72+BB72+BF72+BJ72+BN72 | BR72: =BP72-BQ72 | BS72: / | BT72: / | BU72: 1、甲方管理费：校方按营业额比例13%收取，分组作业应分摊未分摊，已补分摊，服务费比例应做相应调整； | BV72: 1、签订期间：2025.9.1-2026.8.31； 2、指标按照全年换算；
A73: 98 | B73: KQCY0098 | C73: 餐饮二分部 | D73: CF363 | E73: 南通大学启东校区 | F73: 分组作业 | G73: 郑虎 | H73: 第四班组 | I73: 黄焖鸡酸菜鱼 | J73: 金健华 | K73: =LET(k,D73&"|"&E73&"|"&H73&"|"&I73&"|"&J73,sk,tblRevenueInput[项目代码]&"|"&tblRevenueInput[项目名称]&"|"&tblRevenueInput[分组作业名称]&"|"&tblRevenueInput[分组作业窗口名称]&"|"&tblRevenueInput[签订人],ok,tblRevenueOverride[项目代码]&"|"&tblRevenueOverride[项目名称]&"|"&tblRevenueOverride[分组作业名称]&"|"&tblRevenueOverride[分组作业窗口名称]&"|"&tblRevenueOverride[责任人],ov,IFERROR(XLOOKUP(k,ok,tblRevenueOverride[营业额覆盖],""),""),IF(ov<>"",ov,IFERROR(XLOOKUP(k,sk,tblRevenueInput[全额营业额合计],""),""))) | N73: 2346.53 | O73: 1080000 | P73: 0.2 | Q73: =K73*P73 | R73: 1614.2 | S73: =Q73-R73 | T73: 0 | U73: =K73*T73 | W73: =U73-V73 | X73: 0 | Y73: =K73*X73 | AA73: =Y73-Z73 | AB73: 0 | AC73: =K73*AB73 | AE73: =AC73-AD73 | AF73: 0 | AG73: =K73*AF73 | AI73: =AG73-AH73 | AJ73: 按比例分摊 | AK73: =AL73 | AM73: =AK73-AL73 | AN73: 500/月，1、2、7、8月不收 | AO73: 200 | AP73: 200 | AQ73: =AO73-AP73 | AR73: 0.03 | AS73: =K73*AR73 | AT73: 242.13 | AU73: =AS73-AT73 | AV73: 0.04 | AW73: =K73*AV73 | AX73: 322.84 | AY73: =AW73-AX73 | AZ73: 按实 | BA73: =BB73 | BC73: =BA73-BB73 | BD73: 0 | BE73: =K73*BD73 | BG73: =BE73-BF73 | BH73: 0 | BI73: =K73*BH73 | BK73: =BI73-BJ73 | BL73: 按实 | BM73: 2170.3092 | BN73: 2170.3092 | BO73: =BM73-BN73 | BP73: =N73+Q73+U73+Y73+AC73+AG73+AK73+AO73+AS73+AW73+BA73+BE73+BI73+BM73 | BQ73: =N73+R73+V73+Z73+AD73+AH73+AL73+AP73+AT73+AX73+BB73+BF73+BJ73+BN73 | BR73: =BP73-BQ73 | BS73: / | BT73: / | BU73: 1、甲方管理费：校方按营业额比例13%收取，分组作业应分摊未分摊，已补分摊，服务费比例应做相应调整； | BV73: 1、签订期间：2025.9.1-2026.8.31； 2、指标按照全年换算；
A74: 99 | B74: KQCY0099 | C74: 餐饮二分部 | D74: CF363 | E74: 南通大学启东校区 | F74: 分组作业 | G74: 郑虎 | H74: 第五班组 | I74: 卤肉饭套餐 | J74: 金健华 | K74: =LET(k,D74&"|"&E74&"|"&H74&"|"&I74&"|"&J74,sk,tblRevenueInput[项目代码]&"|"&tblRevenueInput[项目名称]&"|"&tblRevenueInput[分组作业名称]&"|"&tblRevenueInput[分组作业窗口名称]&"|"&tblRevenueInput[签订人],ok,tblRevenueOverride[项目代码]&"|"&tblRevenueOverride[项目名称]&"|"&tblRevenueOverride[分组作业名称]&"|"&tblRevenueOverride[分组作业窗口名称]&"|"&tblRevenueOverride[责任人],ov,IFERROR(XLOOKUP(k,ok,tblRevenueOverride[营业额覆盖],""),""),IF(ov<>"",ov,IFERROR(XLOOKUP(k,sk,tblRevenueInput[全额营业额合计],""),""))) | N74: 2318.53 | O74: 920000 | P74: 0.2 | Q74: =K74*P74 | R74: 2305.6 | S74: =Q74-R74 | T74: 0 | U74: =K74*T74 | W74: =U74-V74 | X74: 0 | Y74: =K74*X74 | AA74: =Y74-Z74 | AB74: 0 | AC74: =K74*AB74 | AE74: =AC74-AD74 | AF74: 0 | AG74: =K74*AF74 | AI74: =AG74-AH74 | AJ74: 按比例分摊 | AK74: =AL74 | AM74: =AK74-AL74 | AN74: 500/月，1、2、7、8月不收 | AO74: 200 | AP74: 200 | AQ74: =AO74-AP74 | AR74: 0.03 | AS74: =K74*AR74 | AT74: 345.84 | AU74: =AS74-AT74 | AV74: 0.04 | AW74: =K74*AV74 | AX74: 461.12 | AY74: =AW74-AX74 | AZ74: 按实 | BA74: =BB74 | BC74: =BA74-BB74 | BD74: 0 | BE74: =K74*BD74 | BG74: =BE74-BF74 | BH74: 0 | BI74: =K74*BH74 | BK74: =BI74-BJ74 | BL74: 按实 | BM74: 3107.2752 | BN74: 3107.2752 | BO74: =BM74-BN74 | BP74: =N74+Q74+U74+Y74+AC74+AG74+AK74+AO74+AS74+AW74+BA74+BE74+BI74+BM74 | BQ74: =N74+R74+V74+Z74+AD74+AH74+AL74+AP74+AT74+AX74+BB74+BF74+BJ74+BN74 | BR74: =BP74-BQ74 | BS74: / | BT74: / | BU74: 1、甲方管理费：校方按营业额比例13%收取，分组作业应分摊未分摊，已补分摊，服务费比例应做相应调整； | BV74: 1、签订期间：2025.9.1-2026.8.31； 2、指标按照全年换算；
A75: 100 | B75: KQCY0100 | C75: 餐饮二分部 | D75: CF363 | E75: 南通大学启东校区 | F75: 分组作业 | G75: 郑虎 | H75: 第六班组 | I75: 营养粥杂粮煎饼 | J75: 邵国才 | K75: =LET(k,D75&"|"&E75&"|"&H75&"|"&I75&"|"&J75,sk,tblRevenueInput[项目代码]&"|"&tblRevenueInput[项目名称]&"|"&tblRevenueInput[分组作业名称]&"|"&tblRevenueInput[分组作业窗口名称]&"|"&tblRevenueInput[签订人],ok,tblRevenueOverride[项目代码]&"|"&tblRevenueOverride[项目名称]&"|"&tblRevenueOverride[分组作业名称]&"|"&tblRevenueOverride[分组作业窗口名称]&"|"&tblRevenueOverride[责任人],ov,IFERROR(XLOOKUP(k,ok,tblRevenueOverride[营业额覆盖],""),""),IF(ov<>"",ov,IFERROR(XLOOKUP(k,sk,tblRevenueInput[全额营业额合计],""),""))) | N75: 28 | O75: 720000 | P75: 0.23 | Q75: =K75*P75 | R75: 968.645 | S75: =Q75-R75 | T75: 0 | U75: =K75*T75 | W75: =U75-V75 | X75: 0 | Y75: =K75*X75 | AA75: =Y75-Z75 | AB75: 0 | AC75: =K75*AB75 | AE75: =AC75-AD75 | AF75: 0 | AG75: =K75*AF75 | AI75: =AG75-AH75 | AJ75: 按比例分摊 | AK75: =AL75 | AM75: =AK75-AL75 | AN75: 500/月，1、2、7、8月不收 | AO75: 200 | AP75: 200 | AQ75: =AO75-AP75 | AR75: 0.03 | AS75: =K75*AR75 | AT75: 126.345 | AU75: =AS75-AT75 | AV75: 0.04 | AW75: =K75*AV75 | AX75: 168.46 | AY75: =AW75-AX75 | AZ75: 按实 | BA75: =BB75 | BC75: =BA75-BB75 | BD75: 0 | BE75: =K75*BD75 | BG75: =BE75-BF75 | BH75: 0 | BI75: =K75*BH75 | BK75: =BI75-BJ75 | BL75: 按实 | BM75: 318.2058 | BN75: 318.2058 | BO75: =BM75-BN75 | BP75: =N75+Q75+U75+Y75+AC75+AG75+AK75+AO75+AS75+AW75+BA75+BE75+BI75+BM75 | BQ75: =N75+R75+V75+Z75+AD75+AH75+AL75+AP75+AT75+AX75+BB75+BF75+BJ75+BN75 | BR75: =BP75-BQ75 | BS75: / | BT75: / | BU75: 1、甲方管理费：校方按营业额比例13%收取，分组作业应分摊未分摊，已补分摊，服务费比例应做相应调整； | BV75: 1、签订期间：2025.9.1-2026.8.31； 2、指标按照全年换算；
A76: 101 | B76: KQCY0101 | C76: 餐饮二分部 | D76: CF363 | E76: 南通大学启东校区 | F76: 分组作业 | G76: 郑虎 | H76: 第七班组 | I76: 面条馄饨 | J76: 邵国才 | K76: =LET(k,D76&"|"&E76&"|"&H76&"|"&I76&"|"&J76,sk,tblRevenueInput[项目代码]&"|"&tblRevenueInput[项目名称]&"|"&tblRevenueInput[分组作业名称]&"|"&tblRevenueInput[分组作业窗口名称]&"|"&tblRevenueInput[签订人],ok,tblRevenueOverride[项目代码]&"|"&tblRevenueOverride[项目名称]&"|"&tblRevenueOverride[分组作业名称]&"|"&tblRevenueOverride[分组作业窗口名称]&"|"&tblRevenueOverride[责任人],ov,IFERROR(XLOOKUP(k,ok,tblRevenueOverride[营业额覆盖],""),""),IF(ov<>"",ov,IFERROR(XLOOKUP(k,sk,tblRevenueInput[全额营业额合计],""),""))) | N76: 1883.53 | O76: 1080000 | P76: 0.23 | Q76: =K76*P76 | R76: 8158.79 | S76: =Q76-R76 | T76: 0 | U76: =K76*T76 | W76: =U76-V76 | X76: 0 | Y76: =K76*X76 | AA76: =Y76-Z76 | AB76: 0 | AC76: =K76*AB76 | AE76: =AC76-AD76 | AF76: 0 | AG76: =K76*AF76 | AI76: =AG76-AH76 | AJ76: 按比例分摊 | AK76: =AL76 | AM76: =AK76-AL76 | AN76: 500/月，1、2、7、8月不收 | AO76: 200 | AP76: 200 | AQ76: =AO76-AP76 | AR76: 0.03 | AS76: =K76*AR76 | AT76: 1064.19 | AU76: =AS76-AT76 | AV76: 0.04 | AW76: =K76*AV76 | AX76: 1418.92 | AY76: =AW76-AX76 | AZ76: 按实 | BA76: =BB76 | BC76: =BA76-BB76 | BD76: 0 | BE76: =K76*BD76 | BG76: =BE76-BF76 | BH76: 0 | BI76: =K76*BH76 | BK76: =BI76-BJ76 | BL76: 按实 | BM76: 7396.0615 | BN76: 7396.0615 | BO76: =BM76-BN76 | BP76: =N76+Q76+U76+Y76+AC76+AG76+AK76+AO76+AS76+AW76+BA76+BE76+BI76+BM76 | BQ76: =N76+R76+V76+Z76+AD76+AH76+AL76+AP76+AT76+AX76+BB76+BF76+BJ76+BN76 | BR76: =BP76-BQ76 | BS76: / | BT76: / | BU76: 1、甲方管理费：校方按营业额比例13%收取，分组作业应分摊未分摊，已补分摊，服务费比例应做相应调整； | BV76: 1、签订期间：2025.9.1-2026.8.31； 2、指标按照全年换算；
A77: 102 | B77: KQCY0102 | C77: 餐饮二分部 | D77: CF363 | E77: 南通大学启东校区 | F77: 分组作业 | G77: 郑虎 | H77: 第八班组 | I77: 米线汤包 | J77: 王友强 | K77: =LET(k,D77&"|"&E77&"|"&H77&"|"&I77&"|"&J77,sk,tblRevenueInput[项目代码]&"|"&tblRevenueInput[项目名称]&"|"&tblRevenueInput[分组作业名称]&"|"&tblRevenueInput[分组作业窗口名称]&"|"&tblRevenueInput[签订人],ok,tblRevenueOverride[项目代码]&"|"&tblRevenueOverride[项目名称]&"|"&tblRevenueOverride[分组作业名称]&"|"&tblRevenueOverride[分组作业窗口名称]&"|"&tblRevenueOverride[责任人],ov,IFERROR(XLOOKUP(k,ok,tblRevenueOverride[营业额覆盖],""),""),IF(ov<>"",ov,IFERROR(XLOOKUP(k,sk,tblRevenueInput[全额营业额合计],""),""))) | N77: 1840.53 | O77: 880000 | P77: 0.23 | Q77: =K77*P77 | R77: 4684.709 | S77: =Q77-R77 | T77: 0 | U77: =K77*T77 | W77: =U77-V77 | X77: 0 | Y77: =K77*X77 | AA77: =Y77-Z77 | AB77: 0 | AC77: =K77*AB77 | AE77: =AC77-AD77 | AF77: 0 | AG77: =K77*AF77 | AI77: =AG77-AH77 | AJ77: 按比例分摊 | AK77: =AL77 | AM77: =AK77-AL77 | AN77: 500/月，1、2、7、8月不收 | AO77: 200 | AP77: 200 | AQ77: =AO77-AP77 | AR77: 0.03 | AS77: =K77*AR77 | AT77: 611.049 | AU77: =AS77-AT77 | AV77: 0.04 | AW77: =K77*AV77 | AX77: 814.732 | AY77: =AW77-AX77 | AZ77: 按实 | BA77: =BB77 | BC77: =BA77-BB77 | BD77: 0 | BE77: =K77*BD77 | BG77: =BE77-BF77 | BH77: 0 | BI77: =K77*BH77 | BK77: =BI77-BJ77 | BL77: 按实 | BM77: 4937.7602 | BN77: 4937.7602 | BO77: =BM77-BN77 | BP77: =N77+Q77+U77+Y77+AC77+AG77+AK77+AO77+AS77+AW77+BA77+BE77+BI77+BM77 | BQ77: =N77+R77+V77+Z77+AD77+AH77+AL77+AP77+AT77+AX77+BB77+BF77+BJ77+BN77 | BR77: =BP77-BQ77 | BS77: / | BT77: / | BU77: 1、甲方管理费：校方按营业额比例13%收取，分组作业应分摊未分摊，已补分摊，服务费比例应做相应调整； | BV77: 1、签订期间：2025.9.1-2026.8.31； 2、指标按照全年换算；
A78: 103 | B78: KQCY0103 | C78: 餐饮二分部 | D78: CF363 | E78: 南通大学启东校区 | F78: 分组作业 | G78: 郑虎 | H78: 第九班组 | I78: 香锅焖面 | J78: 王正明 | K78: =LET(k,D78&"|"&E78&"|"&H78&"|"&I78&"|"&J78,sk,tblRevenueInput[项目代码]&"|"&tblRevenueInput[项目名称]&"|"&tblRevenueInput[分组作业名称]&"|"&tblRevenueInput[分组作业窗口名称]&"|"&tblRevenueInput[签订人],ok,tblRevenueOverride[项目代码]&"|"&tblRevenueOverride[项目名称]&"|"&tblRevenueOverride[分组作业名称]&"|"&tblRevenueOverride[分组作业窗口名称]&"|"&tblRevenueOverride[责任人],ov,IFERROR(XLOOKUP(k,ok,tblRevenueOverride[营业额覆盖],""),""),IF(ov<>"",ov,IFERROR(XLOOKUP(k,sk,tblRevenueInput[全额营业额合计],""),""))) | N78: 2290.53 | O78: 880000 | P78: 0.23 | Q78: =K78*P78 | R78: 1285.24 | S78: =Q78-R78 | T78: 0 | U78: =K78*T78 | W78: =U78-V78 | X78: 0 | Y78: =K78*X78 | AA78: =Y78-Z78 | AB78: 0 | AC78: =K78*AB78 | AE78: =AC78-AD78 | AF78: 0 | AG78: =K78*AF78 | AI78: =AG78-AH78 | AJ78: 按比例分摊 | AK78: =AL78 | AM78: =AK78-AL78 | AN78: 500/月，1、2、7、8月不收 | AO78: 200 | AP78: 200 | AQ78: =AO78-AP78 | AR78: 0.03 | AS78: =K78*AR78 | AT78: 167.64 | AU78: =AS78-AT78 | AV78: 0.04 | AW78: =K78*AV78 | AX78: 223.52 | AY78: =AW78-AX78 | AZ78: 按实 | BA78: =BB78 | BC78: =BA78-BB78 | BD78: 0 | BE78: =K78*BD78 | BG78: =BE78-BF78 | BH78: 0 | BI78: =K78*BH78 | BK78: =BI78-BJ78 | BL78: 按实 | BM78: 696.77137 | BN78: 696.77137 | BO78: =BM78-BN78 | BP78: =N78+Q78+U78+Y78+AC78+AG78+AK78+AO78+AS78+AW78+BA78+BE78+BI78+BM78 | BQ78: =N78+R78+V78+Z78+AD78+AH78+AL78+AP78+AT78+AX78+BB78+BF78+BJ78+BN78 | BR78: =BP78-BQ78 | BS78: / | BT78: / | BU78: 1、甲方管理费：校方按营业额比例13%收取，分组作业应分摊未分摊，已补分摊，服务费比例应做相应调整； | BV78: 1、签订期间：2025.9.1-2026.8.31； 2、指标按照全年换算；
A79: 104 | B79: KQCY0104 | C79: 餐饮二分部 | D79: CF363 | E79: 南通大学启东校区 | F79: 分组作业 | G79: 郑虎 | H79: 第十班组 | I79: 猪肚鸡瓦罐汤套餐 | J79: 翟林璐 | K79: =LET(k,D79&"|"&E79&"|"&H79&"|"&I79&"|"&J79,sk,tblRevenueInput[项目代码]&"|"&tblRevenueInput[项目名称]&"|"&tblRevenueInput[分组作业名称]&"|"&tblRevenueInput[分组作业窗口名称]&"|"&tblRevenueInput[签订人],ok,tblRevenueOverride[项目代码]&"|"&tblRevenueOverride[项目名称]&"|"&tblRevenueOverride[分组作业名称]&"|"&tblRevenueOverride[分组作业窗口名称]&"|"&tblRevenueOverride[责任人],ov,IFERROR(XLOOKUP(k,ok,tblRevenueOverride[营业额覆盖],""),""),IF(ov<>"",ov,IFERROR(XLOOKUP(k,sk,tblRevenueInput[全额营业额合计],""),""))) | N79: 2318.53 | O79: 1520000 | P79: 0.21 | Q79: =K79*P79 | R79: 7328.307 | S79: =Q79-R79 | T79: 0 | U79: =K79*T79 | W79: =U79-V79 | X79: 0 | Y79: =K79*X79 | AA79: =Y79-Z79 | AB79: 0 | AC79: =K79*AB79 | AE79: =AC79-AD79 | AF79: 0 | AG79: =K79*AF79 | AI79: =AG79-AH79 | AJ79: 按比例分摊 | AK79: =AL79 | AM79: =AK79-AL79 | AN79: 500/月，1、2、7、8月不收 | AO79: 200 | AP79: 200 | AQ79: =AO79-AP79 | AR79: 0.03 | AS79: =K79*AR79 | AT79: 1046.901 | AU79: =AS79-AT79 | AV79: 0.04 | AW79: =K79*AV79 | AX79: 1395.868 | AY79: =AW79-AX79 | AZ79: 按实 | BA79: =BB79 | BC79: =BA79-BB79 | BD79: 0 | BE79: =K79*BD79 | BG79: =BE79-BF79 | BH79: 0 | BI79: =K79*BH79 | BK79: =BI79-BJ79 | BL79: 按实 | BM79: 10798.775 | BN79: 10798.775 | BO79: =BM79-BN79 | BP79: =N79+Q79+U79+Y79+AC79+AG79+AK79+AO79+AS79+AW79+BA79+BE79+BI79+BM79 | BQ79: =N79+R79+V79+Z79+AD79+AH79+AL79+AP79+AT79+AX79+BB79+BF79+BJ79+BN79 | BR79: =BP79-BQ79 | BS79: / | BT79: / | BU79: 1、甲方管理费：校方按营业额比例13%收取，分组作业应分摊未分摊，已补分摊，服务费比例应做相应调整； | BV79: 1、签订期间：2025.9.1-2026.8.31； 2、指标按照全年换算；
A80: 105 | B80: KQCY0105 | C80: 餐饮二分部 | D80: CF363 | E80: 南通大学启东校区 | F80: 分组作业 | G80: 郑虎 | H80: 第十一班组 | I80: 汉堡小锅现炒 | J80: 韩荣荣 | K80: =LET(k,D80&"|"&E80&"|"&H80&"|"&I80&"|"&J80,sk,tblRevenueInput[项目代码]&"|"&tblRevenueInput[项目名称]&"|"&tblRevenueInput[分组作业名称]&"|"&tblRevenueInput[分组作业窗口名称]&"|"&tblRevenueInput[签订人],ok,tblRevenueOverride[项目代码]&"|"&tblRevenueOverride[项目名称]&"|"&tblRevenueOverride[分组作业名称]&"|"&tblRevenueOverride[分组作业窗口名称]&"|"&tblRevenueOverride[责任人],ov,IFERROR(XLOOKUP(k,ok,tblRevenueOverride[营业额覆盖],""),""),IF(ov<>"",ov,IFERROR(XLOOKUP(k,sk,tblRevenueInput[全额营业额合计],""),""))) | N80: 3625.06 | O80: 1080000 | P80: 0.22 | Q80: =K80*P80 | R80: 9648.705 | S80: =Q80-R80 | T80: 0 | U80: =K80*T80 | W80: =U80-V80 | X80: 0 | Y80: =K80*X80 | AA80: =Y80-Z80 | AB80: 0 | AC80: =K80*AB80 | AE80: =AC80-AD80 | AF80: 0 | AG80: =K80*AF80 | AI80: =AG80-AH80 | AJ80: 按比例分摊 | AK80: =AL80 | AM80: =AK80-AL80 | AN80: 500/月，1、2、7、8月不收 | AO80: 200 | AP80: 200 | AQ80: =AO80-AP80 | AR80: 0.03 | AS80: =K80*AR80 | AT80: 1315.7325 | AU80: =AS80-AT80 | AV80: 0.04 | AW80: =K80*AV80 | AX80: 1754.31 | AY80: =AW80-AX80 | AZ80: 按实 | BA80: =BB80 | BC80: =BA80-BB80 | BD80: 0 | BE80: =K80*BD80 | BG80: =BE80-BF80 | BH80: 0 | BI80: =K80*BH80 | BK80: =BI80-BJ80 | BL80: 按实 | BM80: 6200.8516 | BN80: 6200.8516 | BO80: =BM80-BN80 | BP80: =N80+Q80+U80+Y80+AC80+AG80+AK80+AO80+AS80+AW80+BA80+BE80+BI80+BM80 | BQ80: =N80+R80+V80+Z80+AD80+AH80+AL80+AP80+AT80+AX80+BB80+BF80+BJ80+BN80 | BR80: =BP80-BQ80 | BS80: / | BT80: / | BU80: 1、甲方管理费：校方按营业额比例13%收取，分组作业应分摊未分摊，已补分摊，服务费比例应做相应调整； | BV80: 1、签订期间：2025.9.1-2026.8.31； 2、指标按照全年换算；
A81: 106 | B81: KQCY0106 | C81: 餐饮二分部 | D81: CF363 | E81: 南通大学启东校区 | F81: 分组作业 | G81: 郑虎 | H81: 第十二班组 | I81: 铁板炒饭 | J81: 王志河 | K81: =LET(k,D81&"|"&E81&"|"&H81&"|"&I81&"|"&J81,sk,tblRevenueInput[项目代码]&"|"&tblRevenueInput[项目名称]&"|"&tblRevenueInput[分组作业名称]&"|"&tblRevenueInput[分组作业窗口名称]&"|"&tblRevenueInput[签订人],ok,tblRevenueOverride[项目代码]&"|"&tblRevenueOverride[项目名称]&"|"&tblRevenueOverride[分组作业名称]&"|"&tblRevenueOverride[分组作业窗口名称]&"|"&tblRevenueOverride[责任人],ov,IFERROR(XLOOKUP(k,ok,tblRevenueOverride[营业额覆盖],""),""),IF(ov<>"",ov,IFERROR(XLOOKUP(k,sk,tblRevenueInput[全额营业额合计],""),""))) | N81: 4075.06 | O81: 880000 | P81: 0.23 | Q81: =K81*P81 | R81: 5904.79 | S81: =Q81-R81 | T81: 0 | U81: =K81*T81 | W81: =U81-V81 | X81: 0 | Y81: =K81*X81 | AA81: =Y81-Z81 | AB81: 0 | AC81: =K81*AB81 | AE81: =AC81-AD81 | AF81: 0 | AG81: =K81*AF81 | AI81: =AG81-AH81 | AJ81: 按比例分摊 | AK81: =AL81 | AM81: =AK81-AL81 | AN81: 500/月，1、2、7、8月不收 | AO81: 200 | AP81: 200 | AQ81: =AO81-AP81 | AR81: 0.03 | AS81: =K81*AR81 | AT81: 770.19 | AU81: =AS81-AT81 | AV81: 0.04 | AW81: =K81*AV81 | AX81: 1026.92 | AY81: =AW81-AX81 | AZ81: 按实 | BA81: =BB81 | BB81: 500 | BC81: =BA81-BB81 | BD81: 0 | BE81: =K81*BD81 | BG81: =BE81-BF81 | BH81: 0 | BI81: =K81*BH81 | BK81: =BI81-BJ81 | BL81: 按实 | BM81: 7310.7238 | BN81: 7310.7238 | BO81: =BM81-BN81 | BP81: =N81+Q81+U81+Y81+AC81+AG81+AK81+AO81+AS81+AW81+BA81+BE81+BI81+BM81 | BQ81: =N81+R81+V81+Z81+AD81+AH81+AL81+AP81+AT81+AX81+BB81+BF81+BJ81+BN81 | BR81: =BP81-BQ81 | BS81: / | BT81: / | BU81: 1、甲方管理费：校方按营业额比例13%收取，分组作业应分摊未分摊，已补分摊，服务费比例应做相应调整； | BV81: 1、签订期间：2025.9.1-2026.8.31； 2、指标按照全年换算；
A82: 107 | B82: KQCY0107 | C82: 餐饮二分部 | D82: CF160 | E82: 高新区实验高中食堂(金山路校区) | F82: 人员服务外包 | G82: 陈晨 | H82: / | I82: / | J82: / | K82: =LET(k,D82&"|"&E82&"|"&H82&"|"&I82&"|"&J82,sk,tblRevenueInput[项目代码]&"|"&tblRevenueInput[项目名称]&"|"&tblRevenueInput[分组作业名称]&"|"&tblRevenueInput[分组作业窗口名称]&"|"&tblRevenueInput[签订人],ok,tblRevenueOverride[项目代码]&"|"&tblRevenueOverride[项目名称]&"|"&tblRevenueOverride[分组作业名称]&"|"&tblRevenueOverride[分组作业窗口名称]&"|"&tblRevenueOverride[责任人],ov,IFERROR(XLOOKUP(k,ok,tblRevenueOverride[营业额覆盖],""),""),IF(ov<>"",ov,IFERROR(XLOOKUP(k,sk,tblRevenueInput[全额营业额合计],""),""))) | O82: 2462000 | P82: 0 | Q82: =K82*P82 | S82: =Q82-R82 | T82: 0 | U82: =K82*T82 | W82: =U82-V82 | X82: 0 | Y82: =K82*X82 | AA82: =Y82-Z82 | AB82: 0 | AC82: =K82*AB82 | AE82: =AC82-AD82 | AF82: 0 | AG82: =K82*AF82 | AI82: =AG82-AH82 | AJ82: 0 | AK82: =K82*AJ82 | AM82: =AK82-AL82 | AN82: 0 | AO82: =K82*AN82 | AQ82: =AO82-AP82 | AR82: 0 | AS82: =K82*AR82 | AU82: =AS82-AT82 | AV82: 0 | AW82: =K82*AV82 | AY82: =AW82-AX82 | AZ82: 0 | BA82: =K82*AZ82 | BC82: =BA82-BB82 | BE82: =K82*BD82 | BG82: =BE82-BF82 | BI82: =K82*BH82 | BK82: =BI82-BJ82 | BL82: 0 | BM82: =K82*BL82 | BO82: =BM82-BN82 | BP82: =N82+Q82+U82+Y82+AC82+AG82+AK82+AO82+AS82+AW82+BA82+BE82+BI82+BM82 | BQ82: =N82+R82+V82+Z82+AD82+AH82+AL82+AP82+AT82+AX82+BB82+BF82+BJ82+BN82 | BR82: =BP82-BQ82 | BT82: / | BU82: 1、分部管理费：卡机营业额的3%，最高限额20万元
A83: 108 | B83: KQCY0108 | C83: 餐饮二分部 | D83: CF174 | E83: 高新区实验高中食堂(科技城校区) | F83: 人员服务外包 | G83: 陈晨 | H83: / | I83: / | J83: / | K83: =LET(k,D83&"|"&E83&"|"&H83&"|"&I83&"|"&J83,sk,tblRevenueInput[项目代码]&"|"&tblRevenueInput[项目名称]&"|"&tblRevenueInput[分组作业名称]&"|"&tblRevenueInput[分组作业窗口名称]&"|"&tblRevenueInput[签订人],ok,tblRevenueOverride[项目代码]&"|"&tblRevenueOverride[项目名称]&"|"&tblRevenueOverride[分组作业名称]&"|"&tblRevenueOverride[分组作业窗口名称]&"|"&tblRevenueOverride[责任人],ov,IFERROR(XLOOKUP(k,ok,tblRevenueOverride[营业额覆盖],""),""),IF(ov<>"",ov,IFERROR(XLOOKUP(k,sk,tblRevenueInput[全额营业额合计],""),""))) | O83: 2465000 | P83: 0 | Q83: =K83*P83 | S83: =Q83-R83 | T83: 0 | U83: =K83*T83 | W83: =U83-V83 | X83: 0 | Y83: =K83*X83 | AA83: =Y83-Z83 | AB83: 0 | AC83: =K83*AB83 | AE83: =AC83-AD83 | AF83: 0 | AG83: =K83*AF83 | AI83: =AG83-AH83 | AJ83: 0 | AK83: =K83*AJ83 | AM83: =AK83-AL83 | AN83: 0 | AO83: =K83*AN83 | AQ83: =AO83-AP83 | AR83: 0 | AS83: =K83*AR83 | AU83: =AS83-AT83 | AV83: 0 | AW83: =K83*AV83 | AY83: =AW83-AX83 | AZ83: 0 | BA83: =K83*AZ83 | BC83: =BA83-BB83 | BE83: =K83*BD83 | BG83: =BE83-BF83 | BI83: =K83*BH83 | BK83: =BI83-BJ83 | BL83: 0 | BM83: =K83*BL83 | BO83: =BM83-BN83 | BP83: =N83+Q83+U83+Y83+AC83+AG83+AK83+AO83+AS83+AW83+BA83+BE83+BI83+BM83 | BQ83: =N83+R83+V83+Z83+AD83+AH83+AL83+AP83+AT83+AX83+BB83+BF83+BJ83+BN83 | BR83: =BP83-BQ83 | BT83: / | BU83: 1、分部管理费：卡机营业额的3%，最高限额20万元
A84: 109 | B84: KQCY0109 | C84: 餐饮二分部 | D84: CF175 | E84: 高新区实验初中食堂(金山路校区) | F84: 人员服务外包 | G84: 陈晨 | H84: / | I84: / | J84: / | K84: =LET(k,D84&"|"&E84&"|"&H84&"|"&I84&"|"&J84,sk,tblRevenueInput[项目代码]&"|"&tblRevenueInput[项目名称]&"|"&tblRevenueInput[分组作业名称]&"|"&tblRevenueInput[分组作业窗口名称]&"|"&tblRevenueInput[签订人],ok,tblRevenueOverride[项目代码]&"|"&tblRevenueOverride[项目名称]&"|"&tblRevenueOverride[分组作业名称]&"|"&tblRevenueOverride[分组作业窗口名称]&"|"&tblRevenueOverride[责任人],ov,IFERROR(XLOOKUP(k,ok,tblRevenueOverride[营业额覆盖],""),""),IF(ov<>"",ov,IFERROR(XLOOKUP(k,sk,tblRevenueInput[全额营业额合计],""),""))) | O84: 2650000 | P84: 0 | Q84: =K84*P84 | S84: =Q84-R84 | T84: 0 | U84: =K84*T84 | W84: =U84-V84 | X84: 0 | Y84: =K84*X84 | AA84: =Y84-Z84 | AB84: 0 | AC84: =K84*AB84 | AE84: =AC84-AD84 | AF84: 0 | AG84: =K84*AF84 | AI84: =AG84-AH84 | AJ84: 0 | AK84: =K84*AJ84 | AM84: =AK84-AL84 | AN84: 0 | AO84: =K84*AN84 | AQ84: =AO84-AP84 | AR84: 0 | AS84: =K84*AR84 | AU84: =AS84-AT84 | AV84: 0 | AW84: =K84*AV84 | AY84: =AW84-AX84 | AZ84: 0 | BA84: =K84*AZ84 | BC84: =BA84-BB84 | BE84: =K84*BD84 | BG84: =BE84-BF84 | BI84: =K84*BH84 | BK84: =BI84-BJ84 | BL84: 0 | BM84: =K84*BL84 | BO84: =BM84-BN84 | BP84: =N84+Q84+U84+Y84+AC84+AG84+AK84+AO84+AS84+AW84+BA84+BE84+BI84+BM84 | BQ84: =N84+R84+V84+Z84+AD84+AH84+AL84+AP84+AT84+AX84+BB84+BF84+BJ84+BN84 | BR84: =BP84-BQ84 | BT84: / | BU84: 1、分部管理费：卡机营业额的3%，最高限额20万元
A85: 110 | B85: KQCY0110 | C85: 餐饮二分部 | D85: CF177 | E85: 高新区实验初中食堂(锦峰路校区) | F85: 人员服务外包 | G85: 陈晨 | H85: / | I85: / | J85: / | K85: =LET(k,D85&"|"&E85&"|"&H85&"|"&I85&"|"&J85,sk,tblRevenueInput[项目代码]&"|"&tblRevenueInput[项目名称]&"|"&tblRevenueInput[分组作业名称]&"|"&tblRevenueInput[分组作业窗口名称]&"|"&tblRevenueInput[签订人],ok,tblRevenueOverride[项目代码]&"|"&tblRevenueOverride[项目名称]&"|"&tblRevenueOverride[分组作业名称]&"|"&tblRevenueOverride[分组作业窗口名称]&"|"&tblRevenueOverride[责任人],ov,IFERROR(XLOOKUP(k,ok,tblRevenueOverride[营业额覆盖],""),""),IF(ov<>"",ov,IFERROR(XLOOKUP(k,sk,tblRevenueInput[全额营业额合计],""),""))) | O85: 1574000 | P85: 0 | Q85: =K85*P85 | S85: =Q85-R85 | T85: 0 | U85: =K85*T85 | W85: =U85-V85 | X85: 0 | Y85: =K85*X85 | AA85: =Y85-Z85 | AB85: 0 | AC85: =K85*AB85 | AE85: =AC85-AD85 | AF85: 0 | AG85: =K85*AF85 | AI85: =AG85-AH85 | AJ85: 0 | AK85: =K85*AJ85 | AM85: =AK85-AL85 | AN85: 0 | AO85: =K85*AN85 | AQ85: =AO85-AP85 | AR85: 0 | AS85: =K85*AR85 | AU85: =AS85-AT85 | AV85: 0 | AW85: =K85*AV85 | AY85: =AW85-AX85 | AZ85: 0 | BA85: =K85*AZ85 | BC85: =BA85-BB85 | BE85: =K85*BD85 | BG85: =BE85-BF85 | BI85: =K85*BH85 | BK85: =BI85-BJ85 | BL85: 0 | BM85: =K85*BL85 | BO85: =BM85-BN85 | BP85: =N85+Q85+U85+Y85+AC85+AG85+AK85+AO85+AS85+AW85+BA85+BE85+BI85+BM85 | BQ85: =N85+R85+V85+Z85+AD85+AH85+AL85+AP85+AT85+AX85+BB85+BF85+BJ85+BN85 | BR85: =BP85-BQ85 | BT85: / | BU85: 1、分部管理费：卡机营业额的3%，最高限额20万元
A86: 111 | B86: KQCY0111 | C86: 餐饮二分部 | D86: CF173 | E86: 高新区一中食堂（汾湖路校区） | F86: 人员服务外包 | G86: 陈晨 | H86: / | I86: / | J86: / | K86: =LET(k,D86&"|"&E86&"|"&H86&"|"&I86&"|"&J86,sk,tblRevenueInput[项目代码]&"|"&tblRevenueInput[项目名称]&"|"&tblRevenueInput[分组作业名称]&"|"&tblRevenueInput[分组作业窗口名称]&"|"&tblRevenueInput[签订人],ok,tblRevenueOverride[项目代码]&"|"&tblRevenueOverride[项目名称]&"|"&tblRevenueOverride[分组作业名称]&"|"&tblRevenueOverride[分组作业窗口名称]&"|"&tblRevenueOverride[责任人],ov,IFERROR(XLOOKUP(k,ok,tblRevenueOverride[营业额覆盖],""),""),IF(ov<>"",ov,IFERROR(XLOOKUP(k,sk,tblRevenueInput[全额营业额合计],""),""))) | O86: 3130000 | P86: 0 | Q86: =K86*P86 | S86: =Q86-R86 | T86: 0 | U86: =K86*T86 | W86: =U86-V86 | X86: 0 | Y86: =K86*X86 | AA86: =Y86-Z86 | AB86: 0 | AC86: =K86*AB86 | AE86: =AC86-AD86 | AF86: 0 | AG86: =K86*AF86 | AI86: =AG86-AH86 | AJ86: 0 | AK86: =K86*AJ86 | AM86: =AK86-AL86 | AN86: 0 | AO86: =K86*AN86 | AQ86: =AO86-AP86 | AR86: 0 | AS86: =K86*AR86 | AU86: =AS86-AT86 | AV86: 0 | AW86: =K86*AV86 | AY86: =AW86-AX86 | AZ86: 0 | BA86: =K86*AZ86 | BC86: =BA86-BB86 | BE86: =K86*BD86 | BG86: =BE86-BF86 | BI86: =K86*BH86 | BK86: =BI86-BJ86 | BL86: 0 | BM86: =K86*BL86 | BO86: =BM86-BN86 | BP86: =N86+Q86+U86+Y86+AC86+AG86+AK86+AO86+AS86+AW86+BA86+BE86+BI86+BM86 | BQ86: =N86+R86+V86+Z86+AD86+AH86+AL86+AP86+AT86+AX86+BB86+BF86+BJ86+BN86 | BR86: =BP86-BQ86 | BT86: / | BU86: 1、分部管理费：卡机营业额的3%，最高限额20万元
A87: 112 | B87: KQCY0112 | C87: 餐饮二分部 | D87: CF179 | E87: 高新区一中食堂（科技城校区） | F87: 人员服务外包 | G87: 陈晨 | H87: / | I87: / | J87: / | K87: =LET(k,D87&"|"&E87&"|"&H87&"|"&I87&"|"&J87,sk,tblRevenueInput[项目代码]&"|"&tblRevenueInput[项目名称]&"|"&tblRevenueInput[分组作业名称]&"|"&tblRevenueInput[分组作业窗口名称]&"|"&tblRevenueInput[签订人],ok,tblRevenueOverride[项目代码]&"|"&tblRevenueOverride[项目名称]&"|"&tblRevenueOverride[分组作业名称]&"|"&tblRevenueOverride[分组作业窗口名称]&"|"&tblRevenueOverride[责任人],ov,IFERROR(XLOOKUP(k,ok,tblRevenueOverride[营业额覆盖],""),""),IF(ov<>"",ov,IFERROR(XLOOKUP(k,sk,tblRevenueInput[全额营业额合计],""),""))) | O87: 2588000 | P87: 0 | Q87: =K87*P87 | S87: =Q87-R87 | T87: 0 | U87: =K87*T87 | W87: =U87-V87 | X87: 0 | Y87: =K87*X87 | AA87: =Y87-Z87 | AB87: 0 | AC87: =K87*AB87 | AE87: =AC87-AD87 | AF87: 0 | AG87: =K87*AF87 | AI87: =AG87-AH87 | AJ87: 0 | AK87: =K87*AJ87 | AM87: =AK87-AL87 | AN87: 0 | AO87: =K87*AN87 | AQ87: =AO87-AP87 | AR87: 0 | AS87: =K87*AR87 | AU87: =AS87-AT87 | AV87: 0 | AW87: =K87*AV87 | AY87: =AW87-AX87 | AZ87: 0 | BA87: =K87*AZ87 | BC87: =BA87-BB87 | BE87: =K87*BD87 | BG87: =BE87-BF87 | BI87: =K87*BH87 | BK87: =BI87-BJ87 | BL87: 0 | BM87: =K87*BL87 | BO87: =BM87-BN87 | BP87: =N87+Q87+U87+Y87+AC87+AG87+AK87+AO87+AS87+AW87+BA87+BE87+BI87+BM87 | BQ87: =N87+R87+V87+Z87+AD87+AH87+AL87+AP87+AT87+AX87+BB87+BF87+BJ87+BN87 | BR87: =BP87-BQ87 | BT87: / | BU87: 1、分部管理费：卡机营业额的3%，最高限额20万元
A88: 113 | B88: KQCY0113 | C88: 餐饮二分部 | D88: CF180 | E88: 高新区一初中食堂（珠江路校区） | F88: 人员服务外包 | G88: 陈晨 | H88: / | I88: / | J88: / | K88: =LET(k,D88&"|"&E88&"|"&H88&"|"&I88&"|"&J88,sk,tblRevenueInput[项目代码]&"|"&tblRevenueInput[项目名称]&"|"&tblRevenueInput[分组作业名称]&"|"&tblRevenueInput[分组作业窗口名称]&"|"&tblRevenueInput[签订人],ok,tblRevenueOverride[项目代码]&"|"&tblRevenueOverride[项目名称]&"|"&tblRevenueOverride[分组作业名称]&"|"&tblRevenueOverride[分组作业窗口名称]&"|"&tblRevenueOverride[责任人],ov,IFERROR(XLOOKUP(k,ok,tblRevenueOverride[营业额覆盖],""),""),IF(ov<>"",ov,IFERROR(XLOOKUP(k,sk,tblRevenueInput[全额营业额合计],""),""))) | O88: 1249000 | P88: 0 | Q88: =K88*P88 | S88: =Q88-R88 | T88: 0 | U88: =K88*T88 | W88: =U88-V88 | X88: 0 | Y88: =K88*X88 | AA88: =Y88-Z88 | AB88: 0 | AC88: =K88*AB88 | AE88: =AC88-AD88 | AF88: 0 | AG88: =K88*AF88 | AI88: =AG88-AH88 | AJ88: 0 | AK88: =K88*AJ88 | AM88: =AK88-AL88 | AN88: 0 | AO88: =K88*AN88 | AQ88: =AO88-AP88 | AR88: 0 | AS88: =K88*AR88 | AU88: =AS88-AT88 | AV88: 0 | AW88: =K88*AV88 | AY88: =AW88-AX88 | AZ88: 0 | BA88: =K88*AZ88 | BC88: =BA88-BB88 | BE88: =K88*BD88 | BG88: =BE88-BF88 | BI88: =K88*BH88 | BK88: =BI88-BJ88 | BL88: 0 | BM88: =K88*BL88 | BO88: =BM88-BN88 | BP88: =N88+Q88+U88+Y88+AC88+AG88+AK88+AO88+AS88+AW88+BA88+BE88+BI88+BM88 | BQ88: =N88+R88+V88+Z88+AD88+AH88+AL88+AP88+AT88+AX88+BB88+BF88+BJ88+BN88 | BR88: =BP88-BQ88 | BT88: / | BU88: 1、分部管理费：卡机营业额的3%，最高限额20万元
A89: 114 | B89: KQCY0114 | C89: 餐饮二分部 | D89: CF183 | E89: 中医科苏州新校区食堂 | F89: 人员服务外包 | G89: 徐敏捷 | H89: / | I89: / | J89: / | K89: =LET(k,D89&"|"&E89&"|"&H89&"|"&I89&"|"&J89,sk,tblRevenueInput[项目代码]&"|"&tblRevenueInput[项目名称]&"|"&tblRevenueInput[分组作业名称]&"|"&tblRevenueInput[分组作业窗口名称]&"|"&tblRevenueInput[签订人],ok,tblRevenueOverride[项目代码]&"|"&tblRevenueOverride[项目名称]&"|"&tblRevenueOverride[分组作业名称]&"|"&tblRevenueOverride[分组作业窗口名称]&"|"&tblRevenueOverride[责任人],ov,IFERROR(XLOOKUP(k,ok,tblRevenueOverride[营业额覆盖],""),""),IF(ov<>"",ov,IFERROR(XLOOKUP(k,sk,tblRevenueInput[全额营业额合计],""),""))) | O89: 0 | P89: 0 | Q89: =K89*P89 | S89: =Q89-R89 | T89: 0 | U89: =K89*T89 | W89: =U89-V89 | X89: 0 | Y89: =K89*X89 | AA89: =Y89-Z89 | AB89: 0 | AC89: =K89*AB89 | AE89: =AC89-AD89 | AF89: 0 | AG89: =K89*AF89 | AI89: =AG89-AH89 | AJ89: 0 | AK89: =K89*AJ89 | AM89: =AK89-AL89 | AN89: 0 | AO89: =K89*AN89 | AQ89: =AO89-AP89 | AR89: 0 | AS89: =K89*AR89 | AU89: =AS89-AT89 | AV89: 0 | AW89: =K89*AV89 | AY89: =AW89-AX89 | AZ89: 0 | BA89: =K89*AZ89 | BC89: =BA89-BB89 | BE89: =K89*BD89 | BG89: =BE89-BF89 | BI89: =K89*BH89 | BK89: =BI89-BJ89 | BL89: 0 | BM89: =K89*BL89 | BO89: =BM89-BN89 | BP89: =N89+Q89+U89+Y89+AC89+AG89+AK89+AO89+AS89+AW89+BA89+BE89+BI89+BM89 | BQ89: =N89+R89+V89+Z89+AD89+AH89+AL89+AP89+AT89+AX89+BB89+BF89+BJ89+BN89 | BR89: =BP89-BQ89 | BS89: 0.08 | BT89: 0.015
A90: 117 | B90: KQCY0117 | C90: 餐饮二分部 | D90: CF450 | E90: 天津大学学二食堂 | F90: 强责 | G90: 徐敏捷 | H90: / | I90: 馄饨（轻食） | J90: 李佳玉 | K90: =LET(k,D90&"|"&E90&"|"&H90&"|"&I90&"|"&J90,sk,tblRevenueInput[项目代码]&"|"&tblRevenueInput[项目名称]&"|"&tblRevenueInput[分组作业名称]&"|"&tblRevenueInput[分组作业窗口名称]&"|"&tblRevenueInput[签订人],ok,tblRevenueOverride[项目代码]&"|"&tblRevenueOverride[项目名称]&"|"&tblRevenueOverride[分组作业名称]&"|"&tblRevenueOverride[分组作业窗口名称]&"|"&tblRevenueOverride[责任人],ov,IFERROR(XLOOKUP(k,ok,tblRevenueOverride[营业额覆盖],""),""),IF(ov<>"",ov,IFERROR(XLOOKUP(k,sk,tblRevenueInput[全额营业额合计],""),""))) | N90: 59195 | O90: 400000 | P90: 0.17 | Q90: =K90*P90 | R90: 42136.26 | S90: =Q90-R90 | T90: 0 | U90: =K90*T90 | V90: 0 | W90: =U90-V90 | X90: 0.02 | Y90: =K90*X90 | Z90: 5479.77 | AA90: =Y90-Z90 | AB90: 0 | AC90: =K90*AB90 | AD90: 0 | AE90: =AC90-AD90 | AF90: 0 | AG90: =K90*AF90 | AH90: 0 | AI90: =AG90-AH90 | AJ90: 0 | AK90: =K90*AJ90 | AL90: 0 | AM90: =AK90-AL90 | AN90: 0 | AO90: =K90*AN90 | AP90: 0 | AQ90: =AO90-AP90 | AR90: 0.04 | AS90: =K90*AR90 | AT90: 10959.55 | AU90: =AS90-AT90 | AV90: 0.04 | AW90: =K90*AV90 | AX90: 10475.37 | AY90: =AW90-AX90 | AZ90: 0 | BA90: =K90*AZ90 | BB90: 0 | BC90: =BA90-BB90 | BE90: =K90*BD90 | BF90: 0 | BG90: =BE90-BF90 | BI90: =K90*BH90 | BJ90: 0 | BK90: =BI90-BJ90 | BL90: 按实 | BM90: =BN90 | BN90: 139626.01 | BO90: =BM90-BN90 | BP90: =N90+Q90+U90+Y90+AC90+AG90+AK90+AO90+AS90+AW90+BA90+BE90+BI90+BM90 | BQ90: =N90+R90+V90+Z90+AD90+AH90+AL90+AP90+AT90+AX90+BB90+BF90+BJ90+BN90 | BR90: =BP90-BQ90 | BS90: / | BT90: / | BV90: 1、签订期间：2026.1.1-2026.8.1； 2、指标按照全年换算；
A91: 118 | B91: KQCY0118 | C91: 餐饮二分部 | D91: CF450 | E91: 天津大学学二食堂 | F91: 强责 | G91: 徐敏捷 | H91: / | I91: 面夫子 | J91: 刘魁 | K91: =LET(k,D91&"|"&E91&"|"&H91&"|"&I91&"|"&J91,sk,tblRevenueInput[项目代码]&"|"&tblRevenueInput[项目名称]&"|"&tblRevenueInput[分组作业名称]&"|"&tblRevenueInput[分组作业窗口名称]&"|"&tblRevenueInput[签订人],ok,tblRevenueOverride[项目代码]&"|"&tblRevenueOverride[项目名称]&"|"&tblRevenueOverride[分组作业名称]&"|"&tblRevenueOverride[分组作业窗口名称]&"|"&tblRevenueOverride[责任人],ov,IFERROR(XLOOKUP(k,ok,tblRevenueOverride[营业额覆盖],""),""),IF(ov<>"",ov,IFERROR(XLOOKUP(k,sk,tblRevenueInput[全额营业额合计],""),""))) | O91: 380000 | P91: 0.15 | Q91: =K91*P91 | S91: =Q91-R91 | T91: 0 | U91: =K91*T91 | W91: =U91-V91 | X91: 0.02 | Y91: =K91*X91 | AA91: =Y91-Z91 | AB91: 0 | AC91: =K91*AB91 | AE91: =AC91-AD91 | AF91: 0 | AG91: =K91*AF91 | AI91: =AG91-AH91 | AJ91: 0 | AK91: =K91*AJ91 | AM91: =AK91-AL91 | AN91: 0 | AO91: =K91*AN91 | AQ91: =AO91-AP91 | AR91: 0.04 | AS91: =K91*AR91 | AU91: =AS91-AT91 | AV91: 0.04 | AW91: =K91*AV91 | AY91: =AW91-AX91 | AZ91: 0 | BA91: =K91*AZ91 | BC91: =BA91-BB91 | BE91: =K91*BD91 | BG91: =BE91-BF91 | BI91: =K91*BH91 | BK91: =BI91-BJ91 | BL91: 按实 | BM91: =BN91 | BO91: =BM91-BN91 | BP91: =N91+Q91+U91+Y91+AC91+AG91+AK91+AO91+AS91+AW91+BA91+BE91+BI91+BM91 | BQ91: =N91+R91+V91+Z91+AD91+AH91+AL91+AP91+AT91+AX91+BB91+BF91+BJ91+BN91 | BR91: =BP91-BQ91 | BS91: / | BT91: / | BV91: 1、签订期间：2026.1.1-2026.8.1； 2、指标按照全年换算；
A92: 119 | B92: KQCY0119 | C92: 餐饮二分部 | D92: CF450 | E92: 天津大学学二食堂 | F92: 强责 | G92: 徐敏捷 | H92: / | I92: 滑蛋饭 | J92: 李保 | K92: =LET(k,D92&"|"&E92&"|"&H92&"|"&I92&"|"&J92,sk,tblRevenueInput[项目代码]&"|"&tblRevenueInput[项目名称]&"|"&tblRevenueInput[分组作业名称]&"|"&tblRevenueInput[分组作业窗口名称]&"|"&tblRevenueInput[签订人],ok,tblRevenueOverride[项目代码]&"|"&tblRevenueOverride[项目名称]&"|"&tblRevenueOverride[分组作业名称]&"|"&tblRevenueOverride[分组作业窗口名称]&"|"&tblRevenueOverride[责任人],ov,IFERROR(XLOOKUP(k,ok,tblRevenueOverride[营业额覆盖],""),""),IF(ov<>"",ov,IFERROR(XLOOKUP(k,sk,tblRevenueInput[全额营业额合计],""),""))) | O92: 500000 | P92: 0.18 | Q92: =K92*P92 | S92: =Q92-R92 | T92: 0 | U92: =K92*T92 | W92: =U92-V92 | X92: 0.02 | Y92: =K92*X92 | AA92: =Y92-Z92 | AB92: 0 | AC92: =K92*AB92 | AE92: =AC92-AD92 | AF92: 0 | AG92: =K92*AF92 | AI92: =AG92-AH92 | AJ92: 0 | AK92: =K92*AJ92 | AM92: =AK92-AL92 | AN92: 0 | AO92: =K92*AN92 | AQ92: =AO92-AP92 | AR92: 0.04 | AS92: =K92*AR92 | AU92: =AS92-AT92 | AV92: 0.04 | AW92: =K92*AV92 | AY92: =AW92-AX92 | AZ92: 0 | BA92: =K92*AZ92 | BC92: =BA92-BB92 | BE92: =K92*BD92 | BG92: =BE92-BF92 | BI92: =K92*BH92 | BK92: =BI92-BJ92 | BL92: 按实 | BM92: =BN92 | BO92: =BM92-BN92 | BP92: =N92+Q92+U92+Y92+AC92+AG92+AK92+AO92+AS92+AW92+BA92+BE92+BI92+BM92 | BQ92: =N92+R92+V92+Z92+AD92+AH92+AL92+AP92+AT92+AX92+BB92+BF92+BJ92+BN92 | BR92: =BP92-BQ92 | BS92: / | BT92: / | BV92: 1、签订期间：2026.1.1-2026.8.1； 2、指标按照全年换算；
A93: 120 | B93: KQCY0120 | C93: 餐饮二分部 | D93: CF450 | E93: 天津大学学二食堂 | F93: 强责 | G93: 徐敏捷 | H93: / | I93: 基本伙窗口 | J93: 孟祥东 | K93: =LET(k,D93&"|"&E93&"|"&H93&"|"&I93&"|"&J93,sk,tblRevenueInput[项目代码]&"|"&tblRevenueInput[项目名称]&"|"&tblRevenueInput[分组作业名称]&"|"&tblRevenueInput[分组作业窗口名称]&"|"&tblRevenueInput[签订人],ok,tblRevenueOverride[项目代码]&"|"&tblRevenueOverride[项目名称]&"|"&tblRevenueOverride[分组作业名称]&"|"&tblRevenueOverride[分组作业窗口名称]&"|"&tblRevenueOverride[责任人],ov,IFERROR(XLOOKUP(k,ok,tblRevenueOverride[营业额覆盖],""),""),IF(ov<>"",ov,IFERROR(XLOOKUP(k,sk,tblRevenueInput[全额营业额合计],""),""))) | O93: 800000 | P93: 0.1 | Q93: =K93*P93 | S93: =Q93-R93 | T93: 0 | U93: =K93*T93 | W93: =U93-V93 | X93: 0.02 | Y93: =K93*X93 | AA93: =Y93-Z93 | AB93: 0 | AC93: =K93*AB93 | AE93: =AC93-AD93 | AF93: 0 | AG93: =K93*AF93 | AI93: =AG93-AH93 | AJ93: 0 | AK93: =K93*AJ93 | AM93: =AK93-AL93 | AN93: 0 | AO93: =K93*AN93 | AQ93: =AO93-AP93 | AR93: 0.04 | AS93: =K93*AR93 | AU93: =AS93-AT93 | AV93: 0.04 | AW93: =K93*AV93 | AY93: =AW93-AX93 | AZ93: 0 | BA93: =K93*AZ93 | BC93: =BA93-BB93 | BE93: =K93*BD93 | BG93: =BE93-BF93 | BI93: =K93*BH93 | BK93: =BI93-BJ93 | BL93: 按实 | BM93: =BN93 | BO93: =BM93-BN93 | BP93: =N93+Q93+U93+Y93+AC93+AG93+AK93+AO93+AS93+AW93+BA93+BE93+BI93+BM93 | BQ93: =N93+R93+V93+Z93+AD93+AH93+AL93+AP93+AT93+AX93+BB93+BF93+BJ93+BN93 | BR93: =BP93-BQ93 | BS93: / | BT93: / | BV93: 1、签订期间：2026.1.1-2026.8.1； 2、指标按照全年换算；
A94: 121 | B94: KQCY0121 | C94: 餐饮二分部 | D94: CF450 | E94: 天津大学学二食堂 | F94: 强责 | G94: 徐敏捷 | H94: / | I94: 小卖部 | J94: 张玉珠 | K94: =LET(k,D94&"|"&E94&"|"&H94&"|"&I94&"|"&J94,sk,tblRevenueInput[项目代码]&"|"&tblRevenueInput[项目名称]&"|"&tblRevenueInput[分组作业名称]&"|"&tblRevenueInput[分组作业窗口名称]&"|"&tblRevenueInput[签订人],ok,tblRevenueOverride[项目代码]&"|"&tblRevenueOverride[项目名称]&"|"&tblRevenueOverride[分组作业名称]&"|"&tblRevenueOverride[分组作业窗口名称]&"|"&tblRevenueOverride[责任人],ov,IFERROR(XLOOKUP(k,ok,tblRevenueOverride[营业额覆盖],""),""),IF(ov<>"",ov,IFERROR(XLOOKUP(k,sk,tblRevenueInput[全额营业额合计],""),""))) | O94: 240000 | P94: 0.02 | Q94: =K94*P94 | S94: =Q94-R94 | T94: 0 | U94: =K94*T94 | W94: =U94-V94 | X94: 0.02 | Y94: =K94*X94 | AA94: =Y94-Z94 | AB94: 0 | AC94: =K94*AB94 | AE94: =AC94-AD94 | AF94: 0 | AG94: =K94*AF94 | AI94: =AG94-AH94 | AJ94: 0 | AK94: =K94*AJ94 | AM94: =AK94-AL94 | AN94: 0 | AO94: =K94*AN94 | AQ94: =AO94-AP94 | AR94: 0.04 | AS94: =K94*AR94 | AU94: =AS94-AT94 | AV94: 0.01 | AW94: =K94*AV94 | AY94: =AW94-AX94 | AZ94: 0 | BA94: =K94*AZ94 | BC94: =BA94-BB94 | BE94: =K94*BD94 | BG94: =BE94-BF94 | BI94: =K94*BH94 | BK94: =BI94-BJ94 | BL94: 按实 | BM94: =BN94 | BO94: =BM94-BN94 | BP94: =N94+Q94+U94+Y94+AC94+AG94+AK94+AO94+AS94+AW94+BA94+BE94+BI94+BM94 | BQ94: =N94+R94+V94+Z94+AD94+AH94+AL94+AP94+AT94+AX94+BB94+BF94+BJ94+BN94 | BR94: =BP94-BQ94 | BS94: / | BT94: / | BV94: 1、签订期间：2026.1.1-2026.8.1； 2、指标按照全年换算；
A95: 122 | B95: KQCY0122 | C95: 餐饮二分部 | D95: CF450 | E95: 天津大学学二食堂 | F95: 强责 | G95: 徐敏捷 | H95: / | I95: 黄焖鸡 | J95: 蒋彩云 | K95: =LET(k,D95&"|"&E95&"|"&H95&"|"&I95&"|"&J95,sk,tblRevenueInput[项目代码]&"|"&tblRevenueInput[项目名称]&"|"&tblRevenueInput[分组作业名称]&"|"&tblRevenueInput[分组作业窗口名称]&"|"&tblRevenueInput[签订人],ok,tblRevenueOverride[项目代码]&"|"&tblRevenueOverride[项目名称]&"|"&tblRevenueOverride[分组作业名称]&"|"&tblRevenueOverride[分组作业窗口名称]&"|"&tblRevenueOverride[责任人],ov,IFERROR(XLOOKUP(k,ok,tblRevenueOverride[营业额覆盖],""),""),IF(ov<>"",ov,IFERROR(XLOOKUP(k,sk,tblRevenueInput[全额营业额合计],""),""))) | O95: 480000 | P95: 0.18 | Q95: =K95*P95 | S95: =Q95-R95 | T95: 0 | U95: =K95*T95 | W95: =U95-V95 | X95: 0.02 | Y95: =K95*X95 | AA95: =Y95-Z95 | AB95: 0 | AC95: =K95*AB95 | AE95: =AC95-AD95 | AF95: 0 | AG95: =K95*AF95 | AI95: =AG95-AH95 | AJ95: 0 | AK95: =K95*AJ95 | AM95: =AK95-AL95 | AN95: 0 | AO95: =K95*AN95 | AQ95: =AO95-AP95 | AR95: 0.04 | AS95: =K95*AR95 | AU95: =AS95-AT95 | AV95: 0.04 | AW95: =K95*AV95 | AY95: =AW95-AX95 | AZ95: 0 | BA95: =K95*AZ95 | BC95: =BA95-BB95 | BE95: =K95*BD95 | BG95: =BE95-BF95 | BI95: =K95*BH95 | BK95: =BI95-BJ95 | BL95: 按实 | BM95: =BN95 | BO95: =BM95-BN95 | BP95: =N95+Q95+U95+Y95+AC95+AG95+AK95+AO95+AS95+AW95+BA95+BE95+BI95+BM95 | BQ95: =N95+R95+V95+Z95+AD95+AH95+AL95+AP95+AT95+AX95+BB95+BF95+BJ95+BN95 | BR95: =BP95-BQ95 | BS95: / | BT95: / | BV95: 1、签订期间：2026.1.1-2026.8.1； 2、指标按照全年换算；
A96: 123 | B96: KQCY0123 | C96: 餐饮二分部 | D96: CF450 | E96: 天津大学学二食堂 | F96: 强责 | G96: 徐敏捷 | H96: / | I96: 南方面条 | J96: 孟祥东 | K96: =LET(k,D96&"|"&E96&"|"&H96&"|"&I96&"|"&J96,sk,tblRevenueInput[项目代码]&"|"&tblRevenueInput[项目名称]&"|"&tblRevenueInput[分组作业名称]&"|"&tblRevenueInput[分组作业窗口名称]&"|"&tblRevenueInput[签订人],ok,tblRevenueOverride[项目代码]&"|"&tblRevenueOverride[项目名称]&"|"&tblRevenueOverride[分组作业名称]&"|"&tblRevenueOverride[分组作业窗口名称]&"|"&tblRevenueOverride[责任人],ov,IFERROR(XLOOKUP(k,ok,tblRevenueOverride[营业额覆盖],""),""),IF(ov<>"",ov,IFERROR(XLOOKUP(k,sk,tblRevenueInput[全额营业额合计],""),""))) | O96: 240000 | P96: 0.18 | Q96: =K96*P96 | S96: =Q96-R96 | T96: 0 | U96: =K96*T96 | W96: =U96-V96 | X96: 0.02 | Y96: =K96*X96 | AA96: =Y96-Z96 | AB96: 0 | AC96: =K96*AB96 | AE96: =AC96-AD96 | AF96: 0 | AG96: =K96*AF96 | AI96: =AG96-AH96 | AJ96: 0 | AK96: =K96*AJ96 | AM96: =AK96-AL96 | AN96: 0 | AO96: =K96*AN96 | AQ96: =AO96-AP96 | AR96: 0.04 | AS96: =K96*AR96 | AU96: =AS96-AT96 | AV96: 0.04 | AW96: =K96*AV96 | AY96: =AW96-AX96 | AZ96: 0 | BA96: =K96*AZ96 | BC96: =BA96-BB96 | BE96: =K96*BD96 | BG96: =BE96-BF96 | BI96: =K96*BH96 | BK96: =BI96-BJ96 | BL96: 按实 | BM96: =BN96 | BO96: =BM96-BN96 | BP96: =N96+Q96+U96+Y96+AC96+AG96+AK96+AO96+AS96+AW96+BA96+BE96+BI96+BM96 | BQ96: =N96+R96+V96+Z96+AD96+AH96+AL96+AP96+AT96+AX96+BB96+BF96+BJ96+BN96 | BR96: =BP96-BQ96 | BS96: / | BT96: / | BV96: 1、签订期间：2026.1.1-2026.8.1； 2、指标按照全年换算；
A97: 124 | B97: KQCY0124 | C97: 餐饮二分部 | D97: CF450 | E97: 天津大学学二食堂 | F97: 强责 | G97: 徐敏捷 | H97: / | I97: 饸饹面 | J97: 要志远 | K97: =LET(k,D97&"|"&E97&"|"&H97&"|"&I97&"|"&J97,sk,tblRevenueInput[项目代码]&"|"&tblRevenueInput[项目名称]&"|"&tblRevenueInput[分组作业名称]&"|"&tblRevenueInput[分组作业窗口名称]&"|"&tblRevenueInput[签订人],ok,tblRevenueOverride[项目代码]&"|"&tblRevenueOverride[项目名称]&"|"&tblRevenueOverride[分组作业名称]&"|"&tblRevenueOverride[分组作业窗口名称]&"|"&tblRevenueOverride[责任人],ov,IFERROR(XLOOKUP(k,ok,tblRevenueOverride[营业额覆盖],""),""),IF(ov<>"",ov,IFERROR(XLOOKUP(k,sk,tblRevenueInput[全额营业额合计],""),""))) | O97: 220000 | P97: 0.18 | Q97: =K97*P97 | S97: =Q97-R97 | T97: 0 | U97: =K97*T97 | W97: =U97-V97 | X97: 0.02 | Y97: =K97*X97 | AA97: =Y97-Z97 | AB97: 0 | AC97: =K97*AB97 | AE97: =AC97-AD97 | AF97: 0 | AG97: =K97*AF97 | AI97: =AG97-AH97 | AJ97: 0 | AK97: =K97*AJ97 | AM97: =AK97-AL97 | AN97: 0 | AO97: =K97*AN97 | AQ97: =AO97-AP97 | AR97: 0.04 | AS97: =K97*AR97 | AU97: =AS97-AT97 | AV97: 0.04 | AW97: =K97*AV97 | AY97: =AW97-AX97 | AZ97: 0 | BA97: =K97*AZ97 | BC97: =BA97-BB97 | BE97: =K97*BD97 | BG97: =BE97-BF97 | BI97: =K97*BH97 | BK97: =BI97-BJ97 | BL97: 按实 | BM97: =BN97 | BO97: =BM97-BN97 | BP97: =N97+Q97+U97+Y97+AC97+AG97+AK97+AO97+AS97+AW97+BA97+BE97+BI97+BM97 | BQ97: =N97+R97+V97+Z97+AD97+AH97+AL97+AP97+AT97+AX97+BB97+BF97+BJ97+BN97 | BR97: =BP97-BQ97 | BS97: / | BT97: / | BV97: 1、签订期间：2026.1.1-2026.8.1； 2、指标按照全年换算；
A98: 125 | B98: KQCY0125 | C98: 餐饮二分部 | D98: CF450 | E98: 天津大学学二食堂 | F98: 强责 | G98: 徐敏捷 | H98: / | I98: 麻辣烫 | J98: 孟迪 | K98: =LET(k,D98&"|"&E98&"|"&H98&"|"&I98&"|"&J98,sk,tblRevenueInput[项目代码]&"|"&tblRevenueInput[项目名称]&"|"&tblRevenueInput[分组作业名称]&"|"&tblRevenueInput[分组作业窗口名称]&"|"&tblRevenueInput[签订人],ok,tblRevenueOverride[项目代码]&"|"&tblRevenueOverride[项目名称]&"|"&tblRevenueOverride[分组作业名称]&"|"&tblRevenueOverride[分组作业窗口名称]&"|"&tblRevenueOverride[责任人],ov,IFERROR(XLOOKUP(k,ok,tblRevenueOverride[营业额覆盖],""),""),IF(ov<>"",ov,IFERROR(XLOOKUP(k,sk,tblRevenueInput[全额营业额合计],""),""))) | O98: 300000 | P98: 0.18 | Q98: =K98*P98 | S98: =Q98-R98 | T98: 0 | U98: =K98*T98 | W98: =U98-V98 | X98: 0.02 | Y98: =K98*X98 | AA98: =Y98-Z98 | AB98: 0 | AC98: =K98*AB98 | AE98: =AC98-AD98 | AF98: 0 | AG98: =K98*AF98 | AI98: =AG98-AH98 | AJ98: 0 | AK98: =K98*AJ98 | AM98: =AK98-AL98 | AN98: 0 | AO98: =K98*AN98 | AQ98: =AO98-AP98 | AR98: 0.04 | AS98: =K98*AR98 | AU98: =AS98-AT98 | AV98: 0.04 | AW98: =K98*AV98 | AY98: =AW98-AX98 | AZ98: 0 | BA98: =K98*AZ98 | BC98: =BA98-BB98 | BE98: =K98*BD98 | BG98: =BE98-BF98 | BI98: =K98*BH98 | BK98: =BI98-BJ98 | BL98: 按实 | BM98: =BN98 | BO98: =BM98-BN98 | BP98: =N98+Q98+U98+Y98+AC98+AG98+AK98+AO98+AS98+AW98+BA98+BE98+BI98+BM98 | BQ98: =N98+R98+V98+Z98+AD98+AH98+AL98+AP98+AT98+AX98+BB98+BF98+BJ98+BN98 | BR98: =BP98-BQ98 | BS98: / | BT98: / | BV98: 1、签订期间：2026.1.1-2026.8.1； 2、指标按照全年换算；
A99: 126 | B99: KQCY0126 | C99: 餐饮二分部 | D99: CF450 | E99: 天津大学学二食堂 | F99: 强责 | G99: 徐敏捷 | H99: / | I99: 烤鸭饭 | J99: 董子帅 | K99: =LET(k,D99&"|"&E99&"|"&H99&"|"&I99&"|"&J99,sk,tblRevenueInput[项目代码]&"|"&tblRevenueInput[项目名称]&"|"&tblRevenueInput[分组作业名称]&"|"&tblRevenueInput[分组作业窗口名称]&"|"&tblRevenueInput[签订人],ok,tblRevenueOverride[项目代码]&"|"&tblRevenueOverride[项目名称]&"|"&tblRevenueOverride[分组作业名称]&"|"&tblRevenueOverride[分组作业窗口名称]&"|"&tblRevenueOverride[责任人],ov,IFERROR(XLOOKUP(k,ok,tblRevenueOverride[营业额覆盖],""),""),IF(ov<>"",ov,IFERROR(XLOOKUP(k,sk,tblRevenueInput[全额营业额合计],""),""))) | O99: 400000 | P99: 0.18 | Q99: =K99*P99 | S99: =Q99-R99 | T99: 0 | U99: =K99*T99 | W99: =U99-V99 | X99: 0.02 | Y99: =K99*X99 | AA99: =Y99-Z99 | AB99: 0 | AC99: =K99*AB99 | AE99: =AC99-AD99 | AF99: 0 | AG99: =K99*AF99 | AI99: =AG99-AH99 | AJ99: 0 | AK99: =K99*AJ99 | AM99: =AK99-AL99 | AN99: 0 | AO99: =K99*AN99 | AQ99: =AO99-AP99 | AR99: 0.04 | AS99: =K99*AR99 | AU99: =AS99-AT99 | AV99: 0.04 | AW99: =K99*AV99 | AY99: =AW99-AX99 | AZ99: 0 | BA99: =K99*AZ99 | BC99: =BA99-BB99 | BE99: =K99*BD99 | BG99: =BE99-BF99 | BI99: =K99*BH99 | BK99: =BI99-BJ99 | BL99: 按实 | BM99: =BN99 | BO99: =BM99-BN99 | BP99: =N99+Q99+U99+Y99+AC99+AG99+AK99+AO99+AS99+AW99+BA99+BE99+BI99+BM99 | BQ99: =N99+R99+V99+Z99+AD99+AH99+AL99+AP99+AT99+AX99+BB99+BF99+BJ99+BN99 | BR99: =BP99-BQ99 | BS99: / | BT99: / | BV99: 1、签订期间：2026.1.1-2026.8.1； 2、指标按照全年换算；
A100: 127 | B100: KQCY0127 | C100: 餐饮二分部 | D100: CF450 | E100: 天津大学学二食堂 | F100: 强责 | G100: 徐敏捷 | H100: / | I100: 真有面 | J100: 尹细老 | K100: =LET(k,D100&"|"&E100&"|"&H100&"|"&I100&"|"&J100,sk,tblRevenueInput[项目代码]&"|"&tblRevenueInput[项目名称]&"|"&tblRevenueInput[分组作业名称]&"|"&tblRevenueInput[分组作业窗口名称]&"|"&tblRevenueInput[签订人],ok,tblRevenueOverride[项目代码]&"|"&tblRevenueOverride[项目名称]&"|"&tblRevenueOverride[分组作业名称]&"|"&tblRevenueOverride[分组作业窗口名称]&"|"&tblRevenueOverride[责任人],ov,IFERROR(XLOOKUP(k,ok,tblRevenueOverride[营业额覆盖],""),""),IF(ov<>"",ov,IFERROR(XLOOKUP(k,sk,tblRevenueInput[全额营业额合计],""),""))) | O100: 300000 | P100: 0.18 | Q100: =K100*P100 | S100: =Q100-R100 | T100: 0 | U100: =K100*T100 | W100: =U100-V100 | X100: 0.02 | Y100: =K100*X100 | AA100: =Y100-Z100 | AB100: 0 | AC100: =K100*AB100 | AE100: =AC100-AD100 | AF100: 0 | AG100: =K100*AF100 | AI100: =AG100-AH100 | AJ100: 0 | AK100: =K100*AJ100 | AM100: =AK100-AL100 | AN100: 0 | AO100: =K100*AN100 | AQ100: =AO100-AP100 | AR100: 0.04 | AS100: =K100*AR100 | AU100: =AS100-AT100 | AV100: 0.04 | AW100: =K100*AV100 | AY100: =AW100-AX100 | AZ100: 0 | BA100: =K100*AZ100 | BC100: =BA100-BB100 | BE100: =K100*BD100 | BG100: =BE100-BF100 | BI100: =K100*BH100 | BK100: =BI100-BJ100 | BL100: 按实 | BM100: =BN100 | BO100: =BM100-BN100 | BP100: =N100+Q100+U100+Y100+AC100+AG100+AK100+AO100+AS100+AW100+BA100+BE100+BI100+BM100 | BQ100: =N100+R100+V100+Z100+AD100+AH100+AL100+AP100+AT100+AX100+BB100+BF100+BJ100+BN100 | BR100: =BP100-BQ100 | BS100: / | BT100: / | BV100: 1、签订期间：2026.1.1-2026.8.1； 2、指标按照全年换算；
...

Sheet 营业额数据源
A1: 营业额数据源（每月覆盖粘贴 A:M 数据区）
A2: 数据行从第 4 行开始；目标输出以项目代码、项目名称、班组、窗口、责任人五项进行精确匹配。
A3: 序号 | B3: 档口唯一标志 | C3: 分部名称 | D3: 项目代码 | E3: 项目名称 | F3: 项目类型 | G3: 分组作业名称 | H3: 分组作业窗口名称 | I3: 签订人 | J3: 全额营业额合计 | K3: 备注状态 | L3: 收入会计 | M3: 补充说明
A4: 1 | B4: KQCY0001 | C4: 餐饮一分部 | D4: CF139 | E4: 苏州中科新药篮餐厅 | F4: 自营 | G4: 自营 | H4: / | I4: / | J4: 201107.98 | L4: 谢苗苗 | M4: 已核对
A5: 2 | B5: KQCY0002 | C5: 餐饮一分部 | D5: CF481 | E5: 常熟世华高级中学食堂 | F5: 自营 | G5: 自营 | H5: / | I5: 杨志军 | J5: 66255.63 | L5: 谢苗苗 | M5: 已核对
A6: 3 | B6: KQCY0003 | C6: 餐饮一分部 | D6: CF478 | E6: 苏州华杨电子餐厅 | F6: 强责 | G6: / | H6: / | I6: 武良军 | J6: 170171.4 | L6: 谢苗苗 | M6: 已核对
A7: 4 | B7: KQCY0004 | C7: 餐饮一分部 | D7: CF751 | E7: 国防科大（长沙）食堂 | F7: 人员服务外包 | G7: / | H7: / | I7: / | J7: 621582.5 | L7: 位军浩
A8: 5 | B8: KQCY0005 | C8: 餐饮一分部 | D8: CF474 | E8: 安工大七食堂 | F8: 强责 | G8: / | H8: / | I8: 李俊彦 | J8: 29505.2 | L8: 位军浩
A9: 6 | B9: KQCY0006 | C9: 餐饮一分部 | D9: CF474 | E9: 安工大七食堂 | F9: 强责 | G9: 第一班组 | H9: 手工馄饨（大陷水饺、刀削面/汆肉米线） | I9: 潘海英 | J9: 0 | K9: 已退场 | L9: 位军浩
A10: 7 | B10: KQCY0007 | C10: 餐饮一分部 | D10: CF474 | E10: 安工大七食堂 | F10: 强责 | G10: 第二班组 | H10: 黄焖系列（酸菜肉煲系列、椒麻鸡系列、酸菜鱼系列） | I10: 胡科才 | J10: 1807.5 | L10: 位军浩
A11: 8 | B11: KQCY0008 | C11: 餐饮一分部 | D11: CF474 | E11: 安工大七食堂 | F11: 强责 | G11: 第三班组 | H11: 猪脚饭系列（套饭系列、菜饭骨头汤系列） | I11: 杨克顺 | J11: 2179.5 | L11: 位军浩
A12: 9 | B12: KQCY0009 | C12: 餐饮一分部 | D12: CF474 | E12: 安工大七食堂 | F12: 强责 | G12: 第四班组 | H12: 拌饭系列（肉夹馍、紫菜包饭） | I12: 魏祖华 | J12: 0 | K12: 已退场 | L12: 位军浩
A13: 10 | B13: KQCY0010 | C13: 餐饮一分部 | D13: CF477 | E13: 上海民航第一食堂 | F13: 自营 | G13: 自营 | H13: / | I13: / | J13: 0 | L13: 谢苗苗 | M13: 已核对
A14: 11 | B14: KQCY0011 | C14: 餐饮一分部 | D14: CF477 | E14: 上海民航第一食堂 | F14: 分组作业 | G14: 第二班组 | H14: 山东煎饼 | I14: 姚群 | J14: 0 | L14: 谢苗苗 | M14: 已核对
A15: 12 | B15: KQCY0012 | C15: 餐饮一分部 | D15: CF477 | E15: 上海民航第一食堂 | F15: 分组作业 | G15: 第六班组 | H15: 蜜雪冰城 | I15: 任黎明 | J15: 0 | L15: 谢苗苗 | M15: 已核对
A16: 13 | B16: KQCY0013 | C16: 餐饮一分部 | D16: CF477 | E16: 上海民航第一食堂 | F16: 分组作业 | G16: 第三班组 | H16: 糖水粥铺 | I16: 孙青青 | J16: 0 | L16: 谢苗苗 | M16: 已核对
A17: 14 | B17: KQCY0014 | C17: 餐饮一分部 | D17: CF477 | E17: 上海民航第一食堂 | F17: 分组作业 | G17: 第四班组 | H17: 大碗面 | I17: 景帅帅 | J17: 0 | L17: 谢苗苗 | M17: 已核对
A18: 15 | B18: KQCY0015 | C18: 餐饮一分部 | D18: CF477 | E18: 上海民航第一食堂 | F18: 分组作业 | G18: 第一班组 | H18: 早餐 | I18: 芦磊 | J18: 0 | L18: 谢苗苗 | M18: 已核对
A19: 16 | B19: KQCY0016 | C19: 餐饮一分部 | D19: CF272 | E19: 苏州工学院南一食堂 | F19: 强责 | G19: / | H19: / | I19: / | L19: 位军浩
A20: 17 | B20: KQCY0017 | C20: 餐饮一分部 | D20: CF272 | E20: 苏州工学院南一食堂 | F20: 强责 | G20: / | H20: 饼铺 | I20: 纪洪强 | J20: 0 | L20: 位军浩
A21: 18 | B21: KQCY0018 | C21: 餐饮一分部 | D21: CF272 | E21: 苏州工学院南一食堂 | F21: 强责 | G21: / | H21: 粥铺 | I21: 贺明 | J21: 0 | L21: 位军浩
A22: 19 | B22: KQCY0019 | C22: 餐饮一分部 | D22: CF272 | E22: 苏州工学院南一食堂 | F22: 强责 | G22: / | H22: 老乡邨 | I22: 刘少军 | J22: 0 | L22: 位军浩
A23: 20 | B23: KQCY0020 | C23: 餐饮一分部 | D23: CF272 | E23: 苏州工学院南一食堂 | F23: 强责 | G23: / | H23: 科桥小厨 | I23: 吴浩 | J23: 0 | L23: 位军浩
A24: 21 | B24: KQCY0021 | C24: 餐饮一分部 | D24: CF272 | E24: 苏州工学院南一食堂 | F24: 强责 | G24: / | H24: 清汤米线 | I24: 张郁磊 | K24: 已撤场 | L24: 位军浩
A25: 22 | B25: KQCY0022 | C25: 餐饮一分部 | D25: CF272 | E25: 苏州工学院南一食堂 | F25: 强责 | G25: / | H25: 黑鸭堡 | I25: 张郁磊 | J25: 0 | L25: 位军浩
A26: 23 | B26: KQCY0023 | C26: 餐饮一分部 | D26: CF272 | E26: 苏州工学院南一食堂 | F26: 强责 | G26: / | H26: 7分甜 | I26: 纪洪强 | J26: 0 | L26: 位军浩
A27: 24 | B27: KQCY0024 | C27: 餐饮一分部 | D27: CF272 | E27: 苏州工学院南一食堂 | F27: 强责 | G27: / | H27: 药膳鸡 | I27: 匡正娟 | J27: 0 | L27: 位军浩
A28: 25 | B28: KQCY0025 | C28: 餐饮一分部 | D28: CF272 | E28: 苏州工学院南一食堂 | F28: 强责 | G28: / | H28: 麻辣香锅 | I28: 纪洪强 | J28: 0 | L28: 位军浩
A29: 26 | B29: KQCY0026 | C29: 餐饮一分部 | D29: CF272 | E29: 苏州工学院南一食堂 | F29: 强责 | G29: / | H29: 生煎牛肉汤 | I29: 徐雪晗 | J29: 0 | L29: 位军浩
A30: 27 | B30: KQCY0027 | C30: 餐饮一分部 | D30: CF272 | E30: 苏州工学院南一食堂 | F30: 强责 | G30: / | H30: 西式简餐 | I30: 李明发 | J30: 0 | L30: 位军浩
A31: 28 | B31: KQCY0028 | C31: 餐饮一分部 | D31: CF272 | E31: 苏州工学院南一食堂 | F31: 强责 | G31: / | H31: 苏式面 | I31: 许正芳 | J31: 0 | L31: 位军浩
A32: 29 | B32: KQCY0029 | C32: 餐饮一分部 | D32: CF272 | E32: 苏州工学院南一食堂 | F32: 强责 | G32: / | H32: 王记炒饭 | I32: 王梓骏 | J32: 0 | L32: 位军浩
A33: 30 | B33: KQCY0030 | C33: 餐饮一分部 | D33: CF272 | E33: 苏州工学院南一食堂 | F33: 强责 | G33: / | H33: 烤鸭 | I33: 王鑫 | J33: 0 | L33: 位军浩
A34: 31 | B34: KQCY0031 | C34: 餐饮一分部 | D34: CF272 | E34: 苏州工学院南一食堂 | F34: 强责 | G34: / | H34: 小街胡同牛杂面 | I34: 黄雨 | J34: 0 | L34: 位军浩
A35: 32 | B35: KQCY0032 | C35: 餐饮一分部 | D35: CF272 | E35: 苏州工学院南一食堂 | F35: 强责 | G35: / | H35: 汉堡炸鸡 | I35: 陆林峰 | K35: 已撤场 | L35: 位军浩
A36: 33 | B36: KQCY0033 | C36: 餐饮一分部 | D36: CF272 | E36: 苏州工学院南一食堂 | F36: 强责 | G36: / | H36: 旋转小火锅 | I36: 潘祥 | K36: 已撤场 | L36: 位军浩
A37: 34 | B37: KQCY0034 | C37: 餐饮一分部 | D37: CF127-1 | E37: 泰科老厂餐厅 | F37: 自营 | G37: 自营 | H37: / | I37: / | J37: 1482243.8 | K37: 预估 | L37: 位军浩
A38: 35 | B38: KQCY0035 | C38: 餐饮一分部 | D38: CF127-3 | E38: 泰科新厂餐厅 | F38: 自营 | G38: 自营 | H38: / | I38: / | J38: 1891615.1 | K38: 预估 | L38: 位军浩
A39: 36 | B39: KQCY0036 | C39: 餐饮一分部 | D39: CF141 | E39: 泰科阳澄湖工厂 | F39: 自营 | G39: 自营 | H39: / | I39: / | J39: 817926.85 | K39: 预估 | L39: 位军浩
A40: 37 | B40: KQCY0037 | C40: 餐饮一分部 | D40: CF129-1 | E40: 中央厨房（加工服务部） | F40: 自营 | G40: 自营 | H40: / | I40: / | K40: 不存在收入 | L40: 位军浩
A41: 38 | B41: KQCY0038 | C41: 餐饮一分部 | D41: CF142 | E41: 卡特彼勒（吴江）餐厅 | F41: 自营 | G41: 自营 | H41: / | I41: / | K41: 已退场 | L41: 位军浩
A42: 39 | B42: KQCY0039 | C42: 餐饮一分部 | D42: CF138 | E42: 苏州生物产业园三期餐厅 | F42: 自营 | G42: 自营 | H42: / | I42: / | J42: 212081.83 | K42: 准确金额下午两点核算出，现为预估金额 | L42: 位军浩
A43: 40 | B43: KQCY0040 | C43: 餐饮二分部 | D43: CF181 | E43: 中科大苏州研究院食堂 | F43: 自营 | G43: 自营 | H43: / | I43: / | J43: 135117.53 | L43: 谢苗苗 | M43: 已核对
A44: 41 | B44: KQCY0041 | C44: 餐饮二分部 | D44: CF124 | E44: 苏州评弹学院食堂 | F44: 自营 | G44: 自营 | H44: / | I44: / | J44: 0 | K44: 暑期放假 | L44: 谢苗苗 | M44: 已核对
A45: 42 | B45: KQCY0042 | C45: 餐饮二分部 | D45: CF125 | E45: 西浦大学宏愿食堂（南） | F45: 自营 | G45: 自营 | H45: / | I45: / | J45: 130412.6 | L45: 谢苗苗 | M45: 已核对
A46: 43 | B46: KQCY0043 | C46: 餐饮二分部 | D46: CF125 | E46: 西浦大学宏愿食堂（南） | F46: 分组作业 | G46: / | H46: 麻辣烫 | I46: 何军军 | J46: 0 | L46: 谢苗苗 | M46: 已核对
A47: 44 | B47: KQCY0044 | C47: 餐饮二分部 | D47: CF125 | E47: 西浦大学宏愿食堂（南） | F47: 分组作业 | G47: / | H47: 小炒 | I47: 王成龙 | J47: 32020.6 | L47: 谢苗苗 | M47: 已核对
A48: 45 | B48: KQCY0045 | C48: 餐饮二分部 | D48: CF125 | E48: 西浦大学宏愿食堂（南） | F48: 分组作业 | G48: / | H48: 枣糕 | I48: 杜松松 | J48: 2181 | L48: 谢苗苗 | M48: 已核对
A49: 46 | B49: KQCY0046 | C49: 餐饮二分部 | D49: CF125 | E49: 西浦大学宏愿食堂（南） | F49: 分组作业 | G49: / | H49: 面条 | I49: 葛文静 | J49: 0 | K49: 已撤场 | L49: 谢苗苗 | M49: 已核对
A50: 47 | B50: KQCY0047 | C50: 餐饮二分部 | D50: CF125 | E50: 西浦大学宏愿食堂（南） | F50: 分组作业 | G50: / | H50: 烤肉 | I50: 杜松松 | J50: 0 | K50: 已撤场 | L50: 谢苗苗 | M50: 已核对
A51: 48 | B51: KQCY0048 | C51: 餐饮二分部 | D51: CF125 | E51: 西浦大学宏愿食堂（南） | F51: 分组作业 | G51: / | H51: 粉丝汤 | I51: 李鑫 | J51: 7077.97 | L51: 谢苗苗 | M51: 已核对
A52: 49 | B52: KQCY0049 | C52: 餐饮二分部 | D52: CF137 | E52: 西浦大学宏愿食堂（北） | F52: 自营 | G52: 自营 | H52: / | I52: / | J52: 0 | K52: 系统出错31号卡机收入无法查询，未加金额 | L52: 谢苗苗 | M52: 已核对
A53: 50 | B53: KQCY0050 | C53: 餐饮二分部 | D53: CF137 | E53: 西浦大学宏愿食堂（北） | F53: 分组作业 | G53: / | H53: 滑蛋饭 | I53: 赵广伟 | J53: 0 | K53: 未营业 | L53: 谢苗苗 | M53: 已核对
A54: 51 | B54: KQCY0051 | C54: 餐饮二分部 | D54: CF137 | E54: 西浦大学宏愿食堂（北） | F54: 分组作业 | G54: / | H54: 手工水饺 | I54: 赵玉才 | J54: 0 | K54: 系统出错31号卡机收入无法查询，未加金额 | L54: 谢苗苗 | M54: 已核对
A55: 52 | B55: KQCY0052 | C55: 餐饮二分部 | D55: CF137 | E55: 西浦大学宏愿食堂（北） | F55: 分组作业 | G55: / | H55: 烤盘饭 | I55: 付昌杰 | J55: 0 | K55: 系统出错31号卡机收入无法查询，未加金额 | L55: 谢苗苗 | M55: 已核对
A56: 53 | B56: KQCY0053 | C56: 餐饮二分部 | D56: CF137 | E56: 西浦大学宏愿食堂（北） | F56: 分组作业 | G56: / | H56: 大花米线 | I56: 钱卫军 | J56: 0 | K56: 系统出错31号卡机收入无法查询，未加金额 | L56: 谢苗苗 | M56: 已核对
A57: 54 | B57: KQCY0054 | C57: 餐饮二分部 | D57: CF137 | E57: 西浦大学宏愿食堂（北） | F57: 分组作业 | G57: / | H57: 石锅饭 | I57: 葛颖 | J57: 0 | K57: 系统出错31号卡机收入无法查询，未加金额 | L57: 谢苗苗 | M57: 已核对
A58: 55 | B58: KQCY0055 | C58: 餐饮二分部 | D58: CF137 | E58: 西浦大学宏愿食堂（北） | F58: 分组作业 | G58: / | H58: 一鸣鲜奶吧 | I58: 黎欢 | J58: 0 | K58: 系统出错31号卡机收入无法查询，未加金额 | L58: 谢苗苗 | M58: 已核对
A59: 56 | B59: KQCY0056 | C59: 餐饮二分部 | D59: CF140 | E59: 西浦大学太仓校区食堂 | F59: 自营 | G59: 自营 | H59: / | I59: / | J59: 134752.83 | L59: 谢苗苗 | M59: 已核对
A60: 57 | B60: KQCY0057 | C60: 餐饮二分部 | D60: CF140 | E60: 西浦大学太仓校区食堂 | F60: 分组作业 | G60: 第一班组 | H60: 蛋包饭(肥牛米线、水饺、烤盘饭) | I60: 赵广伟 | J60: 66066.8 | L60: 谢苗苗 | M60: 已核对
A61: 58 | B61: KQCY0058 | C61: 餐饮二分部 | D61: CF140 | E61: 西浦大学太仓校区食堂 | F61: 分组作业 | G61: 第二班组 | H61: 枣糕&热饮(韩式拌饭) | I61: 杜松松 | J61: 0 | K61: 已撤场 | L61: 谢苗苗 | M61: 已核对
A62: 59 | B62: KQCY0059 | C62: 餐饮二分部 | D62: CF182 | E62: 无锡工艺第二食堂 | F62: 自营 | G62: 自营 | H62: / | I62: / | J62: 0 | L62: 谢苗苗 | M62: 已核对
A63: 60 | B63: KQCY0060 | C63: 餐饮二分部 | D63: CF182 | E63: 无锡工艺第二食堂 | F63: 分组作业 | G63: / | H63: 快餐 | I63: 林见锋 | J63: 0 | L63: 谢苗苗 | M63: 已核对
A64: 61 | B64: KQCY0061 | C64: 餐饮二分部 | D64: CF182 | E64: 无锡工艺第二食堂 | F64: 分组作业 | G64: 第二班组 | H64: 烤鸭饭 | I64: 徐其国 | J64: 0 | L64: 谢苗苗 | M64: 已核对
A65: 62 | B65: KQCY0062 | C65: 餐饮二分部 | D65: CF182 | E65: 无锡工艺第二食堂 | F65: 分组作业 | G65: 第三班组 | H65: 营养粥、小笼包 | J65: 0 | L65: 谢苗苗 | M65: 已核对
A66: 63 | B66: KQCY0063 | C66: 餐饮二分部 | D66: CF182 | E66: 无锡工艺第二食堂 | F66: 分组作业 | G66: 第四班组 | H66: 武汉热干面、隆江猪脚饭 | I66: 田振 | J66: 0 | L66: 谢苗苗 | M66: 已核对
A67: 64 | B67: KQCY0064 | C67: 餐饮二分部 | D67: CF182 | E67: 无锡工艺第二食堂 | F67: 分组作业 | G67: 第六班组 | H67: 称重水饺、馄饨 | I67: 张宜轩 | J67: 0 | L67: 谢苗苗 | M67: 已核对
A68: 65 | B68: KQCY0065 | C68: 餐饮二分部 | D68: CF182 | E68: 无锡工艺第二食堂 | F68: 分组作业 | G68: 第七班组 | H68: 掉渣饼、徐州米线、鸡汤饭 | I68: 武玉柳 | J68: 0 | L68: 谢苗苗 | M68: 已核对
A69: 66 | B69: KQCY0066 | C69: 餐饮二分部 | D69: CF182 | E69: 无锡工艺第二食堂 | F69: 分组作业 | G69: 第八班组 | H69: 爆炒盖浇饭、套餐饭 | I69: 赵裕旭 | J69: 0 | L69: 谢苗苗 | M69: 已核对
A70: 67 | B70: KQCY0067 | C70: 餐饮二分部 | D70: CF182 | E70: 无锡工艺第二食堂 | F70: 分组作业 | G70: 第九班组 | H70: 休闲水吧、水果 | I70: 党玉真 | J70: 0 | L70: 谢苗苗 | M70: 已核对
A71: 68 | B71: KQCY0068 | C71: 餐饮二分部 | D71: CF182 | E71: 无锡工艺第二食堂 | F71: 分组作业 | G71: 第十一班组 | H71: （二楼特色小吃）汉堡、炸鸡、自主称重快餐、千里香馄饨、手擀面 | J71: 0 | L71: 谢苗苗 | M71: 已核对
A72: 69 | B72: KQCY0069 | C72: 餐饮二分部 | D72: CF360 | E72: 南通师专新校区食堂 | F72: 自营 | G72: 自营 | H72: 快餐 | J72: 0 | L72: 位军浩
A73: 70 | B73: KQCY0070 | C73: 餐饮二分部 | D73: CF360 | E73: 南通师专新校区食堂 | F73: 分组作业 | G73: 第一班组 | H73: 琳榆炸鸡腿 | I73: 王友强 | J73: 0 | K73: 已撤场 | L73: 位军浩
A74: 71 | B74: KQCY0071 | C74: 餐饮二分部 | D74: CF360 | E74: 南通师专新校区食堂 | F74: 分组作业 | G74: 第二班组 | H74: 中式早点 | I74: 何小杏 | J74: 0 | L74: 位军浩
A75: 72 | B75: KQCY0072 | C75: 餐饮二分部 | D75: CF360 | E75: 南通师专新校区食堂 | F75: 分组作业 | G75: 第三班组 | H75: 土耳其烤肉饭 | I75: 薛小勇 | J75: 0 | K75: 已撤场 | L75: 位军浩
A76: 73 | B76: KQCY0073 | C76: 餐饮二分部 | D76: CF360 | E76: 南通师专新校区食堂 | F76: 分组作业 | G76: 第四班组 | H76: 营养粥小笼包 | I76: 沈玲 | J76: 0 | L76: 位军浩
A77: 74 | B77: KQCY0074 | C77: 餐饮二分部 | D77: CF360 | E77: 南通师专新校区食堂 | F77: 分组作业 | G77: 第五班组 | H77: 生烫牛肉米线 | I77: 刘海霞 | J77: 0 | L77: 位军浩
A78: 75 | B78: KQCY0075 | C78: 餐饮二分部 | D78: CF360 | E78: 南通师专新校区食堂 | F78: 分组作业 | G78: 第六班组 | H78: 咖喱蛋包饭 | I78: 余娇 | J78: 0 | K78: 已撤场 | L78: 位军浩
A79: 76 | B79: KQCY0076 | C79: 餐饮二分部 | D79: CF360 | E79: 南通师专新校区食堂 | F79: 分组作业 | G79: 第七班组 | H79: 麻辣烫麻辣拌 | I79: 虞冬梅 | J79: 0 | L79: 位军浩
A80: 77 | B80: KQCY0077 | C80: 餐饮二分部 | D80: CF360 | E80: 南通师专新校区食堂 | F80: 分组作业 | G80: 第八班组 | H80: 真老大手工云吞 | I80: 彭晴 | J80: 0 | L80: 位军浩
A81: 78 | B81: KQCY0078 | C81: 餐饮二分部 | D81: CF360 | E81: 南通师专新校区食堂 | F81: 分组作业 | G81: 第九班组 | H81: 朱家小馆羊杂面 | I81: 薛桂中 | J81: 0 | L81: 位军浩
A82: 79 | B82: KQCY0079 | C82: 餐饮二分部 | D82: CF360 | E82: 南通师专新校区食堂 | F82: 分组作业 | G82: 第十班组 | H82: 奶茶 | I82: 王艳 | J82: 0 | L82: 位军浩
A83: 80 | B83: KQCY0080 | C83: 餐饮二分部 | D83: CF364 | E83: 江苏航运思本轩食堂 | F83: 自营 | G83: 自营 | H83: / | I83: / | J83: 42101.43 | L83: 位军浩
A84: 82 | B84: KQCY0082 | C84: 餐饮二分部 | D84: CF364 | E84: 江苏航运思本轩食堂 | F84: 分组作业 | G84: 第二班组 | H84: 粉丝汤（牛肉、老母鸡、牛杂、拆骨） | I84: 满超 | J84: 7010.6 | L84: 位军浩
A85: 83 | B85: KQCY0083 | C85: 餐饮二分部 | D85: CF364 | E85: 江苏航运思本轩食堂 | F85: 分组作业 | G85: 第三班组 | H85: 拌饭（鸡腿饭、酸梅鸭饭） | I85: 唐德生 | J85: 11700.09 | L85: 位军浩
A86: 84 | B86: KQCY0084 | C86: 餐饮二分部 | D86: CF364 | E86: 江苏航运思本轩食堂 | F86: 分组作业 | G86: 第五班组 | H86: 早餐 | I86: 潘捷 | J86: 0 | K86: 撤场 | L86: 位军浩
A87: 86 | B87: KQCY0086 | C87: 餐饮二分部 | D87: CF364 | E87: 江苏航运思本轩食堂 | F87: 分组作业 | G87: 第七班组 | H87: 锡纸饭 | I87: 陈芳 | J87: 3129.47 | L87: 位军浩
A88: 89 | B88: KQCY0089 | C88: 餐饮二分部 | D88: CF364 | E88: 江苏航运思本轩食堂 | F88: 分组作业 | G88: 第十班组 | H88: 烤鸭饭 | I88: 蒋继承 | J88: 10513.32 | L88: 位军浩
A89: 90 | B89: KQCY0090 | C89: 餐饮二分部 | D89: CF364 | E89: 江苏航运思本轩食堂 | F89: 分组作业 | G89: 第十一班组 | H89: 朱家小馆 | I89: 张慧南 | J89: 9466.25 | L89: 位军浩
A90: 94 | B90: KQCY0094 | C90: 餐饮二分部 | D90: CF363 | E90: 南通大学启东校区 | F90: 自营 | G90: 自营 | H90: / | I90: / | J90: 0 | L90: 位军浩
A91: 95 | B91: KQCY0095 | C91: 餐饮二分部 | D91: CF363 | E91: 南通大学启东校区 | F91: 分组作业 | G91: 第一班组 | H91: 基本大伙 | I91: 朱寿凤 | J91: 0 | L91: 位军浩
A92: 96 | B92: KQCY0096 | C92: 餐饮二分部 | D92: CF363 | E92: 南通大学启东校区 | F92: 分组作业 | G92: 第二班组 | H92: 自选称重 | I92: 朱寿凤 | J92: 0 | L92: 位军浩
A93: 97 | B93: KQCY0097 | C93: 餐饮二分部 | D93: CF363 | E93: 南通大学启东校区 | F93: 分组作业 | G93: 第三班组 | H93: 中式早点 | I93: 王正明 | J93: 0 | L93: 位军浩
A94: 98 | B94: KQCY0098 | C94: 餐饮二分部 | D94: CF363 | E94: 南通大学启东校区 | F94: 分组作业 | G94: 第四班组 | H94: 黄焖鸡酸菜鱼 | I94: 金健华 | J94: 0 | L94: 位军浩
A95: 99 | B95: KQCY0099 | C95: 餐饮二分部 | D95: CF363 | E95: 南通大学启东校区 | F95: 分组作业 | G95: 第五班组 | H95: 卤肉饭套餐 | I95: 金健华 | J95: 0 | L95: 位军浩
A96: 100 | B96: KQCY0100 | C96: 餐饮二分部 | D96: CF363 | E96: 南通大学启东校区 | F96: 分组作业 | G96: 第六班组 | H96: 营养粥杂粮煎饼 | I96: 邵国才 | J96: 0 | L96: 位军浩
A97: 101 | B97: KQCY0101 | C97: 餐饮二分部 | D97: CF363 | E97: 南通大学启东校区 | F97: 分组作业 | G97: 第七班组 | H97: 面条馄饨 | I97: 邵国才 | J97: 0 | L97: 位军浩
A98: 102 | B98: KQCY0102 | C98: 餐饮二分部 | D98: CF363 | E98: 南通大学启东校区 | F98: 分组作业 | G98: 第八班组 | H98: 米线汤包 | I98: 王友强 | J98: 0 | L98: 位军浩
... A102: 106 | B102: KQCY0106 | C102: 餐饮二分部 | D102: CF363 | E102: 南通大学启东校区 | F102: 分组作业 | G102: 第十二班组 | H102: 铁板炒饭 | I102: 王志河 | J102: 0 | L102: 位军浩
B103: KQCY0107 | C103: 餐饮二分部 | D103: CF160 | E103: 高新区实验高中食堂(金山路校区) | F103: 人员服务外包 | G103: / | H103: / | I103: / | J103: 111638.94 | L103: 位军浩
...

Sheet 营业额导入核验
A1: 营业额导入核验（纯函数）
A3: 输出记录数 | B3: =ROWS('函数目标输出'!A4#)
A4: 正常 | B4: =COUNTIF(INDEX('函数目标输出'!A4#,0,1),"正常")
A5: 保留人工营业额 | B5: =COUNTIF(INDEX('函数目标输出'!A4#,0,1),"保留人工录入")
A6: 待核验 | B6: =COUNTIF(INDEX('函数目标输出'!A4#,0,1),"待核验")
A7: 新增窗口 | B7: =COUNTIF(INDEX('函数目标输出'!A4#,0,1),"新增窗口")
A8: 责任人变更 | B8: =COUNTIF(INDEX('函数目标输出'!A4#,0,1),"新增（责任人变更）")
A10: 明细：点击“数据源行”跳转到本文件内的营业额数据源。
A12: 状态 | B12: 数据源行（点击跳转） | C12: 标记 | D12: 档口唯一标志 | E12: 分部名称 | F12: 项目代码 | G12: 项目名称 | H12: 项目类型 | I12: 分组作业名称 | J12: 分组作业窗口名称 | K12: 责任人 | L12: 当月营业额 | M12: 说明
A13: =LET(x,'函数目标输出'!A4#,HSTACK(INDEX(x,,1),IF(INDEX(x,,2)="","",HYPERLINK("#'营业额数据源'!A"&INDEX(x,,2),INDEX(x,,2))),DROP(x,,3)))

Sheet 人工营业额覆盖
A1: 人工营业额覆盖（优先级高于数据源；仅维护经确认的例外）
A3: 项目代码 | B3: 项目名称 | C3: 分组作业名称 | D3: 分组作业窗口名称 | E3: 责任人 | F3: 营业额覆盖 | G3: 覆盖原因
A4: CF699 | B4: 徐医大第一食堂 | C4: / | D4: 麻辣烫 | E4: 董浩 | F4: 3358.13 | G4: 原模板人工营业额，已预置
A5: CF699 | B5: 徐医大第一食堂 | C5: / | D5: 脆香鸡 | E5: 闫玉净 | F5: 6538.5 | G5: 原模板人工营业额，已预置
A6: CF699 | B6: 徐医大第一食堂 | C6: / | D6: 鸡柳窜巷 | E6: 王晨 | F6: 0 | G6: 原模板人工营业额，已预置
A7: CF699 | B7: 徐医大第一食堂 | C7: / | D7: 螺蛳粉 | E7: 王梅 | F7: 6169.68 | G7: 原模板人工营业额，已预置
A8: CF699 | B8: 徐医大第一食堂 | C8: / | D8: 苏式汤面 | E8: 刘行行 | F8: 5915.21 | G8: 原模板人工营业额，已预置
A9: CF699 | B9: 徐医大第一食堂 | C9: / | D9: 营养粥 | E9: 周冰 | F9: 3626.3 | G9: 原模板人工营业额，已预置
A10: CF699 | B10: 徐医大第一食堂 | C10: / | D10: 辣椒炒肉 | E10: 王桐 | F10: 4097.2 | G10: 原模板人工营业额，已预置
A11: CF699 | B11: 徐医大第一食堂 | C11: / | D11: 板煮演义 | E11: 郑亚兰 | F11: 2538 | G11: 原模板人工营业额，已预置
A12: CF699 | B12: 徐医大第一食堂 | C12: / | D12: 老翟板面 | E12: 经蕊蕊 | F12: 2745.4 | G12: 原模板人工营业额，已预置
A13: CF699 | B13: 徐医大第一食堂 | C13: / | D13: 杂粮煎饼 | E13: 陈希广 | F13: 4510.1 | G13: 原模板人工营业额，已预置
A14: CF699 | B14: 徐医大第一食堂 | C14: / | D14: 早餐 | E14: 张召兵 | F14: 5714.25 | G14: 原模板人工营业额，已预置
A15: CF699 | B15: 徐医大第一食堂 | C15: / | D15: 快餐 | E15: 任现军 | F15: 0 | G15: 原模板人工营业额，已预置
... A29: CF478 | B29: 苏州华杨电子餐厅 | C29: / | D29: / | E29: 武良军 | F29: 177321 | G29: 原模板人工营业额，已预置
A30: CF700 | B30: 北理工长三角研究院(嘉兴）食堂 | C30: 自选快餐面条 | F30: 213402.66 | G30: 原模板人工营业额，已预置
A31: CF699 | B31: 徐医大第一食堂 | C31: / | D31: 快餐 | E31: 张振 | F31: 6859.1 | G31: 原模板人工营业额，已预置
A32: CF450 | B32: 天津大学学二食堂 | C32: / | D32: 牛肉面 | E32: 何元双 | F32: 16536 | G32: 原模板人工营业额，已预置
A33: CF699 | B33: 徐医大第一食堂 | C33: / | D33: 炸串卷饼拌饭 | E33: 王倩 | F33: 676.57 | G33: 原模板人工营业额，已预置
A34: CF699 | B34: 徐医大第一食堂 | C34: / | D34: 鸡架拌面 | E34: 姜艳芳 | F34: 2954.9 | G34: 原模板人工营业额，已预置

Sheet  2026年科桥餐饮公司各项指标明细
A1: 2026年科桥餐饮公司各项指标明细
A2: 序号 | B2: 档口唯一标志 | C2: 分部名称 | D2: 项目代码 | E2: 项目名称 | F2: 项目类型 | G2: 核算会计 | H2: 分组作业名称 | I2: 分组作业窗口名称 | J2: 签订人 （会议纪要） | K2: 人员工资 | L2: 营业额指标 【部分金额折算成一年】 | M2: 服务费 | N2: 虫害消杀 (按实） | O2: 采购费 （按实） | P2: 装修折旧费 (按实） | Q2: 管理人员费 （按实） | R2: 共建活动费 （按实） | S2: 资产费 （按实） | T2: 卫生费 （按实） | U2: 能源费 （按实） | V2: 其他 （按实） | W2: 原材料 （按实） | X2: 甲方管理费 （按实） | Y2: 甲方房租 | Z2: 甲方人员工资 | AA2: 甲方捐赠 | AB2: 分部管理费 （按实+固定值） | AC2: 业务费 | AD2: 备注1 | AE2: 备注2 | AF2: 难以落地条款
A3: 1 | B3: KQCY0001 | C3: 餐饮一分部 | D3: CF139 | E3: 苏州中科新药篮餐厅 | F3: 自营 | G3: 卫屹 | H3: / | I3: / | J3: / | K3: / | L3: 1900000 | M3: / | N3: / | O3: / | P3: / | Q3: / | R3: / | S3: / | T3: / | U3: / | V3: / | X3: / | Y3: / | Z3: / | AA3: / | AB3: 0.06 | AC3: /
A4: 2 | B4: KQCY0002 | C4: 餐饮一分部 | D4: CF481 | E4: 常熟世华高级中学食堂 | F4: 自营 | G4: 卫屹 | H4: / | I4: / | J4: / | K4: / | L4: 2600000 | M4: / | N4: / | O4: / | P4: / | Q4: / | R4: / | S4: / | T4: / | U4: / | V4: / | X4: / | Y4: / | Z4: / | AA4: / | AB4: 0.0585 | AC4: 0.005 | AD4: 1、原材料：若政府部门要求执行“阳光平台”的原材料比例，乙方实际经营中原材料比例与阳光平台规定比例的差额的处理和费用都由甲方承担。（阳光平台原材料占餐食营业额比例≥75%，项目按实际领用）
A5: 3 | B5: KQCY0003 | C5: 餐饮一分部 | D5: CF478 | E5: 苏州华杨电子餐厅 | F5: 强责 | G5: 陆琪 | H5: / | I5: / | J5: 武良军 | K5: / | L5: 2200000 | M5: / | N5: / | O5: 0.01 | P5: / | Q5: / | R5: / | S5: / | T5: / | U5: / | V5: / | X5: / | Y5: / | Z5: / | AA5: / | AB5: 0.04 | AC5: /
A6: 4 | B6: KQCY0004 | C6: 餐饮一分部 | D6: CF751 | E6: 国防科大（长沙）食堂 | F6: 人员服务外包 | G6: 陆琪 | H6: / | I6: / | J6: / | K6: / | L6: 8931000 | M6: / | N6: / | O6: / | P6: / | Q6: / | R6: / | S6: / | T6: / | U6: / | V6: / | W6: / | X6: / | Y6: / | Z6: / | AA6: / | AB6: 0.045 | AC6: /
A7: 5 | B7: KQCY0005 | C7: 餐饮一分部 | D7: CF474 | E7: 安工大七食堂 | F7: 强责 | G7: 卫屹 | H7: / | I7: / | J7: 李俊彦 | K7: / | L7: / | M7: / | N7: / | O7: / | P7: / | Q7: / | R7: / | S7: / | T7: / | U7: / | V7: / | W7: 0.55 | X7: / | Y7: / | Z7: / | AA7: / | AB7: 0.015 | AC7: / | AD7: 1、原材料：安徽工业大学食堂食品原材料定点采购办法约定食品原材料≥55%营业额（不含一次性打包用品）
A8: 6 | B8: KQCY0006 | C8: 餐饮一分部 | D8: CF474 | E8: 安工大七食堂 | F8: 强责 | G8: 卫屹 | H8: 第一班组 | I8: 手工馄饨（大陷水饺、刀削面/汆肉米线） | J8: 潘海英 | K8: / | L8: 700000 | M8: 0.07 | N8: 0.01 | O8: / | P8: 0.03 | Q8: 0.03 | R8: 0.01 | S8: 0.02 | T8: 0.04 | U8: 0.05 | V8: / | W8: 0.4 | X8: / | Y8: / | Z8: / | AA8: / | AB8: / | AC8: / | AD8: 1、甲方管理费：乙方自愿向甲方缴纳考核奖励资金，费用金额为29.5万元/年。一年按照10个月计算(2、8月份不计)，每月从餐厅营业款中扣除。服务费包含未拆分 2、甲方捐赠：助学基金5000元。服务费包含未拆分 3、原材料：安徽工业大学食堂食品原材料定点采购办法约定食品原材料≥55%营业额（不含一次性打包用品） | AF8: 1、会议纪要中约定了各项费用比例，但实际账务处理中未按照各费用比例分别收取； 建议：项目收支明细表按会议纪要签订的要求进行统计；
A9: 7 | B9: KQCY0007 | C9: 餐饮一分部 | D9: CF474 | E9: 安工大七食堂 | F9: 强责 | G9: 卫屹 | H9: 第二班组 | I9: 黄焖系列（酸菜肉煲系列、椒麻鸡系列、酸菜鱼系列） | J9: 胡科才 | K9: / | L9: 500000 | M9: 0.07 | N9: 0.01 | O9: / | P9: 0.03 | Q9: 0.03 | R9: 0.01 | S9: 0.02 | T9: 0.04 | U9: 0.05 | V9: / | W9: 0.4 | X9: / | Y9: / | Z9: / | AA9: / | AB9: / | AC9: / | AD9: 1、甲方管理费：乙方自愿向甲方缴纳考核奖励资金，费用金额为29.5万元/年。一年按照10个月计算(2、8月份不计)，每月从餐厅营业款中扣除。服务费包含未拆分 2、甲方捐赠：助学基金5000元。服务费包含未拆分 3、原材料：安徽工业大学食堂食品原材料定点采购办法约定食品原材料≥55%营业额（不含一次性打包用品） | AF9: 1、会议纪要中约定了各项费用比例，但实际账务处理中未按照各费用比例分别收取； 建议：项目收支明细表按会议纪要签订的要求进行统计；
A10: 8 | B10: KQCY0008 | C10: 餐饮一分部 | D10: CF474 | E10: 安工大七食堂 | F10: 强责 | G10: 卫屹 | H10: 第三班组 | I10: 猪脚饭系列（套饭系列、菜饭骨头汤系列） | J10: 杨克顺 | K10: / | L10: 700000 | M10: 0.07 | N10: 0.01 | O10: / | P10: 0.03 | Q10: 0.03 | R10: 0.01 | S10: 0.02 | T10: 0.04 | U10: 0.05 | V10: / | W10: 0.4 | X10: / | Y10: / | Z10: / | AA10: / | AB10: / | AC10: / | AD10: 1、甲方管理费：乙方自愿向甲方缴纳考核奖励资金，费用金额为29.5万元/年。一年按照10个月计算(2、8月份不计)，每月从餐厅营业款中扣除。服务费包含未拆分 2、甲方捐赠：助学基金5000元。服务费包含未拆分 3、原材料：安徽工业大学食堂食品原材料定点采购办法约定食品原材料≥55%营业额（不含一次性打包用品） | AF10: 1、会议纪要中约定了各项费用比例，但实际账务处理中未按照各费用比例分别收取； 建议：项目收支明细表按会议纪要签订的要求进行统计；
A11: 9 | B11: KQCY0009 | C11: 餐饮一分部 | D11: CF474 | E11: 安工大七食堂 | F11: 强责 | G11: 卫屹 | H11: 第四班组 | I11: 拌饭系列（肉夹馍、紫菜包饭） | J11: 魏祖华 | K11: / | L11: 700000 | M11: 0.07 | N11: 0.01 | O11: / | P11: 0.03 | Q11: 0.03 | R11: 0.01 | S11: 0.02 | T11: 0.04 | U11: 0.05 | V11: / | W11: 0.4 | X11: / | Y11: / | Z11: / | AA11: / | AB11: / | AC11: / | AD11: 1、甲方管理费：乙方自愿向甲方缴纳考核奖励资金，费用金额为29.5万元/年。一年按照10个月计算(2、8月份不计)，每月从餐厅营业款中扣除。服务费包含未拆分 2、甲方捐赠：助学基金5000元。服务费包含未拆分 3、原材料：安徽工业大学食堂食品原材料定点采购办法约定食品原材料≥55%营业额（不含一次性打包用品） | AF11: 1、会议纪要中约定了各项费用比例，但实际账务处理中未按照各费用比例分别收取； 建议：项目收支明细表按会议纪要签订的要求进行统计；
A12: 10 | B12: KQCY0010 | C12: 餐饮一分部 | D12: CF477 | E12: 上海民航第一食堂 | F12: 自营 | G12: 卫屹 | H12: / | I12: / | J12: / | K12: / | L12: / | M12: / | N12: / | O12: / | P12: / | Q12: / | R12: / | S12: / | T12: / | U12: / | V12: / | X12: / | Y12: / | Z12: / | AA12: / | AB12: 0.03 | AC12: /
A13: 11 | B13: KQCY0011 | C13: 餐饮一分部 | D13: CF477 | E13: 上海民航第一食堂 | F13: 分组作业 | G13: 卫屹 | H13: 第二班组 | I13: 山东煎饼 | J13: 姚群 | K13: / | L13: 570000 | M13: 0.1 | N13: 0.03 | O13: / | P13: 0.05 | Q13: 0.02 | R13: / | S13: 0.03 | T13: / | U13: 0.04 | V13: / | X13: / | Y13: / | Z13: / | AA13: / | AB13: / | AC13: / | AD13: 1、服务费：包含卫生费，不单独分摊 | AF13: 1、会议纪要中约定了各项费用比例，但实际账务处理中未按照各费用比例分别收取； 建议：项目收支明细表按会议纪要签订的要求进行统计；
A14: 12 | B14: KQCY0012 | C14: 餐饮一分部 | D14: CF477 | E14: 上海民航第一食堂 | F14: 分组作业 | G14: 卫屹 | H14: 第六班组 | I14: 蜜雪冰城 | J14: 任黎明 | K14: / | L14: 899800 | M14: / | N14: / | O14: / | P14: / | Q14: / | R14: / | S14: / | T14: / | U14: / | V14: 160000 | W14: / | X14: / | Y14: / | Z14: / | AA14: / | AB14: / | AC14: / | AD14: 1、其他：固定资金16万元/年
A15: 13 | B15: KQCY0013 | C15: 餐饮一分部 | D15: CF477 | E15: 上海民航第一食堂 | F15: 分组作业 | G15: 卫屹 | H15: 第三班组 | I15: 糖水粥铺 | J15: 孙青青 | K15: / | L15: 449900 | M15: 0.1 | N15: 0.03 | O15: / | P15: 0.05 | Q15: 0.02 | R15: / | S15: 0.03 | T15: / | U15: 0.04 | V15: / | X15: / | Y15: / | Z15: / | AA15: / | AB15: / | AC15: / | AD15: 1、服务费：包含卫生费，不单独分摊 | AF15: 1、会议纪要中约定了各项费用比例，但实际账务处理中未按照各费用比例分别收取； 建议：项目收支明细表按会议纪要签订的要求进行统计；
A16: 14 | B16: KQCY0014 | C16: 餐饮一分部 | D16: CF477 | E16: 上海民航第一食堂 | F16: 分组作业 | G16: 卫屹 | H16: 第四班组 | I16: 大碗面 | J16: 景帅帅 | K16: / | L16: 486500 | M16: 0.1 | N16: 0.03 | O16: / | P16: 0.05 | Q16: 0.02 | R16: / | S16: 0.03 | T16: / | U16: 0.04 | V16: / | X16: / | Y16: / | Z16: / | AA16: / | AB16: / | AC16: / | AD16: 1、服务费：包含卫生费，不单独分摊 | AF16: 1、条款：技术合作方所有人员与公司签订劳动合同，签订劳动合同的技术合作方负责人必须参加公司社保，否则不予录用； 问题：非所有分组作业人员都入职到公司，非所有负责人缴纳社保； 2、会议纪要中约定了各项费用比例，但实际账务处理中未按照各费用比例分别收取； 建议：项目收支明细表按会议纪要签订的要求进行统计；
A17: 15 | B17: KQCY0015 | C17: 餐饮一分部 | D17: CF477 | E17: 上海民航第一食堂 | F17: 分组作业 | G17: 卫屹 | H17: 第一班组 | I17: 早餐 | J17: 芦磊 | K17: / | L17: 628600 | M17: 0.1 | N17: 0.03 | O17: / | P17: 0.05 | Q17: 0.02 | R17: / | S17: 0.03 | T17: / | U17: / | V17: / | X17: / | Y17: / | Z17: / | AA17: / | AB17: / | AC17: / | AD17: 1、服务费：包含卫生费、能源费，不单独分摊 | AF17: 1、条款：技术合作方所有人员与公司签订劳动合同，签订劳动合同的技术合作方负责人必须参加公司社保，否则不予录用； 问题：非所有分组作业人员都入职到公司，非所有负责人缴纳社保； 2、会议纪要中约定了各项费用比例，但实际账务处理中未按照各费用比例分别收取； 建议：项目收支明细表按会议纪要签订的要求进行统计；
A18: 16 | C18: 餐饮一分部 | D18: CF272 | E18: 苏州工学院南一食堂 | F18: 强责 | G18: 位军浩 | H18: / | I18: / | J18: / | K18: / | L18: / | M18: / | Q18: / | R18: / | S18: / | X18: / | Y18: / | Z18: / | AA18: 350000 | AB18: 0.02 | AC18: / | AD18: 1、自营未实际经营；
A19: 17 | B19: KQCY0016 | C19: 餐饮一分部 | D19: CF272 | E19: 苏州工学院南一食堂 | F19: 强责 | G19: 位军浩 | H19: / | I19: 饼铺 | J19: 纪洪强 | K19: / | L19: 460000 | M19: 0.08 | N19: / | O19: / | P19: 0.065 | Q19: 0.02 | R19: 0.035 | S19: / | T19: 0.03 | U19: 0.06 | V19: / | X19: / | Y19: / | Z19: / | AA19: / | AB19: / | AC19: / | AD19: 1、甲方捐赠：35万/年，分组作业未分摊，服务费已包含； 2、采购费：1.35万/年，分组作业未分摊，服务费已包含； | AE19: 1、签订期间：2026.2.25-2026.7.19； 2、指标按照全年换算； | AF19: 1、会议纪要中约定了各项费用比例，但实际账务处理中未按照各费用比例分别收取； 建议：项目收支明细表按会议纪要签订的要求进行统计；
A20: 18 | B20: KQCY0017 | C20: 餐饮一分部 | D20: CF272 | E20: 苏州工学院南一食堂 | F20: 强责 | G20: 位军浩 | H20: / | I20: 粥铺 | J20: 贺明 | K20: / | L20: 384000 | M20: 0.08 | N20: / | O20: / | P20: 0.065 | Q20: 0.02 | R20: 0.035 | S20: / | T20: 0.03 | U20: 0.06 | V20: / | X20: / | Y20: / | Z20: / | AA20: / | AB20: / | AC20: / | AD20: 1、甲方捐赠：35万/年，分组作业未分摊，服务费已包含； 2、采购费：1.35万/年，分组作业未分摊，服务费已包含； | AE20: 1、签订期间：2026.2.25-2026.7.19； 2、指标按照全年换算； | AF20: 1、会议纪要中约定了各项费用比例，但实际账务处理中未按照各费用比例分别收取； 建议：项目收支明细表按会议纪要签订的要求进行统计；
A21: 19 | B21: KQCY0018 | C21: 餐饮一分部 | D21: CF272 | E21: 苏州工学院南一食堂 | F21: 强责 | G21: 位军浩 | H21: / | I21: 老乡邨 | J21: 刘少军 | K21: / | L21: 930000 | M21: 0.08 | N21: / | O21: / | P21: 0.065 | Q21: 0.02 | R21: 0.035 | S21: / | T21: 0.03 | U21: 0.06 | V21: / | X21: / | Y21: / | Z21: / | AA21: / | AB21: / | AC21: / | AD21: 1、甲方捐赠：35万/年，分组作业未分摊，服务费已包含； 2、采购费：1.35万/年，分组作业未分摊，服务费已包含； | AE21: 1、签订期间：2026.2.25-2026.7.19； 2、指标按照全年换算； | AF21: 1、会议纪要中约定了各项费用比例，但实际账务处理中未按照各费用比例分别收取； 建议：项目收支明细表按会议纪要签订的要求进行统计；
A22: 20 | B22: KQCY0019 | C22: 餐饮一分部 | D22: CF272 | E22: 苏州工学院南一食堂 | F22: 强责 | G22: 位军浩 | H22: / | I22: 科桥小厨 | J22: 吴浩 | K22: / | L22: 1280000 | M22: 0.06 | N22: / | O22: / | P22: 0.055 | Q22: 0.02 | R22: 0.025 | S22: / | T22: 0.03 | U22: 0.06 | V22: / | X22: / | Y22: / | Z22: / | AA22: / | AB22: / | AC22: / | AD22: 1、甲方捐赠：35万/年，分组作业未分摊，服务费已包含； 2、采购费：1.35万/年，分组作业未分摊，服务费已包含； | AE22: 1、签订期间：2026.2.25-2026.7.19； 2、指标按照全年换算； | AF22: 1、会议纪要中约定了各项费用比例，但实际账务处理中未按照各费用比例分别收取； 建议：项目收支明细表按会议纪要签订的要求进行统计；
A23: 21 | B23: KQCY0020 | C23: 餐饮一分部 | D23: CF272 | E23: 苏州工学院南一食堂 | F23: 强责 | G23: 位军浩 | H23: / | I23: 清汤米线 | J23: 张郁磊 | K23: / | L23: 264000 | M23: 0.08 | N23: / | O23: / | P23: 0.065 | Q23: 0.02 | R23: 0.035 | S23: / | T23: 0.03 | U23: 0.06 | V23: / | X23: / | Y23: / | Z23: / | AA23: / | AB23: / | AC23: / | AD23: 1、甲方捐赠：35万/年，分组作业未分摊，服务费已包含； 2、采购费：1.35万/年，分组作业未分摊，服务费已包含； | AE23: 1、签订期间：2026.2.25-2026.7.19； 2、指标按照全年换算； | AF23: 1、会议纪要中约定了各项费用比例，但实际账务处理中未按照各费用比例分别收取； 建议：项目收支明细表按会议纪要签订的要求进行统计；
A24: 22 | B24: KQCY0021 | C24: 餐饮一分部 | D24: CF272 | E24: 苏州工学院南一食堂 | F24: 强责 | G24: 位军浩 | H24: / | I24: 黑鸭堡 | J24: 张郁磊 | K24: / | L24: 290000 | M24: 0.08 | N24: / | O24: / | P24: 0.065 | Q24: 0.02 | R24: 0.035 | S24: / | T24: 0.03 | U24: 0.06 | V24: / | X24: / | Y24: / | Z24: / | AA24: / | AB24: / | AC24: / | AD24: 1、甲方捐赠：35万/年，分组作业未分摊，服务费已包含； 2、采购费：1.35万/年，分组作业未分摊，服务费已包含； | AE24: 1、签订期间：2026.2.25-2026.7.19； 2、指标按照全年换算； | AF24: 1、会议纪要中约定了各项费用比例，但实际账务处理中未按照各费用比例分别收取； 建议：项目收支明细表按会议纪要签订的要求进行统计；
A25: 23 | B25: KQCY0022 | C25: 餐饮一分部 | D25: CF272 | E25: 苏州工学院南一食堂 | F25: 强责 | G25: 位军浩 | H25: / | I25: 7分甜 | J25: 纪洪强 | K25: / | L25: 222000 | M25: / | N25: / | O25: / | P25: / | Q25: / | R25: / | S25: / | T25: / | V25: / | X25: / | Y25: / | Z25: / | AA25: / | AB25: / | AC25: / | AD25: 1、甲方捐赠：35万/年，分组作业未分摊，服务费已包含； 2、采购费：1.35万/年，分组作业未分摊，服务费已包含； | AE25: 1、签订期间：2026.2.25-2026.7.19； 2、指标按照全年换算；
A26: 24 | B26: KQCY0023 | C26: 餐饮一分部 | D26: CF272 | E26: 苏州工学院南一食堂 | F26: 强责 | G26: 位军浩 | H26: / | I26: 药膳鸡 | J26: 匡正娟 | K26: / | L26: 234000 | M26: / | N26: / | O26: / | P26: / | Q26: / | R26: / | S26: / | T26: 0.025 | U26: 0.055 | V26: / | X26: / | Y26: / | Z26: / | AA26: / | AB26: / | AC26: / | AD26: 1、甲方捐赠：35万/年，分组作业未分摊，服务费已包含； 2、采购费：1.35万/年，分组作业未分摊，服务费已包含； | AE26: 1、签订期间：2026.2.25-2026.7.19； 2、指标按照全年换算； | AF26: 1、会议纪要中约定了各项费用比例，但实际账务处理中未按照各费用比例分别收取； 建议：项目收支明细表按会议纪要签订的要求进行统计；
A27: 25 | B27: KQCY0024 | C27: 餐饮一分部 | D27: CF272 | E27: 苏州工学院南一食堂 | F27: 强责 | G27: 位军浩 | H27: / | I27: 麻辣香锅 | J27: 纪洪强 | K27: / | L27: 514000 | M27: 0.08 | N27: / | O27: / | P27: 0.065 | Q27: 0.02 | R27: 0.035 | S27: / | T27: 0.03 | U27: 0.06 | V27: / | X27: / | Y27: / | Z27: / | AA27: / | AB27: / | AC27: / | AD27: 1、甲方捐赠：35万/年，分组作业未分摊，服务费已包含； 2、采购费：1.35万/年，分组作业未分摊，服务费已包含； | AE27: 1、签订期间：2026.2.25-2026.7.19； 2、指标按照全年换算； | AF27: 1、会议纪要中约定了各项费用比例，但实际账务处理中未按照各费用比例分别收取； 建议：项目收支明细表按会议纪要签订的要求进行统计；
A28: 26 | B28: KQCY0025 | C28: 餐饮一分部 | D28: CF272 | E28: 苏州工学院南一食堂 | F28: 强责 | G28: 位军浩 | H28: / | I28: 生煎牛肉汤 | J28: 徐雪晗 | K28: / | L28: 316000 | M28: 0.08 | N28: / | O28: / | P28: 0.065 | Q28: 0.02 | R28: 0.035 | S28: / | T28: 0.03 | U28: 0.06 | V28: / | X28: / | Y28: / | Z28: / | AA28: / | AB28: / | AC28: / | AD28: 1、甲方捐赠：35万/年，分组作业未分摊，服务费已包含； 2、采购费：1.35万/年，分组作业未分摊，服务费已包含； | AE28: 1、签订期间：2026.2.25-2026.7.19； 2、指标按照全年换算； | AF28: 1、会议纪要中约定了各项费用比例，但实际账务处理中未按照各费用比例分别收取； 建议：项目收支明细表按会议纪要签订的要求进行统计；
A29: 27 | B29: KQCY0026 | C29: 餐饮一分部 | D29: CF272 | E29: 苏州工学院南一食堂 | F29: 强责 | G29: 位军浩 | H29: / | I29: 西式简餐 | J29: 李明发 | K29: / | L29: 310000 | M29: 0.08 | N29: / | O29: / | P29: 0.065 | Q29: 0.02 | R29: 0.035 | S29: / | T29: 0.03 | U29: 0.06 | V29: / | X29: / | Y29: / | Z29: / | AA29: / | AB29: / | AC29: / | AD29: 1、甲方捐赠：35万/年，分组作业未分摊，服务费已包含； 2、采购费：1.35万/年，分组作业未分摊，服务费已包含； | AE29: 1、签订期间：2026.2.25-2026.7.19； 2、指标按照全年换算； | AF29: 1、会议纪要中约定了各项费用比例，但实际账务处理中未按照各费用比例分别收取； 建议：项目收支明细表按会议纪要签订的要求进行统计；
A30: 28 | B30: KQCY0027 | C30: 餐饮一分部 | D30: CF272 | E30: 苏州工学院南一食堂 | F30: 强责 | G30: 位军浩 | H30: / | I30: 苏式面 | J30: 许正芳 | K30: / | L30: 530000 | M30: 0.08 | N30: / | O30: / | P30: 0.065 | Q30: 0.02 | R30: 0.035 | S30: / | T30: 0.03 | U30: 0.06 | V30: / | X30: / | Y30: / | Z30: / | AA30: / | AB30: / | AC30: / | AD30: 1、甲方捐赠：35万/年，分组作业未分摊，服务费已包含； 2、采购费：1.35万/年，分组作业未分摊，服务费已包含； | AE30: 1、签订期间：2026.2.25-2026.7.19； 2、指标按照全年换算； | AF30: 1、会议纪要中约定了各项费用比例，但实际账务处理中未按照各费用比例分别收取； 建议：项目收支明细表按会议纪要签订的要求进行统计；
A31: 29 | B31: KQCY0028 | C31: 餐饮一分部 | D31: CF272 | E31: 苏州工学院南一食堂 | F31: 强责 | G31: 位军浩 | H31: / | I31: 王记炒饭 | J31: 王梓骏 | K31: / | L31: 526000 | M31: 0.08 | N31: / | O31: / | P31: 0.065 | Q31: 0.02 | R31: 0.035 | S31: / | T31: 0.03 | U31: 0.06 | V31: / | X31: / | Y31: / | Z31: / | AA31: / | AB31: / | AC31: / | AD31: 1、甲方捐赠：35万/年，分组作业未分摊，服务费已包含； 2、采购费：1.35万/年，分组作业未分摊，服务费已包含； | AE31: 1、签订期间：2026.2.25-2026.7.19； 2、指标按照全年换算； | AF31: 1、会议纪要中约定了各项费用比例，但实际账务处理中未按照各费用比例分别收取； 建议：项目收支明细表按会议纪要签订的要求进行统计；
A32: 30 | B32: KQCY0029 | C32: 餐饮一分部 | D32: CF272 | E32: 苏州工学院南一食堂 | F32: 强责 | G32: 位军浩 | H32: / | I32: 烤鸭 | J32: 王鑫 | K32: / | L32: 530000 | M32: 0.08 | N32: / | O32: / | P32: 0.065 | Q32: 0.02 | R32: 0.035 | S32: / | T32: 0.03 | U32: 0.06 | V32: / | X32: / | Y32: / | Z32: / | AA32: / | AB32: / | AC32: / | AD32: 1、甲方捐赠：35万/年，分组作业未分摊，服务费已包含； 2、采购费：1.35万/年，分组作业未分摊，服务费已包含； | AE32: 1、签订期间：2026.2.25-2026.7.19； 2、指标按照全年换算； | AF32: 1、会议纪要中约定了各项费用比例，但实际账务处理中未按照各费用比例分别收取； 建议：项目收支明细表按会议纪要签订的要求进行统计；
A33: 31 | B33: KQCY0030 | C33: 餐饮一分部 | D33: CF272 | E33: 苏州工学院南一食堂 | F33: 强责 | G33: 位军浩 | H33: / | I33: 小街胡同牛杂面 | J33: 黄雨 | K33: / | L33: 360000 | M33: 0.08 | N33: / | O33: / | P33: 0.065 | Q33: 0.02 | R33: 0.035 | S33: / | T33: 0.03 | U33: 0.06 | V33: / | X33: / | Y33: / | Z33: / | AA33: / | AB33: / | AC33: / | AD33: 1、甲方捐赠：35万/年，分组作业未分摊，服务费已包含； 2、采购费：1.35万/年，分组作业未分摊，服务费已包含； | AE33: 1、签订期间：2026.2.25-2026.7.19； 2、指标按照全年换算； | AF33: 1、会议纪要中约定了各项费用比例，但实际账务处理中未按照各费用比例分别收取； 建议：项目收支明细表按会议纪要签订的要求进行统计；
A34: 32 | B34: KQCY0031 | C34: 餐饮一分部 | D34: CF272 | E34: 苏州工学院南一食堂 | F34: 强责 | G34: 位军浩 | H34: / | I34: 汉堡炸鸡 | J34: 陆林峰 | K34: / | L34: 366000 | M34: 0.08 | N34: / | O34: / | P34: 0.065 | Q34: 0.02 | R34: 0.035 | S34: / | T34: 0.03 | U34: 0.06 | V34: / | X34: / | Y34: / | Z34: / | AA34: / | AB34: / | AC34: / | AD34: 1、甲方捐赠：35万/年，分组作业未分摊，服务费已包含； 2、采购费：1.35万/年，分组作业未分摊，服务费已包含； | AE34: 1、签订期间：2026.2.25-2026.7.19； 2、指标按照全年换算； | AF34: 1、会议纪要中约定了各项费用比例，但实际账务处理中未按照各费用比例分别收取； 建议：项目收支明细表按会议纪要签订的要求进行统计；
A35: 33 | B35: KQCY0032 | C35: 餐饮一分部 | D35: CF272 | E35: 苏州工学院南一食堂 | F35: 强责 | G35: 位军浩 | H35: / | I35: 旋转小火锅 | J35: 潘祥 | K35: / | L35: 284000 | M35: 0.06 | N35: / | O35: / | P35: 0.065 | Q35: 0.02 | R35: 0.025 | S35: / | T35: 0.03 | U35: 0.06 | V35: / | X35: / | Y35: / | Z35: / | AA35: / | AB35: / | AC35: / | AD35: 1、甲方捐赠：35万/年，分组作业未分摊，服务费已包含； 2、采购费：1.35万/年，分组作业未分摊，服务费已包含； | AE35: 1、签订期间：2026.2.25-2026.7.19； 2、指标按照全年换算； 3、已撤场（2026年3月）； | AF35: 1、会议纪要中约定了各项费用比例，但实际账务处理中未按照各费用比例分别收取； 建议：项目收支明细表按会议纪要签订的要求进行统计；
A36: 34 | B36: KQCY0033 | C36: 餐饮一分部 | D36: CF127-1 | E36: 泰科老厂餐厅 | F36: 自营 | G36: 位军浩 | H36: / | I36: / | J36: / | K36: / | L36: 20350000 | M36: / | N36: / | O36: 0.02 | P36: / | Q36: / | R36: / | S36: / | T36: / | U36: / | V36: / | X36: / | Y36: / | Z36: / | AA36: / | AB36: 0.05 | AC36: /
A37: 35 | B37: KQCY0034 | C37: 餐饮一分部 | D37: CF127-3 | E37: 泰科新厂餐厅 | F37: 自营 | G37: 位军浩 | H37: / | I37: / | J37: / | K37: / | L37: 25000000 | M37: / | N37: / | O37: 0.02 | P37: / | Q37: / | R37: / | S37: / | T37: / | U37: / | V37: / | X37: / | Y37: / | Z37: / | AA37: / | AB37: 0.05 | AC37: /
A38: 36 | B38: KQCY0035 | C38: 餐饮一分部 | D38: CF141 | E38: 泰科阳澄湖工厂 | F38: 自营 | G38: 位军浩 | H38: / | I38: / | J38: / | K38: / | L38: 9507000 | M38: / | N38: / | O38: 0.02 | P38: / | Q38: / | R38: / | S38: / | T38: / | U38: / | V38: / | X38: / | Y38: / | Z38: / | AA38: / | AB38: 0.05 | AC38: /
A39: 37 | B39: KQCY0036 | C39: 餐饮一分部 | D39: CF129-1 | E39: 中央厨房（加工服务部） | F39: 自营 | G39: 位军浩 | H39: / | I39: / | J39: / | K39: / | L39: / | M39: / | N39: / | O39: 0.02 | P39: / | Q39: / | R39: / | S39: / | T39: / | U39: / | V39: / | X39: / | Y39: / | Z39: / | AA39: / | AB39: / | AC39: /
A40: 38 | B40: KQCY0037 | C40: 餐饮一分部 | D40: CF142 | E40: 卡特彼勒（吴江）餐厅 | F40: 自营 | G40: 位军浩 | H40: / | I40: / | J40: / | K40: / | L40: 3960000 | M40: / | N40: / | O40: 0.02 | P40: / | Q40: / | R40: / | S40: / | T40: / | U40: / | V40: / | X40: / | Y40: / | Z40: / | AA40: / | AB40: 0.05 | AC40: /
A41: 39 | B41: KQCY0038 | C41: 餐饮一分部 | D41: CF138 | E41: 苏州生物产业园三期餐厅 | F41: 自营 | G41: 位军浩 | H41: / | I41: / | J41: / | K41: / | L41: 2350000 | M41: / | N41: / | O41: 0.02 | P41: / | Q41: / | R41: / | S41: / | T41: / | U41: / | V41: / | X41: / | Y41: / | Z41: / | AA41: / | AB41: 0.06 | AC41: /
A42: 40 | B42: KQCY0039 | C42: 餐饮二分部 | D42: CF181 | E42: 中科大苏州研究院食堂 | F42: 自营 | G42: 吉沐牛 | H42: / | I42: / | J42: / | K42: / | L42: 1570000 | M42: / | N42: / | O42: / | P42: / | Q42: / | R42: / | S42: / | T42: / | U42: / | V42: / | W42: / | X42: / | Y42: / | Z42: / | AA42: / | AB42: 0.03 | AC42: /
A43: 41 | B43: KQCY0040 | C43: 餐饮二分部 | D43: CF124 | E43: 苏州评弹学院食堂 | F43: 自营 | G43: 吉沐牛 | H43: / | I43: / | J43: / | K43: / | L43: 2850000 | M43: / | N43: / | O43: / | P43: / | Q43: / | R43: / | S43: / | T43: / | U43: / | V43: / | W43: / | X43: / | Y43: / | Z43: / | AA43: / | AB43: 0.16 | AC43: /
A44: 42 | B44: KQCY0041 | C44: 餐饮二分部 | D44: CF125 | E44: 西浦大学宏愿食堂（南） | F44: 自营 | G44: 吉沐牛 | H44: / | I44: / | J44: / | K44: / | L44: / | M44: / | O44: 0.02 | Q44: / | R44: / | S44: / | V44: / | X44: 0.035 | Y44: / | Z44: / | AA44: / | AB44: 0.08 | AC44: /
A45: 43 | B45: KQCY0042 | C45: 餐饮二分部 | D45: CF125 | E45: 西浦大学宏愿食堂（南） | F45: 分组作业 | G45: 吉沐牛 | H45: / | I45: 麻辣烫 | J45: 何军军 | K45: / | L45: 850000 | M45: 0.12 | O45: 0.02 | P45: / | Q45: / | R45: / | S45: / | V45: / | W45: 0.2 | X45: 0.035 | Y45: / | Z45: / | AA45: / | AB45: / | AC45: / | AD45: 1、装修折旧费：项目反馈不收取，包含在服务费中； | AE45: 1、签订期间：2025.9-2026.8； 2、指标按照全年换算； | AF45: 1、会议纪要中未提及收取甲方管理费，实际是收取的，待明确； 建议：会议纪要中明确该条款；
A46: 44 | B46: KQCY0043 | C46: 餐饮二分部 | D46: CF125 | E46: 西浦大学宏愿食堂（南） | F46: 分组作业 | G46: 吉沐牛 | H46: / | I46: 小炒 | J46: 王成龙 | K46: / | L46: 1500000 | M46: 0.12 | O46: 0.02 | P46: / | Q46: / | R46: / | S46: / | V46: / | X46: 0.035 | Y46: / | Z46: / | AA46: / | AB46: / | AC46: / | AD46: 1、装修折旧费：项目反馈不收取，包含在服务费中； | AE46: 1、签订期间：2025.9-2026.8； 2、指标按照全年换算； | AF46: 1、会议纪要中未提及收取甲方管理费，实际是收取的，待明确； 建议：会议纪要中明确该条款；
A47: 45 | B47: KQCY0044 | C47: 餐饮二分部 | D47: CF125 | E47: 西浦大学宏愿食堂（南） | F47: 分组作业 | G47: 吉沐牛 | H47: / | I47: 枣糕 | J47: 杜松松 | K47: / | L47: 340000 | M47: 0.12 | O47: 0.02 | P47: / | Q47: / | R47: / | S47: / | V47: / | W47: 0.2 | X47: 0.035 | Y47: / | Z47: / | AA47: / | AB47: / | AC47: / | AD47: 1、装修折旧费：项目反馈不收取，包含在服务费中； | AE47: 1、签订期间：2025.9-2026.8； 2、指标按照全年换算； | AF47: 1、会议纪要中未提及收取甲方管理费，实际是收取的，待明确； 建议：会议纪要中明确该条款；
A48: 46 | B48: KQCY0045 | C48: 餐饮二分部 | D48: CF125 | E48: 西浦大学宏愿食堂（南） | F48: 分组作业 | G48: 吉沐牛 | H48: / | I48: 面条 | J48: 葛文静 | K48: / | L48: 365000 | M48: 0.12 | O48: 0.02 | P48: / | Q48: / | R48: / | S48: / | V48: / | W48: 0.2 | X48: 0.035 | Y48: / | Z48: / | AA48: / | AB48: / | AC48: / | AD48: 1、装修折旧费：项目反馈不收取，包含在服务费中； | AE48: 1、签订期间：2025.9-2026.8； 2、指标按照全年换算； | AF48: 1、会议纪要中未提及收取甲方管理费，实际是收取的，待明确； 建议：会议纪要中明确该条款；
A49: 47 | B49: KQCY0046 | C49: 餐饮二分部 | D49: CF125 | E49: 西浦大学宏愿食堂（南） | F49: 分组作业 | G49: 吉沐牛 | H49: / | I49: 烤肉 | J49: 杜松松 | K49: / | L49: 370000 | M49: 0.12 | O49: 0.02 | P49: / | Q49: / | R49: / | S49: / | V49: / | W49: 0.2 | X49: 0.035 | Y49: / | Z49: / | AA49: / | AB49: / | AC49: / | AD49: 1、装修折旧费：项目反馈不收取，包含在服务费中； | AE49: 1、签订期间：2025.9-2026.8； 2、指标按照全年换算； | AF49: 1、会议纪要中未提及收取甲方管理费，实际是收取的，待明确； 建议：会议纪要中明确该条款；
A50: 48 | B50: KQCY0047 | C50: 餐饮二分部 | D50: CF125 | E50: 西浦大学宏愿食堂（南） | F50: 分组作业 | G50: 吉沐牛 | H50: / | I50: 粉丝汤 | J50: 李鑫 | K50: / | L50: 440000 | M50: 0.12 | O50: 0.02 | P50: / | Q50: / | R50: / | S50: / | V50: / | W50: 0.2 | X50: 0.035 | Y50: / | Z50: / | AA50: / | AB50: / | AC50: / | AD50: 1、装修折旧费：项目反馈不收取，包含在服务费中； | AE50: 1、签订期间：2025.9-2026.8； 2、指标按照全年换算； | AF50: 1、会议纪要中未提及收取甲方管理费，实际是收取的，待明确； 建议：会议纪要中明确该条款；
A51: 49 | B51: KQCY0048 | C51: 餐饮二分部 | D51: CF137 | E51: 西浦大学宏愿食堂（北） | F51: 自营 | G51: 吉沐牛 | H51: / | I51: / | J51: / | K51: / | L51: / | M51: / | O51: 0.02 | Q51: / | R51: / | S51: / | V51: / | X51: / | Z51: / | AA51: / | AB51: 0.06 | AC51: /
A52: 50 | B52: KQCY0049 | C52: 餐饮二分部 | D52: CF137 | E52: 西浦大学宏愿食堂（北） | F52: 分组作业 | G52: 吉沐牛 | H52: / | I52: 滑蛋饭 | J52: 赵广伟 | K52: / | L52: 345000 | M52: 0.14 | N52: / | O52: 0.02 | P52: / | Q52: / | R52: / | S52: / | T52: 0.05 | U52: 0.06 | V52: 0.01 | W52: 0.2 | X52: / | Y52: / | Z52: / | AA52: / | AB52: / | AC52: / | AD52: 1、装修折旧费：项目反馈不收取，包含在服务费中； 2、甲方房租：项目反馈不收取，包含在服务费中； | AE52: 1、签订期间：2025.10-2026.9； 2、指标按照全年换算；
A53: 51 | B53: KQCY0050 | C53: 餐饮二分部 | D53: CF137 | E53: 西浦大学宏愿食堂（北） | F53: 分组作业 | G53: 吉沐牛 | H53: / | I53: 手工水饺 | J53: 赵玉才 | K53: / | L53: 475000 | M53: 0.14 | N53: / | O53: 0.02 | P53: / | Q53: / | R53: / | S53: / | T53: 0.05 | U53: 0.06 | V53: 0.01 | W53: 0.2 | X53: / | Y53: / | Z53: / | AA53: / | AB53: / | AC53: / | AD53: 1、装修折旧费：项目反馈不收取，包含在服务费中； 2、甲方房租：项目反馈不收取，包含在服务费中； | AE53: 1、签订期间：2025.10-2026.9； 2、指标按照全年换算；
A54: 52 | B54: KQCY0051 | C54: 餐饮二分部 | D54: CF137 | E54: 西浦大学宏愿食堂（北） | F54: 分组作业 | G54: 吉沐牛 | H54: / | I54: 烤盘饭 | J54: 付昌杰 | K54: / | L54: 875000 | M54: 0.14 | N54: / | O54: 0.02 | P54: / | Q54: / | R54: / | S54: / | T54: 0.05 | U54: 0.06 | V54: 0.01 | W54: 0.2 | X54: / | Y54: / | Z54: / | AA54: / | AB54: / | AC54: / | AD54: 1、装修折旧费：项目反馈不收取，包含在服务费中； 2、甲方房租：项目反馈不收取，包含在服务费中； | AE54: 1、签订期间：2025.10-2026.9； 2、指标按照全年换算；
A55: 53 | B55: KQCY0052 | C55: 餐饮二分部 | D55: CF137 | E55: 西浦大学宏愿食堂（北） | F55: 分组作业 | G55: 吉沐牛 | H55: / | I55: 大花米线 | J55: 钱卫军 | K55: / | L55: 485000 | M55: 0.14 | N55: / | O55: 0.02 | P55: / | Q55: / | R55: / | S55: / | T55: 0.05 | U55: 0.06 | V55: 0.01 | W55: 0.2 | X55: / | Y55: / | Z55: / | AA55: / | AB55: / | AC55: / | AD55: 1、装修折旧费：项目反馈不收取，包含在服务费中； 2、甲方房租：项目反馈不收取，包含在服务费中； | AE55: 1、签订期间：2025.10-2026.9； 2、指标按照全年换算；
A56: 54 | B56: KQCY0053 | C56: 餐饮二分部 | D56: CF137 | E56: 西浦大学宏愿食堂（北） | F56: 分组作业 | G56: 吉沐牛 | H56: / | I56: 石锅饭 | J56: 葛颖 | K56: / | L56: 600000 | M56: 0.14 | N56: / | O56: 0.02 | P56: / | Q56: / | R56: / | S56: / | T56: 0.05 | U56: 0.06 | V56: 0.01 | W56: 0.2 | X56: / | Y56: / | Z56: / | AA56: / | AB56: / | AC56: / | AD56: 1、装修折旧费：项目反馈不收取，包含在服务费中； 2、甲方房租：项目反馈不收取，包含在服务费中； | AE56: 1、签订期间：2025.10-2026.9； 2、指标按照全年换算；
A57: 55 | B57: KQCY0054 | C57: 餐饮二分部 | D57: CF137 | E57: 西浦大学宏愿食堂（北） | F57: 分组作业 | G57: 吉沐牛 | H57: / | I57: 一鸣鲜奶吧 | J57: 黎欢 | K57: / | L57: 615000 | M57: 120000 | N57: / | O57: / | P57: / | Q57: / | R57: / | S57: / | T57: 0.03 | U57: 0.05 | V57: 0.005 | X57: / | Y57: / | Z57: / | AA57: / | AB57: / | AC57: / | AD57: 1、服务费：12万/年； 2、采购费：项目反馈不收取，包含在服务费中； 3、装修折旧费：项目反馈不收取，包含在服务费中； 4、甲方房租：项目反馈不收取，包含在服务费中； | AE57: 1、签订期间：2025.10-2026.9； 2、指标按照全年换算；
A58: 56 | B58: KQCY0055 | C58: 餐饮二分部 | D58: CF140 | E58: 西浦大学太仓校区食堂 | F58: 自营 | G58: 吉沐牛 | H58: / | I58: / | J58: / | K58: / | L58: / | M58: / | O58: 0.02 | P58: / | Q58: / | R58: / | S58: / | U58: / | V58: / | X58: / | Y58: / | Z58: / | AA58: / | AB58: 0.04 | AC58: /
A59: 57 | B59: KQCY0056 | C59: 餐饮二分部 | D59: CF140 | E59: 西浦大学太仓校区食堂 | F59: 分组作业 | G59: 吉沐牛 | H59: 第一班组 | I59: 蛋包饭(肥牛米线、水饺、烤盘饭) | J59: 赵广伟 | K59: / | L59: 450000 | M59: 0.03 | N59: / | O59: 0.02 | P59: / | Q59: 0.03 | R59: / | S59: / | T59: / | U59: / | V59: / | W59: 0.2 | X59: / | Y59: / | Z59: / | AA59: / | AB59: / | AC59: / | AD59: 1、虫害消杀：项目反馈不收取，包含在服务费中； 2、卫生费：项目反馈不收取，包含在服务费中； | AE59: 1、签订期间：2025.9-2026.8； 2、指标按照全年换算；
A60: 58 | B60: KQCY0057 | C60: 餐饮二分部 | D60: CF140 | E60: 西浦大学太仓校区食堂 | F60: 分组作业 | G60: 吉沐牛 | H60: 第二班组 | I60: 枣糕&热饮(韩式拌饭) | J60: 杜松松 | K60: / | L60: 145000 | M60: 0.03 | N60: / | O60: 0.02 | P60: / | Q60: 0.03 | R60: / | S60: / | T60: / | U60: / | V60: / | W60: 0.2 | X60: / | Y60: / | Z60: / | AA60: / | AB60: / | AC60: / | AD60: 1、虫害消杀：项目反馈不收取，包含在服务费中； 2、卫生费：项目反馈不收取，包含在服务费中； | AE60: 1、签订期间：2025.9-2026.8； 2、指标按照全年换算；
A61: 59 | C61: 餐饮二分部 | D61: CF182 | E61: 无锡工艺第二食堂 | F61: 自营 | G61: 吉沐牛 | H61: / | I61: / | J61: / | K61: / | L61: / | M61: / | N61: / | O61: / | P61: / | Q61: / | R61: / | S61: / | T61: / | U61: / | V61: / | W61: / | X61: / | Y61: / | Z61: / | AA61: / | AB61: 0.035 | AC61: 0.005 | AD61: 1、自营未实际经营；
A62: 60 | B62: KQCY0058 | C62: 餐饮二分部 | D62: CF182 | E62: 无锡工艺第二食堂 | F62: 分组作业 | G62: 吉沐牛 | H62: / | I62: 快餐 | J62: 林建峰 | K62: / | L62: 6000000 | M62: 0.035 | O62: / | Q62: / | R62: / | S62: / | V62: / | W62: 47-53% | X62: / | Y62: / | Z62: / | AA62: / | AB62: / | AC62: / | AD62: 1、装修折旧费：按165万，分三年期限分摊，多退少补 | AE62: 1、签订期间：2026.1-2026.12； 2、指标按照全年换算；
A63: 61 | B63: KQCY0059 | C63: 餐饮二分部 | D63: CF360 | E63: 南通师专新校区食堂 | F63: 自营 | G63: 位军浩 | H63: / | I63: / | J63: / | K63: / | L63: / | M63: / | N63: / | O63: / | P63: / | Q63: / | R63: / | S63: / | T63: / | U63: / | V63: / | X63: / | Y63: / | Z63: / | AA63: / | AB63: 0.1 | AC63: /
A64: 62 | B64: KQCY0060 | C64: 餐饮二分部 | D64: CF360 | E64: 南通师专新校区食堂 | F64: 分组作业 | G64: 位军浩 | H64: 第一班组 | I64: 琳榆炸鸡腿 | J64: 王友强 | K64: / | L64: 800000 | M64: 0.2 | N64: / | O64: / | P64: / | Q64: / | R64: / | S64: / | T64: 0.03 | U64: 0.04 | V64: / | W64: 50%±3% | X64: / | Y64: / | Z64: / | AA64: / | AB64: / | AC64: / | AD64: 1、装修折旧费：25万/年，分组作业未分摊，服务费已包含 | AE64: 1、签订期间：2026.3.1-2026.7.31； 2、指标按照全年换算； | AF64: 1、条款：技术合作方严格按照所报备的原料比例执行，具体如下:50%±3%营业额，月度结算时若未达到所报比例，按以上比例结算。 问题：未达到比例时结算的比例需确认具体比例；原材料在实际经营过程中未按会议纪要要求达到比例；
A65: 63 | B65: KQCY0061 | C65: 餐饮二分部 | D65: CF360 | E65: 南通师专新校区食堂 | F65: 分组作业 | G65: 位军浩 | H65: 第二班组 | I65: 中式早点 | J65: 何小杏 | K65: / | L65: 880000 | M65: 0.18 | N65: / | O65: / | P65: / | Q65: / | R65: / | S65: / | T65: 0.02 | U65: 0.03 | V65: / | W65: 50%±3% | X65: / | Y65: / | Z65: / | AA65: / | AB65: / | AC65: / | AD65: 1、装修折旧费：25万/年，分组作业未分摊，服务费已包含 | AE65: 1、签订期间：2026.3.1-2026.7.31； 2、指标按照全年换算； | AF65: 1、条款：技术合作方严格按照所报备的原料比例执行，具体如下:50%±3%营业额，月度结算时若未达到所报比例，按以上比例结算。 问题：未达到比例时结算的比例需确认具体比例；原材料在实际经营过程中未按会议纪要要求达到比例；
A66: 64 | B66: KQCY0062 | C66: 餐饮二分部 | D66: CF360 | E66: 南通师专新校区食堂 | F66: 分组作业 | G66: 位军浩 | H66: 第三班组 | I66: 土耳其烤肉饭 | J66: 薛小勇 | K66: / | L66: 800000 | M66: 0.18 | N66: / | O66: / | P66: / | Q66: / | R66: / | S66: / | T66: 0.03 | U66: 0.03 | V66: / | W66: 50%±3% | X66: / | Y66: / | Z66: / | AA66: / | AB66: / | AC66: / | AD66: 1、装修折旧费：25万/年，分组作业未分摊，服务费已包含 | AE66: 1、签订期间：2026.3.1-2026.7.31； 2、指标按照全年换算； | AF66: 1、条款：技术合作方严格按照所报备的原料比例执行，具体如下:50%±3%营业额，月度结算时若未达到所报比例，按以上比例结算。 问题：未达到比例时结算的比例需确认具体比例；原材料在实际经营过程中未按会议纪要要求达到比例；
A67: 65 | B67: KQCY0063 | C67: 餐饮二分部 | D67: CF360 | E67: 南通师专新校区食堂 | F67: 分组作业 | G67: 位军浩 | H67: 第四班组 | I67: 营养粥小笼包 | J67: 沈玲 | K67: / | L67: 800000 | M67: 0.2 | N67: / | O67: / | P67: / | Q67: / | R67: / | S67: / | T67: 0.03 | U67: 0.04 | V67: / | W67: 50%±3% | X67: / | Y67: / | Z67: / | AA67: / | AB67: / | AC67: / | AD67: 1、装修折旧费：25万/年，分组作业未分摊，服务费已包含 | AE67: 1、签订期间：2026.3.1-2026.7.31； 2、指标按照全年换算； | AF67: 1、条款：技术合作方严格按照所报备的原料比例执行，具体如下:50%±3%营业额，月度结算时若未达到所报比例，按以上比例结算。 问题：未达到比例时结算的比例需确认具体比例；原材料在实际经营过程中未按会议纪要要求达到比例；
A68: 66 | B68: KQCY0064 | C68: 餐饮二分部 | D68: CF360 | E68: 南通师专新校区食堂 | F68: 分组作业 | G68: 位军浩 | H68: 第五班组 | I68: 生烫牛肉米线 | J68: 刘海霞 | K68: / | L68: 800000 | M68: 0.2 | N68: / | O68: / | P68: / | Q68: / | R68: / | S68: / | T68: 0.03 | U68: 0.04 | V68: / | W68: 50%±3% | X68: / | Y68: / | Z68: / | AA68: / | AB68: / | AC68: / | AD68: 1、装修折旧费：25万/年，分组作业未分摊，服务费已包含 | AE68: 1、签订期间：2026.3.1-2026.7.31； 2、指标按照全年换算； | AF68: 1、条款：技术合作方严格按照所报备的原料比例执行，具体如下:50%±3%营业额，月度结算时若未达到所报比例，按以上比例结算。 问题：未达到比例时结算的比例需确认具体比例；原材料在实际经营过程中未按会议纪要要求达到比例；
A69: 67 | B69: KQCY0065 | C69: 餐饮二分部 | D69: CF360 | E69: 南通师专新校区食堂 | F69: 分组作业 | G69: 位军浩 | H69: 第六班组 | I69: 咖喱蛋包饭 | J69: 余娇 | K69: / | L69: 800000 | M69: 0.2 | N69: / | O69: / | P69: / | Q69: / | R69: / | S69: / | T69: 0.03 | U69: 0.04 | V69: / | W69: 50%±3% | X69: / | Y69: / | Z69: / | AA69: / | AB69: / | AC69: / | AD69: 1、装修折旧费：25万/年，分组作业未分摊，服务费已包含 | AE69: 1、签订期间：2026.3.1-2026.7.31； 2、指标按照全年换算； | AF69: 1、条款：技术合作方严格按照所报备的原料比例执行，具体如下:50%±3%营业额，月度结算时若未达到所报比例，按以上比例结算。 问题：未达到比例时结算的比例需确认具体比例；原材料在实际经营过程中未按会议纪要要求达到比例；
A70: 68 | B70: KQCY0066 | C70: 餐饮二分部 | D70: CF360 | E70: 南通师专新校区食堂 | F70: 分组作业 | G70: 位军浩 | H70: 第七班组 | I70: 麻辣烫麻辣拌 | J70: 虞冬梅 | K70: / | L70: 800000 | M70: 0.18 | N70: / | O70: / | P70: / | Q70: / | R70: / | S70: / | T70: 0.03 | U70: 0.03 | V70: / | W70: 50%±3% | X70: / | Y70: / | Z70: / | AA70: / | AB70: / | AC70: / | AD70: 1、装修折旧费：25万/年，分组作业未分摊，服务费已包含 | AE70: 1、签订期间：2026.3.1-2026.7.31； 2、指标按照全年换算； | AF70: 1、条款：技术合作方严格按照所报备的原料比例执行，具体如下:50%±3%营业额，月度结算时若未达到所报比例，按以上比例结算。 问题：未达到比例时结算的比例需确认具体比例；原材料在实际经营过程中未按会议纪要要求达到比例；
A71: 69 | B71: KQCY0067 | C71: 餐饮二分部 | D71: CF360 | E71: 南通师专新校区食堂 | F71: 分组作业 | G71: 位军浩 | H71: 第八班组 | I71: 真老大手工云吞 | J71: 彭晴 | K71: / | L71: 800000 | M71: 0.2 | N71: / | O71: / | P71: / | Q71: / | R71: / | S71: / | T71: 0.03 | U71: 0.04 | V71: / | W71: 50%±3% | X71: / | Y71: / | Z71: / | AA71: / | AB71: / | AC71: / | AD71: 1、装修折旧费：25万/年，分组作业未分摊，服务费已包含 | AE71: 1、签订期间：2026.3.1-2026.7.31； 2、指标按照全年换算； | AF71: 1、条款：技术合作方严格按照所报备的原料比例执行，具体如下:50%±3%营业额，月度结算时若未达到所报比例，按以上比例结算。 问题：未达到比例时结算的比例需确认具体比例；原材料在实际经营过程中未按会议纪要要求达到比例；
A72: 70 | B72: KQCY0068 | C72: 餐饮二分部 | D72: CF360 | E72: 南通师专新校区食堂 | F72: 分组作业 | G72: 位军浩 | H72: 第九班组 | I72: 朱家小馆羊杂面 | J72: 薛桂中 | K72: / | L72: 960000 | M72: 0.2 | N72: / | O72: / | P72: / | Q72: / | R72: / | S72: / | T72: 0.03 | U72: 0.04 | V72: / | W72: 50%±3% | X72: / | Y72: / | Z72: / | AA72: / | AB72: / | AC72: / | AD72: 1、装修折旧费：25万/年，分组作业未分摊，服务费已包含 | AE72: 1、签订期间：2026.3.1-2026.7.31； 2、指标按照全年换算； | AF72: 1、条款：技术合作方严格按照所报备的原料比例执行，具体如下:50%±3%营业额，月度结算时若未达到所报比例，按以上比例结算。 问题：未达到比例时结算的比例需确认具体比例；原材料在实际经营过程中未按会议纪要要求达到比例；
A73: 71 | B73: KQCY0069 | C73: 餐饮二分部 | D73: CF360 | E73: 南通师专新校区食堂 | F73: 分组作业 | G73: 位军浩 | H73: 第十班组 | I73: 奶茶 | J73: 王艳 | K73: / | L73: 480000 | M73: 0.18 | N73: / | O73: / | P73: / | Q73: / | R73: / | S73: / | T73: / | V73: / | W73: 50%±3% | X73: / | Y73: / | Z73: / | AA73: / | AB73: / | AC73: / | AD73: 1、装修折旧费：25万/年，分组作业未分摊，服务费已包含； 2、卫生费：分组作业不在食堂内，未分摊，服务费已包含； | AE73: 1、签订期间：2026.3.1-2026.7.31； 2、指标按照全年换算； | AF73: 1、条款：技术合作方严格按照所报备的原料比例执行，具体如下:50%±3%营业额，月度结算时若未达到所报比例，按以上比例结算。 问题：未达到比例时结算的比例需确认具体比例；原材料在实际经营过程中未按会议纪要要求达到比例；
A74: 72 | B74: KQCY0070 | C74: 餐饮二分部 | D74: CF364 | E74: 江苏航运思本轩食堂 | F74: 自营 | G74: 位军浩 | H74: / | I74: / | J74: / | K74: / | L74: / | M74: / | N74: / | O74: / | P74: / | Q74: / | R74: / | S74: / | T74: / | U74: / | V74: / | X74: / | Y74: / | Z74: / | AA74: / | AB74: 0.05 | AC74: /
A75: 73 | B75: KQCY0071 | C75: 餐饮二分部 | D75: CF364 | E75: 江苏航运思本轩食堂 | F75: 分组作业 | G75: 位军浩 | H75: 第一班组 | I75: 快餐 | J75: 王瑞连 | K75: / | L75: 1330000 | M75: 0.12 | N75: 0.01 | P75: 0.01 | Q75: 0.01 | R75: 0.01 | S75: 0.02 | T75: 0.02 | U75: 0.02 | V75: / | X75: 0.03 | Y75: / | AA75: / | AB75: / | AC75: / | AD75: 1、甲方管理费：甲方每月按上月营业额的2%暂扣考核返还金、按营业额的1%暂扣公共维修金，分组作业应分摊未分摊，已补分摊，服务费比例应做相应调整； 2、甲方捐赠：乙方承诺资助30000元/年，分组作业未分摊，服务费已包含； | AE75: 1、签订期间：2025.9.1-2026.8.31； 2、指标按照全年换算； 3、已撤场（2025年10月）；
A76: 74 | B76: KQCY0072 | C76: 餐饮二分部 | D76: CF364 | E76: 江苏航运思本轩食堂 | F76: 分组作业 | G76: 位军浩 | H76: 第二班组 | I76: 粉丝汤（牛肉、老母鸡、牛杂、拆骨） | J76: 满超 | K76: / | L76: 590000 | M76: 0.12 | N76: 0.01 | P76: 0.01 | Q76: 0.01 | R76: 0.01 | S76: 0.02 | V76: / | X76: 0.03 | Y76: / | AA76: / | AB76: / | AC76: / | AD76: 1、甲方管理费：甲方每月按上月营业额的2%暂扣考核返还金、按营业额的1%暂扣公共维修金，分组作业应分摊未分摊，已补分摊，服务费比例应做相应调整； 2、甲方捐赠：乙方承诺资助30000元/年，分组作业未分摊，服务费已包含； | AE76: 1、签订期间：2025.9.1-2026.8.31； 2、指标按照全年换算；
A77: 75 | B77: KQCY0073 | C77: 餐饮二分部 | D77: CF364 | E77: 江苏航运思本轩食堂 | F77: 分组作业 | G77: 位军浩 | H77: 第三班组 | I77: 拌饭（鸡腿饭、酸梅鸭饭） | J77: 唐德生 | K77: / | L77: 400000 | M77: 0.12 | N77: 0.01 | P77: 0.01 | Q77: 0.01 | R77: 0.01 | S77: 0.02 | T77: 0.03 | U77: 0.03 | V77: / | X77: 0.03 | Y77: / | AA77: / | AB77: / | AC77: / | AD77: 1、甲方管理费：甲方每月按上月营业额的2%暂扣考核返还金、按营业额的1%暂扣公共维修金，分组作业应分摊未分摊，已补分摊，服务费比例应做相应调整； 2、甲方捐赠：乙方承诺资助30000元/年，分组作业未分摊，服务费已包含； | AE77: 1、签订期间：2025.9.1-2026.8.31； 2、指标按照全年换算；
A78: 76 | B78: KQCY0074 | C78: 餐饮二分部 | D78: CF364 | E78: 江苏航运思本轩食堂 | F78: 分组作业 | G78: 位军浩 | H78: 第五班组 | I78: 早餐 | J78: 潘捷 | K78: / | L78: 240000 | M78: 0.05 | N78: 0.01 | P78: 0.01 | Q78: 0.01 | R78: 0.01 | S78: 0.01 | V78: / | X78: 0.03 | Y78: / | AA78: / | AB78: / | AC78: / | AD78: 1、甲方管理费：甲方每月按上月营业额的2%暂扣考核返还金、按营业额的1%暂扣公共维修金，分组作业应分摊未分摊，已补分摊，服务费比例应做相应调整； 2、甲方捐赠：乙方承诺资助30000元/年，分组作业未分摊，服务费已包含； | AE78: 1、签订期间：2025.9.1-2026.8.31； 2、指标按照全年换算；
A79: 77 | B79: KQCY0075 | C79: 餐饮二分部 | D79: CF364 | E79: 江苏航运思本轩食堂 | F79: 分组作业 | G79: 位军浩 | H79: 第六班组 | I79: 咖喱饭 | J79: 余娇 | K79: / | L79: 325000 | M79: 0.12 | N79: 0.01 | P79: 0.01 | Q79: 0.01 | R79: 0.01 | S79: 0.02 | V79: / | X79: 0.03 | Y79: / | AA79: / | AB79: / | AC79: / | AD79: 1、甲方管理费：甲方每月按上月营业额的2%暂扣考核返还金、按营业额的1%暂扣公共维修金，分组作业应分摊未分摊，已补分摊，服务费比例应做相应调整； 2、甲方捐赠：乙方承诺资助30000元/年，分组作业未分摊，服务费已包含； | AE79: 1、签订期间：2025.9.1-2026.8.31； 2、指标按照全年换算； 3、已撤场（2025年12月）；
A80: 78 | B80: KQCY0076 | C80: 餐饮二分部 | D80: CF364 | E80: 江苏航运思本轩食堂 | F80: 分组作业 | G80: 位军浩 | H80: 第七班组 | I80: 锡纸饭 | J80: 陈芳 | K80: / | L80: 365000 | M80: 0.12 | N80: 0.01 | P80: 0.01 | Q80: 0.01 | R80: 0.01 | S80: 0.02 | V80: / | X80: 0.03 | Y80: / | AA80: / | AB80: / | AC80: / | AD80: 1、甲方管理费：甲方每月按上月营业额的2%暂扣考核返还金、按营业额的1%暂扣公共维修金，分组作业应分摊未分摊，已补分摊，服务费比例应做相应调整； 2、甲方捐赠：乙方承诺资助30000元/年，分组作业未分摊，服务费已包含； | AE80: 1、签订期间：2025.9.1-2026.8.31； 2、指标按照全年换算；
A81: 79 | B81: KQCY0077 | C81: 餐饮二分部 | D81: CF364 | E81: 江苏航运思本轩食堂 | F81: 分组作业 | G81: 位军浩 | H81: 第八班组 | I81: 生烫米线 | J81: 吴建军 | K81: / | L81: 420000 | M81: 0.12 | N81: 0.01 | P81: 0.01 | Q81: 0.01 | R81: 0.01 | S81: 0.02 | V81: / | X81: 0.03 | Y81: / | AA81: / | AB81: / | AC81: / | AD81: 1、甲方管理费：甲方每月按上月营业额的2%暂扣考核返还金、按营业额的1%暂扣公共维修金，分组作业应分摊未分摊，已补分摊，服务费比例应做相应调整； 2、甲方捐赠：乙方承诺资助30000元/年，分组作业未分摊，服务费已包含； | AE81: 1、签订期间：2025.9.1-2026.8.31； 2、指标按照全年换算； 3、已撤场（2025年11月）；
A82: 80 | B82: KQCY0078 | C82: 餐饮二分部 | D82: CF364 | E82: 江苏航运思本轩食堂 | F82: 分组作业 | G82: 位军浩 | H82: 第九班组 | I82: 水饺 | J82: 肖阿色 | K82: / | L82: 375000 | M82: 0.12 | N82: 0.01 | P82: 0.01 | Q82: 0.01 | R82: 0.01 | S82: 0.02 | V82: / | X82: 0.03 | Y82: / | AA82: / | AB82: / | AC82: / | AD82: 1、甲方管理费：甲方每月按上月营业额的2%暂扣考核返还金、按营业额的1%暂扣公共维修金，分组作业应分摊未分摊，已补分摊，服务费比例应做相应调整； 2、甲方捐赠：乙方承诺资助30000元/年，分组作业未分摊，服务费已包含； | AE82: 1、签订期间：2025.9.1-2026.8.31； 2、指标按照全年换算； 3、已撤场（2025年10月）；
A83: 81 | B83: KQCY0079 | C83: 餐饮二分部 | D83: CF364 | E83: 江苏航运思本轩食堂 | F83: 分组作业 | G83: 位军浩 | H83: 第十班组 | I83: 烤鸭饭 | J83: 蒋继承 | K83: / | L83: 1440000 | M83: 0.12 | N83: 0.01 | P83: 0.01 | Q83: 0.01 | R83: 0.01 | S83: 0.02 | T83: 0.03 | U83: 0.02 | V83: / | X83: 0.03 | Y83: / | AA83: / | AB83: / | AC83: / | AD83: 1、甲方管理费：甲方每月按上月营业额的2%暂扣考核返还金、按营业额的1%暂扣公共维修金，分组作业应分摊未分摊，已补分摊，服务费比例应做相应调整； 2、甲方捐赠：乙方承诺资助30000元/年，分组作业未分摊，服务费已包含； | AE83: 1、签订期间：2025.9.1-2026.8.31； 2、指标按照全年换算；
